Workbook

Sheet Dashboard
B1: FIRST ATLANTIC BANK LIMITED
B4: All amounts in thousands of GHS unless stated otherwise
B6: Recommendations
B8: Weighted Average | D8: Multiples Approach | H8: Dividend Discount Model Approach | L8: Residual Income Valuation Approach
B9: =IF($B$16<=-15%,"SELL",IF($B$16<=15%,"HOLD","BUY")) -> BUY | D9: =IF($F$16<=-15%,"SELL",IF($F$16<=15%,"HOLD","BUY")) -> BUY | H9: =IF($J$16<=-15%,"SELL",IF($J$16<=15%,"HOLD","BUY")) -> BUY | L9: =IF($N$16<=-15%,"SELL",IF($N$16<=15%,"HOLD","BUY")) -> BUY
B13: Valuation
B15: =Valuation!G88&" (GHS)" -> Weighted Price (GHS) | D15: =Valuation!B29&" (GHS)" -> Comparable Company Analysis (GHS) | H15: =Valuation!B56&" (GHS)" -> Dividend Discount Model (GHS) | L15: =Valuation!B71&" (GHS)" -> Residual Income Valuation (GHS)
B16: =Valuation!G93 -> 2.2779827 | F16: =Valuation!$F$89/Valuation!$D$10-1 -> 0.78270731 | J16: =Valuation!D68 -> 0.88857877 | N16: =Valuation!D84 -> 4.9641757
B24: Financial Highlights
F25: Income Statement | H25: =I25-1 -> 2024 | I25: =YEAR(Valuation!AB4) -> 2025 | J25: =YEAR(Valuation!AC4) -> 2026 | K25: =YEAR(Valuation!AD4) -> 2027 | L25: =YEAR(Valuation!AE4) -> 2028 | M25: =YEAR(Valuation!AF4) -> 2029 | N25: =YEAR(Valuation!AG4) -> 2030
F26: Net Interest Income | H26: ='Quarterly Historical Financials'!AI11 -> 576088 | I26: ='Quarterly Historical Financials'!AJ11+'Quarterly Financial Projections'!F10 -> 1542039.1 | J26: ='Quarterly Financial Projections'!AC10 -> 1209362.7 | K26: ='Quarterly Financial Projections'!AD10 -> 1470586.6 | L26: ='Quarterly Financial Projections'!AE10 -> 1779440.5 | M26: ='Quarterly Financial Projections'!AF10 -> 2144024.6 | N26: ='Quarterly Financial Projections'!AG10 -> 2573822.2
F27: Net Fees and Commission Income | H27: ='Quarterly Historical Financials'!AI14 -> 180198 | I27: ='Quarterly Historical Financials'!AJ14+'Quarterly Financial Projections'!F13 -> 223370.3 | J27: ='Quarterly Financial Projections'!AC13 -> 215487.73 | K27: ='Quarterly Financial Projections'!AD13 -> 245172.87 | L27: ='Quarterly Financial Projections'!AE13 -> 282278.94 | M27: ='Quarterly Financial Projections'!AF13 -> 325000.88 | N27: ='Quarterly Financial Projections'!AG13 -> 374188.64
F28: Net trading income | H28: ='Quarterly Historical Financials'!AI15 -> 335653 | I28: ='Quarterly Historical Financials'!AJ15+'Quarterly Financial Projections'!F14 -> 207164.61 | J28: ='Quarterly Financial Projections'!AC14 -> 94249.439 | K28: ='Quarterly Financial Projections'!AD14 -> 108513.77 | L28: ='Quarterly Financial Projections'!AE14 -> 124936.95 | M28: ='Quarterly Financial Projections'!AF14 -> 143845.73 | N28: ='Quarterly Financial Projections'!AG14 -> 165616.28
F29: Other income | H29: ='Quarterly Historical Financials'!AI16+'Quarterly Historical Financials'!AI26 -> 1240 | I29: ='Quarterly Historical Financials'!AJ16+'Quarterly Financial Projections'!F15+'Quarterly Historical Financials'!AJ26+'Quarterly Financial Projections'!F23 -> 4476.008 | J29: ='Quarterly Financial Projections'!AC15 -> 1758.4746 | K29: ='Quarterly Financial Projections'!AD15 -> 2088.663 | L29: ='Quarterly Financial Projections'!AE15 -> 2479.2579 | M29: ='Quarterly Financial Projections'!AF15 -> 2936.725 | N29: ='Quarterly Financial Projections'!AG15 -> 3472.0905
F30: Operating Income | H30: =SUM(H26:H29) -> 1093179 | I30: =SUM(I26:I29) -> 1977050 | J30: =SUM(J26:J29) -> 1520858.4 | K30: =SUM(K26:K29) -> 1826361.9 | L30: =SUM(L26:L29) -> 2189135.7 | M30: =SUM(M26:M29) -> 2615807.9 | N30: =SUM(N26:N29) -> 3117099.2
F31: Total Operating Expenses | H31: ='Quarterly Historical Financials'!AI25 -> -553877 | I31: ='Quarterly Historical Financials'!AJ25+'Quarterly Financial Projections'!F22 -> -942766.1 | J31: ='Quarterly Financial Projections'!AC22 -> -634559.42 | K31: ='Quarterly Financial Projections'!AD22 -> -764813.95 | L31: ='Quarterly Financial Projections'!AE22 -> -905564.61 | M31: ='Quarterly Financial Projections'!AF22 -> -1071996.2 | N31: ='Quarterly Financial Projections'!AG22 -> -1269078.9
F32: Profit before income tax | H32: =SUM(H30:H31) -> 539302 | I32: =SUM(I30:I31) -> 1034283.9 | J32: =SUM(J30:J31) -> 886298.96 | K32: =SUM(K30:K31) -> 1061547.9 | L32: =SUM(L30:L31) -> 1283571.1 | M32: =SUM(M30:M31) -> 1543811.7 | N32: =SUM(N30:N31) -> 1848020.3
F33: Total Taxes | H33: =SUM('Quarterly Historical Financials'!AI28:AI31) -> -202623 | I33: =SUM('Quarterly Historical Financials'!AJ28:AJ31)+'Quarterly Financial Projections'!F25 -> -321301.78 | J33: ='Quarterly Financial Projections'!AC25 -> -183038.96 | K33: ='Quarterly Financial Projections'!AD25 -> -219231.47 | L33: ='Quarterly Financial Projections'!AE25 -> -265083.81 | M33: ='Quarterly Financial Projections'!AF25 -> -318828.85 | N33: ='Quarterly Financial Projections'!AG25 -> -381654.19
F34: Profit for the period | H34: =SUM(H32:H33) -> 336679 | I34: =SUM(I32:I33) -> 712982.13 | J34: =SUM(J32:J33) -> 703260 | K34: =SUM(K32:K33) -> 842316.45 | L34: =SUM(L32:L33) -> 1018487.2 | M34: =SUM(M32:M33) -> 1224982.8 | N34: =SUM(N32:N33) -> 1466366.1
F35: Shares Outstanding | H35: ='Quarterly Historical Financials'!AI34 -> 334173.89 | I35: ='Quarterly Historical Financials'!AJ34 -> 349617.46 | J35: ='Quarterly Financial Projections'!AC28 -> 349617.46 | K35: ='Quarterly Financial Projections'!AD28 -> 349617.46 | L35: ='Quarterly Financial Projections'!AE28 -> 349617.46 | M35: ='Quarterly Financial Projections'!AF28 -> 349617.46 | N35: ='Quarterly Financial Projections'!AG28 -> 349617.46
F36: EPS | H36: =H34/H35 -> 1.0074964 | I36: =I34/I35 -> 2.0393207 | J36: =J34/J35 -> 2.0115128 | K36: =K34/K35 -> 2.4092517 | L36: =L34/L35 -> 2.9131475 | M36: =M34/M35 -> 3.5037804 | N36: =N34/N35 -> 4.1942016
F38: Operating Income Growth Rate | H38: =H30/'Quarterly Historical Financials'!AH17-1 -> 0.04607928 | I38: =I30/H30-1 -> 0.80853273 | J38: =J30/I30-1 -> -0.2307436 | K38: =K30/J30-1 -> 0.2008757 | L38: =L30/K30-1 -> 0.19863194 | M38: =M30/L30-1 -> 0.19490443 | N38: =N30/M30-1 -> 0.1916392
F39: Cost-to-Income Ratio | H39: =-H31/H30 -> 0.50666634 | I39: =-I31/I30 -> 0.47685496 | J39: =-J31/J30 -> 0.41723768 | K39: =-K31/K30 -> 0.41876364 | L39: =-L31/L30 -> 0.41366308 | M39: =-M31/M30 -> 0.40981458 | N39: =-N31/N30 -> 0.40713459
F40: Profit Margin | H40: =H34/H30 -> 0.30798158 | I40: =I34/I30 -> 0.36062928 | J40: =J34/J30 -> 0.46240992 | K40: =K34/K30 -> 0.4611991 | L40: =L34/L30 -> 0.46524629 | M40: =M34/M30 -> 0.46829999 | N40: =N34/N30 -> 0.47042651
F64: Statement of Financial Position | H64: =H25 -> 2024 | I64: =I25 -> 2025 | J64: =J25 -> 2026 | K64: =K25 -> 2027 | L64: =L25 -> 2028 | M64: =M25 -> 2029 | N64: =N25 -> 2030
F65: Cash and cash equivalents | H65: ='Quarterly Historical Financials'!AI41 -> 4600045 | I65: ='Quarterly Financial Projections'!AB33 -> 8162460.5 | J65: ='Quarterly Financial Projections'!AC33 -> 8156889.4 | K65: ='Quarterly Financial Projections'!AD33 -> 10125376 | L65: ='Quarterly Financial Projections'!AE33 -> 12467879 | M65: ='Quarterly Financial Projections'!AF33 -> 15249551 | N65: ='Quarterly Financial Projections'!AG33 -> 18546972
F66: Trading assets (Investment securities) | H66: ='Quarterly Historical Financials'!AI43 -> 2647258 | I66: ='Quarterly Financial Projections'!AB34 -> 3178870.4 | J66: ='Quarterly Financial Projections'!AC34 -> 4541640.6 | K66: ='Quarterly Financial Projections'!AD34 -> 5229002.2 | L66: ='Quarterly Financial Projections'!AE34 -> 6020393.7 | M66: ='Quarterly Financial Projections'!AF34 -> 6931559.6 | N66: ='Quarterly Financial Projections'!AG34 -> 7980627.2
F67: Loans and advances to customers | H67: ='Quarterly Historical Financials'!AI44 -> 1927368 | I67: ='Quarterly Financial Projections'!AB35 -> 1947024.8 | J67: ='Quarterly Financial Projections'!AC35 -> 3263912.3 | K67: ='Quarterly Financial Projections'!AD35 -> 3757894.1 | L67: ='Quarterly Financial Projections'!AE35 -> 4326638.5 | M67: ='Quarterly Financial Projections'!AF35 -> 4981460.3 | N67: ='Quarterly Financial Projections'!AG35 -> 5735387.1
F68: Other assets | H68: =SUM('Quarterly Historical Financials'!AI45:AI55) -> 4148654 | I68: =SUM('Quarterly Financial Projections'!AB36:AB44) -> 5904635.8 | J68: =SUM('Quarterly Financial Projections'!AC36:AC44) -> 6299904.1 | K68: =SUM('Quarterly Financial Projections'!AD36:AD44) -> 6725854.9 | L68: =SUM('Quarterly Financial Projections'!AE36:AE44) -> 7184882.8 | M68: =SUM('Quarterly Financial Projections'!AF36:AF44) -> 7679569.6 | N68: =SUM('Quarterly Financial Projections'!AG36:AG44) -> 8212699
F69: Total Assets | H69: =SUM(H65:H68) -> 13323325 | I69: =SUM(I65:I68) -> 19192992 | J69: =SUM(J65:J68) -> 22262346 | K69: =SUM(K65:K68) -> 25838127 | L69: =SUM(L65:L68) -> 29999794 | M69: =SUM(M65:M68) -> 34842141 | N69: =SUM(N65:N68) -> 40475685
F71: Total Deposits | H71: ='Quarterly Historical Financials'!AI59+'Quarterly Historical Financials'!AI60 -> 11611039 | I71: ='Quarterly Financial Projections'!AB48 -> 16642450 | J71: ='Quarterly Financial Projections'!AC48 -> 19161227 | K71: ='Quarterly Financial Projections'!AD48 -> 22061213 | L71: ='Quarterly Financial Projections'!AE48 -> 25400101 | M71: ='Quarterly Financial Projections'!AF48 -> 29244319 | N71: ='Quarterly Financial Projections'!AG48 -> 33670346
F72: Other liabilities | H72: =SUM('Quarterly Historical Financials'!AI61:AI64) -> 91644 | I72: =SUM('Quarterly Financial Projections'!AB49:AB51) -> 303306.12 | J72: =SUM('Quarterly Financial Projections'!AC49:AC51) -> 320819.02 | K72: =SUM('Quarterly Financial Projections'!AD49:AD51) -> 352380.3 | L72: =SUM('Quarterly Financial Projections'!AE49:AE51) -> 390686.15 | M72: =SUM('Quarterly Financial Projections'!AF49:AF51) -> 437177.86 | N72: =SUM('Quarterly Financial Projections'!AG49:AG51) -> 493604.73
F73: Lease liabilities | H73: ='Quarterly Historical Financials'!AI65 -> 23808 | I73: ='Quarterly Financial Projections'!AB52 -> 38841.151 | J73: ='Quarterly Financial Projections'!AC52 -> 55757.328 | K73: ='Quarterly Financial Projections'!AD52 -> 80040.874 | L73: ='Quarterly Financial Projections'!AE52 -> 114900.44 | M73: ='Quarterly Financial Projections'!AF52 -> 164942.11 | N73: ='Quarterly Financial Projections'!AG52 -> 236778.04
F74: Total Liabilities | H74: =SUM(H71:H73) -> 11726491 | I74: =SUM(I71:I73) -> 16984597 | J74: =SUM(J71:J73) -> 19537803 | K74: =SUM(K71:K73) -> 22493634 | L74: =SUM(L71:L73) -> 25905688 | M74: =SUM(M71:M73) -> 29846439 | N74: =SUM(N71:N73) -> 34400729
F76: Stated capital | H76: ='Quarterly Historical Financials'!AI69 -> 404570 | I76: ='Quarterly Financial Projections'!AB56 -> 727506.62 | J76: ='Quarterly Financial Projections'!AC56 -> 726051.15 | K76: ='Quarterly Financial Projections'!AD56 -> 726051.15 | L76: ='Quarterly Financial Projections'!AE56 -> 726051.15 | M76: ='Quarterly Financial Projections'!AF56 -> 726051.15 | N76: ='Quarterly Financial Projections'!AG56 -> 726051.15
F77: Retained earnings | H77: ='Quarterly Historical Financials'!AI70 -> 291090 | I77: ='Quarterly Financial Projections'!AB57 -> 454973.95 | J77: ='Quarterly Financial Projections'!AC57 -> 972577.78 | K77: ='Quarterly Financial Projections'!AD57 -> 1592528.1 | L77: ='Quarterly Financial Projections'!AE57 -> 2342141.1 | M77: ='Quarterly Financial Projections'!AF57 -> 3243736.3 | N77: ='Quarterly Financial Projections'!AG57 -> 4322991.1
F78: Reserves | H78: =SUM('Quarterly Historical Financials'!AI71:AI75) -> 901174 | I78: =SUM('Quarterly Financial Projections'!AB58:AB61) -> 1025914.1 | J78: =SUM('Quarterly Financial Projections'!AC58:AC61) -> 1025914.1 | K78: =SUM('Quarterly Financial Projections'!AD58:AD61) -> 1025914.1 | L78: =SUM('Quarterly Financial Projections'!AE58:AE61) -> 1025914.1 | M78: =SUM('Quarterly Financial Projections'!AF58:AF61) -> 1025914.1 | N78: =SUM('Quarterly Financial Projections'!AG58:AG61) -> 1025914.1
F79: Total Equity | H79: =SUM(H76:H78) -> 1596834 | I79: =SUM(I76:I78) -> 2208394.7 | J79: =SUM(J76:J78) -> 2724543 | K79: =SUM(K76:K78) -> 3344493.3 | L79: =SUM(L76:L78) -> 4094106.4 | M79: =SUM(M76:M78) -> 4995701.5 | N79: =SUM(N76:N78) -> 6074956.3
F81: Total Equity and Liabilities | H81: =H74+H79 -> 13323325 | I81: =I74+I79 -> 19192992 | J81: =J74+J79 -> 22262346 | K81: =K74+K79 -> 25838127 | L81: =L74+L79 -> 29999794 | M81: =M74+M79 -> 34842141 | N81: =N74+N79 -> 40475685
F82: Check | H82: =H69-H81 -> 0 | I82: =I69-I81 -> -0.001000002 | J82: =J69-J81 -> 0 | K82: =K69-K81 -> 0 | L82: =L69-L81 -> 0 | M82: =M69-M81 -> 0 | N82: =N69-N81 -> 0
F84: Loan-to-Deposit Ratio | H84: =H67/H71 -> 0.16599445 | I84: =I67/I71 -> 0.11699148 | J84: =J67/J71 -> 0.17033942 | K84: =K67/K71 -> 0.17033942 | L84: =L67/L71 -> 0.17033942 | M84: =M67/M71 -> 0.17033942 | N84: =N67/N71 -> 0.17033942
F85: Investment-to-Deposit Ratio | H85: =H66/H71 -> 0.22799493 | I85: =I66/I71 -> 0.19100976 | J85: =J66/J71 -> 0.23702243 | K85: =K66/K71 -> 0.23702243 | L85: =L66/L71 -> 0.23702243 | M85: =M66/M71 -> 0.23702243 | N85: =N66/N71 -> 0.23702243
F86: Return on Equity | H86: =H34/H79 -> 0.21084158 | I86: =I34/I79 -> 0.32285087 | J86: =J34/J79 -> 0.25812035 | K86: =K34/K79 -> 0.25185174 | L86: =L34/L79 -> 0.24876912 | M86: =M34/M79 -> 0.24520737 | N86: =N34/N79 -> 0.24137887
F87: Book Value of Equity per Share | H87: =H79/H35 -> 4.7784523 | I87: =I79/I35 -> 6.3166029 | J87: =J79/J35 -> 7.7929261 | K87: =K79/K35 -> 9.5661506 | L87: =L79/L35 -> 11.710246 | M87: =M79/M35 -> 14.28905 | N87: =N79/N35 -> 17.37601
F90: Statement of Cashflow | H90: =H64 -> 2024 | I90: =I64 -> 2025 | J90: =J64 -> 2026 | K90: =K64 -> 2027 | L90: =L64 -> 2028 | M90: =M64 -> 2029 | N90: =N64 -> 2030
F91: Cash generated from operating activities | H91: ='Raw Historical Financials'!V109 -> -661408.4 | I91: ='Raw Historical Financials'!Y109+'Quarterly Financial Projections'!F88 -> 3755857.8 | J91: ='Quarterly Financial Projections'!AC88 -> 372165.68 | K91: ='Quarterly Financial Projections'!AD88 -> 2409406.2 | L91: ='Quarterly Financial Projections'!AE88 -> 2858163.4 | M91: ='Quarterly Financial Projections'!AF88 -> 3384303.7 | N91: ='Quarterly Financial Projections'!AG88 -> 4001098.9
F92: Cash flows from investing activities | H92: ='Raw Historical Financials'!V116 -> -44329.016 | I92: ='Raw Historical Financials'!Y116+'Quarterly Financial Projections'!F96 -> -43928.495 | J92: ='Quarterly Financial Projections'!AC96 -> -34187.146 | K92: ='Quarterly Financial Projections'!AD96 -> -34561.874 | L92: ='Quarterly Financial Projections'!AE96 -> -34947.724 | M92: ='Quarterly Financial Projections'!AF96 -> -35345.115 | N92: ='Quarterly Financial Projections'!AG96 -> -35754.483
F93: Cash generated from financing activities | H93: ='Raw Historical Financials'!V122 -> -9526.9 | I93: ='Raw Historical Financials'!Y122+'Quarterly Financial Projections'!F106 -> -544052.36 | J93: ='Quarterly Financial Projections'!AC106 -> -185656.16 | K93: ='Quarterly Financial Projections'!AD106 -> -222366.18 | L93: ='Quarterly Financial Projections'!AE106 -> -268874.15 | M93: ='Quarterly Financial Projections'!AF106 -> -323387.67 | N93: ='Quarterly Financial Projections'!AG106 -> -387111.32
F94: Net increase/decrease in cash and cash equivalents | H94: =SUM(H91:H93) -> -715264.32 | I94: =SUM(I91:I93) -> 3167876.9 | J94: =SUM(J91:J93) -> 152322.37 | K94: =SUM(K91:K93) -> 2152478.2 | L94: =SUM(L91:L93) -> 2554341.5 | M94: =SUM(M91:M93) -> 3025570.9 | N94: =SUM(N91:N93) -> 3578233.1
F95: Adjustments | H95: ='Raw Historical Financials'!V126 -> -14059.403 | I95: ='Quarterly Financial Projections'!AB111-(I94+I96) -> 3009595.7 | J95: ='Quarterly Financial Projections'!AC109 -> -157893.51 | K95: ='Quarterly Financial Projections'!AD109 -> -183991.65 | L95: ='Quarterly Financial Projections'!AE109 -> -211838.15 | M95: ='Quarterly Financial Projections'!AF109 -> -243899.13 | N95: ='Quarterly Financial Projections'!AG109 -> -280812.42
F96: Cash and cash equivalents at start of period | H96: ='Raw Historical Financials'!V125 -> 2714311.6 | I96: =H97 -> 1984987.9 | J96: =I97 -> 8162460.5 | K96: =J97 -> 8156889.4 | L96: =K97 -> 10125376 | M96: =L97 -> 12467879 | N96: =M97 -> 15249551
F97: Cash and cash equivalents at end of period | H97: =SUM(H94:H96) -> 1984987.9 | I97: =SUM(I94:I96) -> 8162460.5 | J97: =SUM(J94:J96) -> 8156889.4 | K97: =SUM(K94:K96) -> 10125376 | L97: =SUM(L94:L96) -> 12467879 | M97: =SUM(M94:M96) -> 15249551 | N97: =SUM(N94:N96) -> 18546972

Sheet Valuation
B1: FIRST ATLANTIC BANK LIMITED
D2: Year | E2: =YEAR(E4) -> 2025 | F2: =YEAR(F4) -> 2025 | G2: =YEAR(G4) -> 2026 | H2: =YEAR(H4) -> 2026 | I2: =YEAR(I4) -> 2026 | J2: =YEAR(J4) -> 2026 | K2: =YEAR(K4) -> 2027 | L2: =YEAR(L4) -> 2027 | ... Z2: =YEAR(Z4) -> 2030 | AB2: =YEAR(AB4) -> 2025 | AC2: =YEAR(AC4) -> 2026 | AD2: =YEAR(AD4) -> 2027 | AE2: =YEAR(AE4) -> 2028 | AF2: =YEAR(AF4) -> 2029 | AG2: =YEAR(AG4) -> 2030
D3: Start Date | E3: ='Quarterly Historical Financials'!AB3 -> 45839 | F3: =E4+1 -> 45931 | G3: =F4+1 -> 46023 | H3: =G4+1 -> 46113 | I3: =H4+1 -> 46204 | J3: =I4+1 -> 46296 | K3: =J4+1 -> 46388 | L3: =K4+1 -> 46478 | M3: =L4+1 -> 46569 | ... Z3: =Y4+1 -> 47757 | AB3: =F3 -> 45931 | AC3: =AB4+1 -> 46023 | AD3: =AC4+1 -> 46388 | AE3: =AD4+1 -> 46753 | AF3: =AE4+1 -> 47119 | AG3: =AF4+1 -> 47484
D4: End Date | E4: =EOMONTH(E3,2) -> 45930 | F4: =EOMONTH(F3,2) -> 46022 | G4: =EOMONTH(G3,2) -> 46112 | H4: =EOMONTH(H3,2) -> 46203 | I4: =EOMONTH(I3,2) -> 46295 | J4: =EOMONTH(J3,2) -> 46387 | K4: =EOMONTH(K3,2) -> 46477 | L4: =EOMONTH(L3,2) -> 46568 | ... Z4: =EOMONTH(Z3,2) -> 47848 | AB4: =EOMONTH(AB3,2) -> 46022 | AC4: =EOMONTH(AC3,11) -> 46387 | AD4: =EOMONTH(AD3,11) -> 46752 | AE4: =EOMONTH(AE3,11) -> 47118 | AF4: =EOMONTH(AF3,11) -> 47483 | AG4: =EOMONTH(AG3,11) -> 47848
B5: All amounts in thousands of GHS unless stated otherwise | D5: Period | E5: =E4-E3+1 -> 92 | F5: =F4-F3+1 -> 92 | G5: =G4-G3+1 -> 90 | H5: =H4-H3+1 -> 91 | I5: =I4-I3+1 -> 92 | J5: =J4-J3+1 -> 92 | K5: =K4-K3+1 -> 90 | L5: =L4-L3+1 -> 91 | ... Z5: =Z4-Z3+1 -> 92 | AB5: =AB4-AB3+1 -> 92 | AC5: =AC4-AC3+1 -> 365 | AD5: =AD4-AD3+1 -> 365 | AE5: =AE4-AE3+1 -> 366 | AF5: =AF4-AF3+1 -> 365 | AG5: =AG4-AG3+1 -> 365
B7: Cost of Equity Calculation
B9: Date
B10: Current Share Price (GHS) | D10: =Comps!C61 -> 7.97
B11: Shares Outstanding | D11: ='Quarterly Financial Projections'!$F$28 -> 349617.46
B12: Market Capitalisation | D12: =D10*D11 -> 2786451.2
B14: Risk-free Rate | D14: 0.152
B15: Unlevered Beta | D15: 0.45
B16: Debt-to-Equity Ratio | D16: 0
B17: Levered Beta | D17: =D15*(1+((1+Assumptions!$I$115)*Valuation!D16)) -> 0.45
B18: Market Risk Premium | D18: 0.2665
B19: Country Risk Premium | D19: 0.0892
B20: Cost of Equity | D20: =D14+(D17*D18)+D19 -> 0.361125
B21: Quarterlized Cost of Equity | D21: =(1+D20)^(1/4)-1 -> 0.080126205
B24: Yearfrac | G24: =YEARFRAC(F4,G4) -> 0.25 | H24: =YEARFRAC(G4,H4) -> 0.25 | I24: =YEARFRAC(H4,I4) -> 0.25 | J24: =YEARFRAC(I4,J4) -> 0.25 | K24: =YEARFRAC(J4,K4) -> 0.25 | L24: =YEARFRAC(K4,L4) -> 0.25 | M24: =YEARFRAC(L4,M4) -> 0.25 | N24: =YEARFRAC(M4,N4) -> 0.25 | ... Z24: =YEARFRAC(Y4,Z4) -> 0.25 | AB24: =YEARFRAC(AB3,AB4) -> 0.25 | AC24: =YEARFRAC(AB4,AC4) -> 1 | AD24: =YEARFRAC(AC4,AD4) -> 1 | AE24: =YEARFRAC(AD4,AE4) -> 1 | AF24: =YEARFRAC(AE4,AF4) -> 1 | AG24: =YEARFRAC(AF4,AG4) -> 1
B25: Year | G25: =F25+G24 -> 0.25 | H25: =G25+H24 -> 0.5 | I25: =H25+I24 -> 0.75 | J25: =I25+J24 -> 1 | K25: =J25+K24 -> 1.25 | L25: =K25+L24 -> 1.5 | M25: =L25+M24 -> 1.75 | N25: =M25+N24 -> 2 | ... Z25: =Y25+Z24 -> 5 | AB25: =AB24 -> 0.25 | AC25: =AB25+AC24 -> 1.25 | AD25: =AC25+AD24 -> 2.25 | AE25: =AD25+AE24 -> 3.25 | AF25: =AE25+AF24 -> 4.25 | AG25: =AF25+AG24 -> 5.25
B26: Discount Factor | G26: =1/((1+$D$21)^(G25)) -> 0.980915 | H26: =1/((1+$D$21)^(H25)) -> 0.96219423 | I26: =1/((1+$D$21)^(I25)) -> 0.94383075 | J26: =1/((1+$D$21)^(J25)) -> 0.92581774 | K26: =1/((1+$D$21)^(K25)) -> 0.9081485 | L26: =1/((1+$D$21)^(L25)) -> 0.89081649 | M26: =1/((1+$D$21)^(M25)) -> 0.87381525 | N26: =1/((1+$D$21)^(N25)) -> 0.85713848 | ... Z26: =1/((1+$D$21)^(Z25)) -> 0.68018568 | AB26: =1/((1+$D$21)^(AB25)) -> 0.980915 | AC26: =1/((1+$D$21)^(AC25)) -> 0.9081485 | AD26: =1/((1+$D$21)^(AD25)) -> 0.84077999 | AE26: =1/((1+$D$21)^(AE25)) -> 0.77840903 | AF26: =1/((1+$D$21)^(AF25)) -> 0.72066489 | AG26: =1/((1+$D$21)^(AG25)) -> 0.66720434
B29: Comparable Company Analysis
B30: Industry Multiples | D30: AVG
B31: P/E | D31: =SUMIF(Comps!$C$15:$C$18,Valuation!$D$30,Comps!$AG$15:$AG$18) -> 8.8546999
B32: P/D | D32: =SUMIF(Comps!$C$15:$C$18,Valuation!$D$30,Comps!$AK$15:$AK$18) -> 0.28106015
B33: P/B | D33: =SUMIF(Comps!$C$15:$C$18,Valuation!$D$30,Comps!$AM$15:$AM$18) -> 1.712748
B35: Net Profit | F35: ='Quarterly Financial Projections'!F26 -> 230111.06 | G35: ='Quarterly Financial Projections'!G26 -> 171189.53 | H35: ='Quarterly Financial Projections'!H26 -> 168620.22 | I35: ='Quarterly Financial Projections'!I26 -> 177236.64 | J35: ='Quarterly Financial Projections'!J26 -> 186213.61 | K35: ='Quarterly Financial Projections'!K26 -> 195564.63 | L35: ='Quarterly Financial Projections'!L26 -> 205303.59 | M35: ='Quarterly Financial Projections'!M26 -> 215444.89 | ... Z35: ='Quarterly Financial Projections'!Z26 -> 391315.79 | AB35: =SUMIF($F$2:$Z$2,AB$2,$F35:$Z35) -> 230111.06 | AC35: =SUMIF($F$2:$Z$2,AC$2,$F35:$Z35) -> 703260 | AD35: =SUMIF($F$2:$Z$2,AD$2,$F35:$Z35) -> 842316.45 | AE35: =SUMIF($F$2:$Z$2,AE$2,$F35:$Z35) -> 1018487.2 | AF35: =SUMIF($F$2:$Z$2,AF$2,$F35:$Z35) -> 1224982.8 | AG35: =SUMIF($F$2:$Z$2,AG$2,$F35:$Z35) -> 1466366.1
B36: Total Deposits | F36: ='Quarterly Financial Projections'!F48 -> 16642450 | G36: ='Quarterly Financial Projections'!G48 -> 17239266 | H36: ='Quarterly Financial Projections'!H48 -> 17857485 | I36: ='Quarterly Financial Projections'!I48 -> 18497873 | J36: ='Quarterly Financial Projections'!J48 -> 19161227 | K36: ='Quarterly Financial Projections'!K48 -> 19848369 | L36: ='Quarterly Financial Projections'!L48 -> 20560153 | M36: ='Quarterly Financial Projections'!M48 -> 21297463 | ... Z36: ='Quarterly Financial Projections'!Z48 -> 33670346 | AB36: =SUMIF($F$4:$Z$4,AB$4,$F36:$Z36) -> 16642450 | AC36: =SUMIF($F$4:$Z$4,AC$4,$F36:$Z36) -> 19161227 | AD36: =SUMIF($F$4:$Z$4,AD$4,$F36:$Z36) -> 22061213 | AE36: =SUMIF($F$4:$Z$4,AE$4,$F36:$Z36) -> 25400101 | AF36: =SUMIF($F$4:$Z$4,AF$4,$F36:$Z36) -> 29244319 | AG36: =SUMIF($F$4:$Z$4,AG$4,$F36:$Z36) -> 33670346
B37: Total Equity | F37: ='Quarterly Financial Projections'!F62 -> 2208394.7 | G37: ='Quarterly Financial Projections'!G62 -> 2332935.8 | H37: ='Quarterly Financial Projections'!H62 -> 2457041.3 | I37: ='Quarterly Financial Projections'!I62 -> 2587488.6 | J37: ='Quarterly Financial Projections'!J62 -> 2724543 | K37: ='Quarterly Financial Projections'!K62 -> 2868479.8 | L37: ='Quarterly Financial Projections'!L62 -> 3019584.6 | M37: ='Quarterly Financial Projections'!M62 -> 3178153.4 | ... Z37: ='Quarterly Financial Projections'!Z62 -> 6074956.3 | AB37: =SUMIF($F$4:$Z$4,AB$4,$F37:$Z37) -> 2208394.7 | AC37: =SUMIF($F$4:$Z$4,AC$4,$F37:$Z37) -> 2724543 | AD37: =SUMIF($F$4:$Z$4,AD$4,$F37:$Z37) -> 3344493.3 | AE37: =SUMIF($F$4:$Z$4,AE$4,$F37:$Z37) -> 4094106.4 | AF37: =SUMIF($F$4:$Z$4,AF$4,$F37:$Z37) -> 4995701.5 | AG37: =SUMIF($F$4:$Z$4,AG$4,$F37:$Z37) -> 6074956.3
B38: Shares Outstanding | F38: ='Quarterly Financial Projections'!F28 -> 349617.46 | G38: ='Quarterly Financial Projections'!G28 -> 349617.46 | H38: ='Quarterly Financial Projections'!H28 -> 349617.46 | I38: ='Quarterly Financial Projections'!I28 -> 349617.46 | J38: ='Quarterly Financial Projections'!J28 -> 349617.46 | K38: ='Quarterly Financial Projections'!K28 -> 349617.46 | L38: ='Quarterly Financial Projections'!L28 -> 349617.46 | M38: ='Quarterly Financial Projections'!M28 -> 349617.46 | ... Z38: ='Quarterly Financial Projections'!Z28 -> 349617.46 | AB38: =SUMIF($F$4:$Z$4,AB$4,$F38:$Z38) -> 349617.46 | AC38: =SUMIF($F$4:$Z$4,AC$4,$F38:$Z38) -> 349617.46 | AD38: =SUMIF($F$4:$Z$4,AD$4,$F38:$Z38) -> 349617.46 | AE38: =SUMIF($F$4:$Z$4,AE$4,$F38:$Z38) -> 349617.46 | AF38: =SUMIF($F$4:$Z$4,AF$4,$F38:$Z38) -> 349617.46 | AG38: =SUMIF($F$4:$Z$4,AG$4,$F38:$Z38) -> 349617.46
B40: Discounted EPS | F40: =(F35/F$38) -> 0.65817955 | G40: =(G35/G$38)*G26 -> 0.48030319 | H40: =(H35/H$38)*H26 -> 0.46406549 | I40: =(I35/I$38)*I26 -> 0.47846977 | J40: =(J35/J$38)*J26 -> 0.49311 | K40: =(K35/K$38)*K26 -> 0.50798871 | L40: =(L35/L$38)*L26 -> 0.52310838 | M40: =(M35/M$38)*M26 -> 0.53847147 | N40: =(N35/N$38)*N26 -> 0.55408034 | ... Z40: =(Z35/Z$38)*Z26 -> 0.76131036 | AB40: =SUMIF($F$2:$Z$2,AB$2,$F40:$Z40) -> 0.65817955 | AC40: =SUMIF($F$2:$Z$2,AC$2,$F40:$Z40) -> 1.9159484 | AD40: =SUMIF($F$2:$Z$2,AD$2,$F40:$Z40) -> 2.1236489 | AE40: =SUMIF($F$2:$Z$2,AE$2,$F40:$Z40) -> 2.3774056 | AF40: =SUMIF($F$2:$Z$2,AF$2,$F40:$Z40) -> 2.6473799 | AG40: =SUMIF($F$2:$Z$2,AG$2,$F40:$Z40) -> 2.9340397
B41: Discounted DPS | F41: =(F36/F$38) -> 47.601883 | G41: =(G36/G$38)*G26 -> 48.367877 | H41: =(H36/H$38)*H26 -> 49.146197 | I41: =(I36/I$38)*I26 -> 49.937041 | J41: =(J36/J$38)*J26 -> 50.740612 | K41: =(K36/K$38)*K26 -> 51.557113 | L41: =(L36/L$38)*L26 -> 52.386753 | M41: =(M36/M$38)*M26 -> 53.229743 | N41: =(N36/N$38)*N26 -> 54.086299 | ... Z41: =(Z36/Z$38)*Z26 -> 65.506131 | AB41: =SUMIF($F$4:$Z$4,AB$4,$F41:$Z41) -> 47.601883 | AC41: =SUMIF($F$4:$Z$4,AC$4,$F41:$Z41) -> 50.740612 | AD41: =SUMIF($F$4:$Z$4,AD$4,$F41:$Z41) -> 54.086299 | AE41: =SUMIF($F$4:$Z$4,AE$4,$F41:$Z41) -> 57.65259 | AF41: =SUMIF($F$4:$Z$4,AF$4,$F41:$Z41) -> 61.454033 | AG41: =SUMIF($F$4:$Z$4,AG$4,$F41:$Z41) -> 65.506131
B42: Discounted BPS | F42: =(F37/F$38) -> 6.3166029 | G42: =(G37/G$38)*G26 -> 6.5454731 | H42: =(H37/H$38)*H26 -> 6.7621079 | I42: =(I37/I$38)*I26 -> 6.9852098 | J42: =(J37/J$38)*J26 -> 7.2148292 | K42: =(K37/K$38)*K26 -> 7.4510171 | L42: =(L37/L$38)*L26 -> 7.6938255 | M42: =(M37/M$38)*M26 -> 7.9433072 | N42: =(N37/N$38)*N26 -> 8.1995158 | ... Z42: =(Z37/Z$38)*Z26 -> 11.818913 | AB42: =SUMIF($F$4:$Z$4,AB$4,$F42:$Z42) -> 6.3166029 | AC42: =SUMIF($F$4:$Z$4,AC$4,$F42:$Z42) -> 7.2148292 | AD42: =SUMIF($F$4:$Z$4,AD$4,$F42:$Z42) -> 8.1995158 | AE42: =SUMIF($F$4:$Z$4,AE$4,$F42:$Z42) -> 9.2927125 | AF42: =SUMIF($F$4:$Z$4,AF$4,$F42:$Z42) -> 10.497971 | AG42: =SUMIF($F$4:$Z$4,AG$4,$F42:$Z42) -> 11.818913
B44: Rolling NTM Discounted EPS | F44: =SUM(F40:I40) -> 2.081018 | G44: =SUM(G40:J40) -> 1.9159484 | H44: =SUM(H40:K40) -> 1.943634 | I44: =SUM(I40:L40) -> 2.0026769 | J44: =SUM(J40:M40) -> 2.0626786 | K44: =SUM(K40:N40) -> 2.1236489 | L44: =SUM(L40:O40) -> 2.1855975 | M44: =SUM(M40:P40) -> 2.2485338 | ... W44: =SUM(W40:Z40) -> 2.9340397 | X44: =SUM(W40:Z40) -> 2.9340397 | Y44: =SUM(W40:Z40) -> 2.9340397 | Z44: =SUM(W40:Z40) -> 2.9340397 | AB44: =F44 -> 2.081018 | AC44: =AC40 -> 1.9159484 | AD44: =AD40 -> 2.1236489 | AE44: =AE40 -> 2.3774056 | AF44: =AF40 -> 2.6473799 | AG44: =AG40 -> 2.9340397
B45: Rolling NTM Discounted DPS | F45: =F41 -> 47.601883 | G45: =G41 -> 48.367877 | H45: =H41 -> 49.146197 | I45: =I41 -> 49.937041 | J45: =J41 -> 50.740612 | K45: =K41 -> 51.557113 | L45: =L41 -> 52.386753 | M45: =M41 -> 53.229743 | ... Z45: =Z41 -> 65.506131 | AB45: =AB41 -> 47.601883 | AC45: =AC41 -> 50.740612 | AD45: =AD41 -> 54.086299 | AE45: =AE41 -> 57.65259 | AF45: =AF41 -> 61.454033 | AG45: =AG41 -> 65.506131
B46: Rolling NTM Discounted BPS | F46: =F42 -> 6.3166029 | G46: =G42 -> 6.5454731 | H46: =H42 -> 6.7621079 | I46: =I42 -> 6.9852098 | J46: =J42 -> 7.2148292 | K46: =K42 -> 7.4510171 | L46: =L42 -> 7.6938255 | M46: =M42 -> 7.9433072 | ... Z46: =Z42 -> 11.818913 | AB46: =AB42 -> 6.3166029 | AC46: =AC42 -> 7.2148292 | AD46: =AD42 -> 8.1995158 | AE46: =AE42 -> 9.2927125 | AF46: =AF42 -> 10.497971 | AG46: =AG42 -> 11.818913
B49: Share Price
B50: P/E Approach | F50: =F44*$D31 -> 18.42679 | G50: =G44*$D31 -> 16.965148 | H50: =H44*$D31 -> 17.210295 | I50: =I44*$D31 -> 17.733103 | J50: =J44*$D31 -> 18.2644 | K50: =K44*$D31 -> 18.804274 | L50: =L44*$D31 -> 19.35281 | M50: =M44*$D31 -> 19.910092 | ... Z50: =Z44*$D31 -> 25.980041 | AB50: =AB44*$D31 -> 18.42679 | AC50: =AC44*$D31 -> 16.965148 | AD50: =AD44*$D31 -> 18.804274 | AE50: =AE44*$D31 -> 21.051213 | AF50: =AF44*$D31 -> 23.441755 | AG50: =AG44*$D31 -> 25.980041
B51: P/D Approach | F51: =F45*$D32 -> 13.378993 | G51: =G45*$D32 -> 13.594283 | H51: =H45*$D32 -> 13.813038 | I51: =I45*$D32 -> 14.035313 | J51: =J45*$D32 -> 14.261164 | K51: =K45*$D32 -> 14.49065 | L51: =L45*$D32 -> 14.723829 | M51: =M45*$D32 -> 14.96076 | ... Z51: =Z45*$D32 -> 18.411163 | AB51: =AB45*$D32 -> 13.378993 | AC51: =AC45*$D32 -> 14.261164 | AD51: =AD45*$D32 -> 15.201503 | AE51: =AE45*$D32 -> 16.203846 | AF51: =AF45*$D32 -> 17.27228 | AG51: =AG45*$D32 -> 18.411163
B52: P/B Approach | F52: =F46*$D33 -> 10.818749 | G52: =G46*$D33 -> 11.210746 | H52: =H46*$D33 -> 11.581787 | I52: =I46*$D33 -> 11.963904 | J52: =J46*$D33 -> 12.357185 | K52: =K46*$D33 -> 12.761715 | L52: =L46*$D33 -> 13.177585 | M52: =M46*$D33 -> 13.604884 | ... Z52: =Z46*$D33 -> 20.24282 | AB52: =AB46*$D33 -> 10.818749 | AC52: =AC46*$D33 -> 12.357185 | AD52: =AD46*$D33 -> 14.043705 | AE52: =AE46*$D33 -> 15.916075 | AF52: =AF46*$D33 -> 17.980379 | AG52: =AG46*$D33 -> 20.24282
B53: Average Price | F53: =AVERAGE(F50:F52) -> 14.208177 | G53: =AVERAGE(G50:G52) -> 13.923393 | H53: =AVERAGE(H50:H52) -> 14.201707 | I53: =AVERAGE(I50:I52) -> 14.57744 | J53: =AVERAGE(J50:J52) -> 14.960916 | K53: =AVERAGE(K50:K52) -> 15.352213 | L53: =AVERAGE(L50:L52) -> 15.751408 | M53: =AVERAGE(M50:M52) -> 16.158579 | ... Z53: =AVERAGE(Z50:Z52) -> 21.544675 | AB53: =AVERAGE(AB50:AB52) -> 14.208177 | AC53: =AVERAGE(AC50:AC52) -> 14.527832 | AD53: =AVERAGE(AD50:AD52) -> 16.016494 | AE53: =AVERAGE(AE50:AE52) -> 17.723711 | AF53: =AVERAGE(AF50:AF52) -> 19.564804 | AG53: =AVERAGE(AG50:AG52) -> 21.544675
B56: Dividend Discount Model
B57: Sustainable Growth Rate (g) | D57: 0.015
B58: Date | D58: 47848
B59: Dividend | F59: =-'Quarterly Financial Projections'!F105 -> 129654.12 | G59: =-'Quarterly Financial Projections'!G105 -> 45192.948 | H59: =-'Quarterly Financial Projections'!H105 -> 44514.664 | I59: =-'Quarterly Financial Projections'!I105 -> 46789.344 | J59: =-'Quarterly Financial Projections'!J105 -> 49159.209 | K59: =-'Quarterly Financial Projections'!K105 -> 51627.817 | L59: =-'Quarterly Financial Projections'!L105 -> 54198.842 | M59: =-'Quarterly Financial Projections'!M105 -> 56876.079 | ... Z59: =-'Quarterly Financial Projections'!Z105 -> 103304.88 | AB59: =SUMIF($F$2:$Z$2,AB$2,$F59:$Z59) -> 129654.12 | AC59: =SUMIF($F$2:$Z$2,AC$2,$F59:$Z59) -> 185656.16 | AD59: =SUMIF($F$2:$Z$2,AD$2,$F59:$Z59) -> 222366.18 | AE59: =SUMIF($F$2:$Z$2,AE$2,$F59:$Z59) -> 268874.15 | AF59: =SUMIF($F$2:$Z$2,AF$2,$F59:$Z59) -> 323387.67 | AG59: =SUMIF($F$2:$Z$2,AG$2,$F59:$Z59) -> 387111.32
B60: Discounted Dividend | F60: =F59 -> 129654.12 | G60: =G59*G26 -> 44330.44 | H60: =H59*H26 -> 42831.753 | I60: =I59*I26 -> 44161.221 | J60: =J59*J26 -> 45512.467 | K60: =K59*K26 -> 46885.724 | L60: =L59*L26 -> 48281.222 | M60: =M59*M26 -> 49699.185 | N60: =N59*N26 -> 51139.834 | ... Z60: =Z59*Z26 -> 70266.499 | AB60: =SUMIF($F$2:$Z$2,AB$2,$F60:$Z60) -> 129654.12 | AC60: =SUMIF($F$2:$Z$2,AC$2,$F60:$Z60) -> 176835.88 | AD60: =SUMIF($F$2:$Z$2,AD$2,$F60:$Z60) -> 196005.97 | AE60: =SUMIF($F$2:$Z$2,AE$2,$F60:$Z60) -> 219426.89 | AF60: =SUMIF($F$2:$Z$2,AF$2,$F60:$Z60) -> 244344.65 | AG60: =SUMIF($F$2:$Z$2,AG$2,$F60:$Z60) -> 270802.43
B61: Terminal Value | D61: =((SUMIF($AB$4:$AG$4,$D$58,$AB$59:$AG$59))*(1+$D$57))/($D$21-$D$57) -> 6033178.1
F62: Sensitivity Analysis - Cost of Equity vs Sustainable Growth Rate vs Share Price
B63: Sum of PVs of Dividends | D63: =SUM($F$60:$Z$60) -> 1237069.9 | G63: Cost of Equity
B64: PV of Terminal Value | D64: =D61*SUMIF($AB$4:$AG$4,$D$58,$AB$26:$AG$26) -> 4025362.6 | F64: Sustainable Growth Rate | G64: =D67 -> 15.051973 | H64: 0.020126205 | I64: 0.050126205 | J64: 0.080126205 | K64: 0.11012621 | L64: 0.14012621
B65: Equity Value | D65: =SUM(D63:D64) -> 5262432.5 | G65: 0.005 | H65: 70.369385 | I65: 22.880405 | J65: 13.421067 | K65: 9.4193931 | L65: 7.2316557
B66: Shares Outstanding | D66: =$F$38 -> 349617.46 | G66: 0.01 | H66: 103.57847 | I66: 25.363992 | J66: 14.178378 | K66: 9.7567748 | L66: 7.4119818
B67: Implied Share Price | D67: =D65/D66 -> 15.051973 | G67: 0.015 | H67: 201.57055 | I67: 28.554627 | J67: 15.051973 | K67: 10.129623 | L67: 7.6067194
B68: Potential | D68: =D67/$D$10-1 -> 0.88857877 | G68: 0.02 | H68: 8064.0703 | I68: 32.804351 | J68: 16.070861 | K68: 10.543841 | L68: 7.817668
G69: 0.025 | H69: -205.62258 | I69: 38.745427 | J69: 17.274578 | K69: 11.006719 | L69: 8.04694
B71: Residual Income Valuation
B72: Date | D72: 46022
B73: Book Value of Equity | D73: =SUMIF('Quarterly Financial Projections'!$E$4:$Z$4,Valuation!$D$72,'Quarterly Financial Projections'!$E$62:$Z$62) -> 2208394.7
B74: Residual Income | F74: ='Quarterly Financial Projections'!F26+'Quarterly Financial Projections'!F105 -> 100456.95 | G74: ='Quarterly Financial Projections'!G26+'Quarterly Financial Projections'!G105 -> 125996.59 | H74: ='Quarterly Financial Projections'!H26+'Quarterly Financial Projections'!H105 -> 124105.55 | I74: ='Quarterly Financial Projections'!I26+'Quarterly Financial Projections'!I105 -> 130447.29 | J74: ='Quarterly Financial Projections'!J26+'Quarterly Financial Projections'!J105 -> 137054.4 | K74: ='Quarterly Financial Projections'!K26+'Quarterly Financial Projections'!K105 -> 143936.81 | L74: ='Quarterly Financial Projections'!L26+'Quarterly Financial Projections'!L105 -> 151104.75 | M74: ='Quarterly Financial Projections'!M26+'Quarterly Financial Projections'!M105 -> 158568.81 | ... Z74: ='Quarterly Financial Projections'!Z26+'Quarterly Financial Projections'!Z105 -> 288010.91 | AB74: =SUMIF($F$2:$Z$2,AB$2,$F74:$Z74) -> 100456.95 | AC74: =SUMIF($F$2:$Z$2,AC$2,$F74:$Z74) -> 517603.84 | AD74: =SUMIF($F$2:$Z$2,AD$2,$F74:$Z74) -> 619950.27 | AE74: =SUMIF($F$2:$Z$2,AE$2,$F74:$Z74) -> 749613.09 | AF74: =SUMIF($F$2:$Z$2,AF$2,$F74:$Z74) -> 901595.16 | AG74: =SUMIF($F$2:$Z$2,AG$2,$F74:$Z74) -> 1079254.8
B75: Discounted Residual Income | F75: =F74 -> 100456.95 | G75: =G74*G26 -> 123591.94 | H75: =H74*H26 -> 119413.65 | I75: =I74*I26 -> 123120.16 | J75: =J74*J26 -> 126887.4 | K75: =K74*K26 -> 130716 | L75: =L74*L26 -> 134606.6 | M75: =M74*M26 -> 138559.84 | N75: =N74*N26 -> 142576.33 | ... Z75: =Z74*Z26 -> 195900.9 | AB75: =SUMIF($F$2:$Z$2,AB$2,$F75:$Z75) -> 100456.95 | AC75: =SUMIF($F$2:$Z$2,AC$2,$F75:$Z75) -> 493013.15 | AD75: =SUMIF($F$2:$Z$2,AD$2,$F75:$Z75) -> 546458.77 | AE75: =SUMIF($F$2:$Z$2,AE$2,$F75:$Z75) -> 611755.62 | AF75: =SUMIF($F$2:$Z$2,AF$2,$F75:$Z75) -> 681225.59 | AG75: =SUMIF($F$2:$Z$2,AG$2,$F75:$Z75) -> 754989.09
B76: Terminal Value of Residual Income | D76: =((SUMIF($AB$4:$AG$4,$D$58,$AB$74:$AG$74))*(1+$D$57))/($D$21-$D$57) -> 16820320
F77: Sensitivity Analysis - Cost of Equity vs Sustainable Growth Rate vs Share Price
B78: Book Value of Equity | D78: =D73 -> 2208394.7 | G78: Cost of Equity
B79: Sum of PVs of Residual Income | D79: =SUM($F$75:$Z$75) -> 3187899.2 | F79: Sustainable Growth Rate | G79: =D83 -> 47.53448 | H79: 0.020126205 | I79: 0.050126205 | J79: 0.080126205 | K79: 0.11012621 | L79: 0.14012621
B80: PV of Terminal Value | D80: =D76*SUMIF($AB$4:$AG$4,$D$58,$AB$26:$AG$26) -> 11222591 | G80: 0.005 | H80: 201.75777 | I80: 69.359914 | J80: 42.987564 | K80: 31.831017 | L80: 25.73167
B81: Equity Value | D81: =SUM(D78:D80) -> 16618884 | G81: 0.01 | H81: 294.34372 | I81: 76.284083 | J81: 45.098924 | K81: 32.771627 | L81: 26.234414
B82: Shares Outstanding | D82: =$F$38 -> 349617.46 | G82: 0.015 | H82: 567.54271 | I82: 85.179477 | J82: 47.53448 | K82: 33.811117 | L82: 26.777336
B83: Implied Share Price | D83: =D81/D82 -> 47.53448 | G83: 0.02 | H83: 22487.957 | I83: 97.027581 | J83: 50.37511 | K83: 34.965944 | L83: 27.365455
B84: Potential | D84: =D83/$D$10-1 -> 4.9641757 | G84: 0.025 | H84: -567.69956 | I84: 113.59112 | J84: 53.731036 | K84: 36.256433 | L84: 28.004658
B87: Weighted Average Price
E88: Weights | F88: Price | G88: Weighted Price
B89: Multiples Approach | E89: 0.35 | F89: =F53 -> 14.208177 | G89: =E89*F89 -> 4.972862
B90: Dividend Discount Model Approach | E90: 0.3 | F90: =D67 -> 15.051973 | G90: =E90*F90 -> 4.5155918
B91: Residual Income Valuation Approach | E91: =1-SUM(E89:E90) -> 0.35 | F91: =D83 -> 47.53448 | G91: =E91*F91 -> 16.637068
B92: Average Price | E92: =SUM(E89:E91) -> 1 | F92: =AVERAGE(F89:F91) -> 25.59821 | G92: =SUM(G89:G91) -> 26.125522
B93: Potential | F93: =F92/$D$10-1 -> 2.2118206 | G93: =G92/$D$10-1 -> 2.2779827

Sheet Quarterly Financial Projections
B1: FIRST ATLANTIC BANK LIMITED
D2: Year | E2: =YEAR(E4) -> 2025 | F2: =YEAR(F4) -> 2025 | G2: =YEAR(G4) -> 2026 | H2: =YEAR(H4) -> 2026 | I2: =YEAR(I4) -> 2026 | J2: =YEAR(J4) -> 2026 | K2: =YEAR(K4) -> 2027 | L2: =YEAR(L4) -> 2027 | ... Z2: =YEAR(Z4) -> 2030 | AB2: =YEAR(AB4) -> 2025 | AC2: =YEAR(AC4) -> 2026 | AD2: =YEAR(AD4) -> 2027 | AE2: =YEAR(AE4) -> 2028 | AF2: =YEAR(AF4) -> 2029 | AG2: =YEAR(AG4) -> 2030
D3: Start Date | E3: ='Quarterly Historical Financials'!AB3 -> 45839 | F3: =E4+1 -> 45931 | G3: =F4+1 -> 46023 | H3: =G4+1 -> 46113 | I3: =H4+1 -> 46204 | J3: =I4+1 -> 46296 | K3: =J4+1 -> 46388 | L3: =K4+1 -> 46478 | M3: =L4+1 -> 46569 | ... Z3: =Y4+1 -> 47757 | AB3: =E3 -> 45839 | AC3: =AB4+1 -> 46023 | AD3: =AC4+1 -> 46388 | AE3: =AD4+1 -> 46753 | AF3: =AE4+1 -> 47119 | AG3: =AF4+1 -> 47484
D4: End Date | E4: =EOMONTH(E3,2) -> 45930 | F4: =EOMONTH(F3,2) -> 46022 | G4: =EOMONTH(G3,2) -> 46112 | H4: =EOMONTH(H3,2) -> 46203 | I4: =EOMONTH(I3,2) -> 46295 | J4: =EOMONTH(J3,2) -> 46387 | K4: =EOMONTH(K3,2) -> 46477 | L4: =EOMONTH(L3,2) -> 46568 | ... Z4: =EOMONTH(Z3,2) -> 47848 | AB4: =EOMONTH(AB3,5) -> 46022 | AC4: =EOMONTH(AC3,11) -> 46387 | AD4: =EOMONTH(AD3,11) -> 46752 | AE4: =EOMONTH(AE3,11) -> 47118 | AF4: =EOMONTH(AF3,11) -> 47483 | AG4: =EOMONTH(AG3,11) -> 47848
B5: All amounts in thousands of GHS unless stated otherwise | D5: Period | E5: =E4-E3+1 -> 92 | F5: =F4-F3+1 -> 92 | G5: =G4-G3+1 -> 90 | H5: =H4-H3+1 -> 91 | I5: =I4-I3+1 -> 92 | J5: =J4-J3+1 -> 92 | K5: =K4-K3+1 -> 90 | L5: =L4-L3+1 -> 91 | ... Z5: =Z4-Z3+1 -> 92 | AB5: =AB4-AB3+1 -> 184 | AC5: =AC4-AC3+1 -> 365 | AD5: =AD4-AD3+1 -> 365 | AE5: =AE4-AE3+1 -> 366 | AF5: =AF4-AF3+1 -> 365 | AG5: =AG4-AG3+1 -> 365
B7: Income Statement
B8: Interest Income | E8: ='Quarterly Historical Financials'!AB9 -> 276147 | F8: ='Quarterly Historical Financials'!AC9 -> 681759.57 | G8: =Assumptions!N21 -> 384375.91 | H8: =Assumptions!O21 -> 402463.86 | I8: =Assumptions!P21 -> 421307.6 | J8: =Assumptions!Q21 -> 440936.87 | K8: =Assumptions!R21 -> 461382.59 | L8: =Assumptions!S21 -> 482676.87 | M8: =Assumptions!T21 -> 504853.07 | N8: =Assumptions!U21 -> 527945.88 | ... Z8: =Assumptions!AG21 -> 891213.25 | AB8: =SUMIF($E$2:$Z$2,AB$2,$E8:$Z8) -> 957906.57 | AC8: =SUMIF($E$2:$Z$2,AC$2,$E8:$Z8) -> 1649084.2 | AD8: =SUMIF($E$2:$Z$2,AD$2,$E8:$Z8) -> 1976858.4 | AE8: =SUMIF($E$2:$Z$2,AE$2,$E8:$Z8) -> 2362334.8 | AF8: =SUMIF($E$2:$Z$2,AF$2,$E8:$Z8) -> 2815137.9 | AG8: =SUMIF($E$2:$Z$2,AG$2,$E8:$Z8) -> 3346506.3
B9: Interest Expense | E9: ='Quarterly Historical Financials'!AB10 -> -138688 | F9: ='Quarterly Historical Financials'!AC10 -> -102371.52 | G9: =Assumptions!N29 -> -104190.6 | H9: =Assumptions!O29 -> -107926.99 | I9: =Assumptions!P29 -> -111797.37 | J9: =Assumptions!Q29 -> -115806.54 | K9: =Assumptions!R29 -> -119959.49 | L9: =Assumptions!S29 -> -124261.37 | M9: =Assumptions!T29 -> -128717.51 | N9: =Assumptions!U29 -> -133333.46 | ... Z9: =Assumptions!AG29 -> -203496.69 | AB9: =SUMIF($E$2:$Z$2,AB$2,$E9:$Z9) -> -241059.52 | AC9: =SUMIF($E$2:$Z$2,AC$2,$E9:$Z9) -> -439721.5 | AD9: =SUMIF($E$2:$Z$2,AD$2,$E9:$Z9) -> -506271.83 | AE9: =SUMIF($E$2:$Z$2,AE$2,$E9:$Z9) -> -582894.33 | AF9: =SUMIF($E$2:$Z$2,AF$2,$E9:$Z9) -> -671113.38 | AG9: =SUMIF($E$2:$Z$2,AG$2,$E9:$Z9) -> -772684.07
B10: Net Interest Income | E10: =SUM(E8:E9) -> 137459 | F10: =SUM(F8:F9) -> 579388.04 | G10: =SUM(G8:G9) -> 280185.31 | H10: =SUM(H8:H9) -> 294536.87 | I10: =SUM(I8:I9) -> 309510.23 | J10: =SUM(J8:J9) -> 325130.33 | K10: =SUM(K8:K9) -> 341423.1 | L10: =SUM(L8:L9) -> 358415.5 | ... Z10: =SUM(Z8:Z9) -> 687716.56 | AB10: =SUM(AB8:AB9) -> 716847.04 | AC10: =SUM(AC8:AC9) -> 1209362.7 | AD10: =SUM(AD8:AD9) -> 1470586.6 | AE10: =SUM(AE8:AE9) -> 1779440.5 | AF10: =SUM(AF8:AF9) -> 2144024.6 | AG10: =SUM(AG8:AG9) -> 2573822.2
B11: Fee and commission income | E11: ='Quarterly Historical Financials'!AB12 -> 80299 | F11: ='Quarterly Historical Financials'!AC12 -> 76446.237 | G11: =Assumptions!N39 -> 72259.202 | H11: =Assumptions!O39 -> 71258.687 | I11: =Assumptions!P39 -> 73814.101 | J11: =Assumptions!Q39 -> 76461.154 | K11: =Assumptions!R39 -> 79203.134 | L11: =Assumptions!S39 -> 82043.444 | M11: =Assumptions!T39 -> 84985.61 | N11: =Assumptions!U39 -> 88033.286 | ... Z11: =Assumptions!AG39 -> 134358.49 | AB11: =SUMIF($E$2:$Z$2,AB$2,$E11:$Z11) -> 156745.24 | AC11: =SUMIF($E$2:$Z$2,AC$2,$E11:$Z11) -> 293793.14 | AD11: =SUMIF($E$2:$Z$2,AD$2,$E11:$Z11) -> 334265.47 | AE11: =SUMIF($E$2:$Z$2,AE$2,$E11:$Z11) -> 384855.4 | AF11: =SUMIF($E$2:$Z$2,AF$2,$E11:$Z11) -> 443101.94 | AG11: =SUMIF($E$2:$Z$2,AG$2,$E11:$Z11) -> 510163.89
B12: Fee and commission expense | E12: ='Quarterly Historical Financials'!AB13 -> -22529 | F12: ='Quarterly Historical Financials'!AC13 -> -29426.085 | G12: =Assumptions!N44 -> -19259.425 | H12: =Assumptions!O44 -> -18992.755 | I12: =Assumptions!P44 -> -19673.856 | J12: =Assumptions!Q44 -> -20379.381 | K12: =Assumptions!R44 -> -21110.208 | L12: =Assumptions!S44 -> -21867.243 | M12: =Assumptions!T44 -> -22651.426 | N12: =Assumptions!U44 -> -23463.73 | ... Z12: =Assumptions!AG44 -> -35810.902 | AB12: =SUMIF($E$2:$Z$2,AB$2,$E12:$Z12) -> -51955.085 | AC12: =SUMIF($E$2:$Z$2,AC$2,$E12:$Z12) -> -78305.416 | AD12: =SUMIF($E$2:$Z$2,AD$2,$E12:$Z12) -> -89092.607 | AE12: =SUMIF($E$2:$Z$2,AE$2,$E12:$Z12) -> -102576.47 | AF12: =SUMIF($E$2:$Z$2,AF$2,$E12:$Z12) -> -118101.06 | AG12: =SUMIF($E$2:$Z$2,AG$2,$E12:$Z12) -> -135975.25
B13: Net Fees and Commission Income | E13: =SUM(E11:E12) -> 57770 | F13: =SUM(F11:F12) -> 47020.152 | G13: =SUM(G11:G12) -> 52999.777 | H13: =SUM(H11:H12) -> 52265.932 | I13: =SUM(I11:I12) -> 54140.245 | J13: =SUM(J11:J12) -> 56081.773 | K13: =SUM(K11:K12) -> 58092.926 | L13: =SUM(L11:L12) -> 60176.201 | ... Z13: =SUM(Z11:Z12) -> 98547.587 | AB13: =SUM(AB11:AB12) -> 104790.15 | AC13: =SUM(AC11:AC12) -> 215487.73 | AD13: =SUM(AD11:AD12) -> 245172.87 | AE13: =SUM(AE11:AE12) -> 282278.94 | AF13: =SUM(AF11:AF12) -> 325000.88 | AG13: =SUM(AG11:AG12) -> 374188.64
B14: Net trading income | E14: ='Quarterly Historical Financials'!AB15 -> 27893 | F14: ='Quarterly Historical Financials'!AC15 -> 46887.804 | G14: =Assumptions!N55 -> 22332.103 | H14: =Assumptions!O55 -> 23132.956 | I14: =Assumptions!P55 -> 23962.529 | J14: =Assumptions!Q55 -> 24821.851 | K14: =Assumptions!R55 -> 25711.99 | L14: =Assumptions!S55 -> 26634.049 | M14: =Assumptions!T55 -> 27589.175 | N14: =Assumptions!U55 -> 28578.553 | ... Z14: =Assumptions!AG55 -> 43617.265 | AB14: =SUMIF($E$2:$Z$2,AB$2,$E14:$Z14) -> 74780.804 | AC14: =SUMIF($E$2:$Z$2,AC$2,$E14:$Z14) -> 94249.439 | AD14: =SUMIF($E$2:$Z$2,AD$2,$E14:$Z14) -> 108513.77 | AE14: =SUMIF($E$2:$Z$2,AE$2,$E14:$Z14) -> 124936.95 | AF14: =SUMIF($E$2:$Z$2,AF$2,$E14:$Z14) -> 143845.73 | AG14: =SUMIF($E$2:$Z$2,AG$2,$E14:$Z14) -> 165616.28
B15: Other income | E15: ='Quarterly Historical Financials'!AB16 -> 673 | F15: ='Quarterly Historical Financials'!AC16 -> 326.388 | G15: =Assumptions!N64 -> 413.45079 | H15: =Assumptions!O64 -> 428.8922 | I15: =Assumptions!P64 -> 448.08032 | J15: =Assumptions!Q64 -> 468.05132 | K15: =Assumptions!R64 -> 488.83563 | L15: =Assumptions!S64 -> 510.46485 | M15: =Assumptions!T64 -> 532.97184 | N15: =Assumptions!U64 -> 556.39069 | ... Z15: =Assumptions!AG64 -> 922.938 | AB15: =SUMIF($E$2:$Z$2,AB$2,$E15:$Z15) -> 999.388 | AC15: =SUMIF($E$2:$Z$2,AC$2,$E15:$Z15) -> 1758.4746 | AD15: =SUMIF($E$2:$Z$2,AD$2,$E15:$Z15) -> 2088.663 | AE15: =SUMIF($E$2:$Z$2,AE$2,$E15:$Z15) -> 2479.2579 | AF15: =SUMIF($E$2:$Z$2,AF$2,$E15:$Z15) -> 2936.725 | AG15: =SUMIF($E$2:$Z$2,AG$2,$E15:$Z15) -> 3472.0905
B16: Operating Income | E16: =SUM(E10,E13:E15) -> 223795 | F16: =SUM(F10,F13:F15) -> 673622.39 | G16: =SUM(G10,G13:G15) -> 355930.64 | H16: =SUM(H10,H13:H15) -> 370364.65 | I16: =SUM(I10,I13:I15) -> 388061.08 | J16: =SUM(J10,J13:J15) -> 406502 | K16: =SUM(K10,K13:K15) -> 425716.85 | L16: =SUM(L10,L13:L15) -> 445736.22 | ... Z16: =SUM(Z10,Z13:Z15) -> 830804.35 | AB16: =SUM(AB10,AB13:AB15) -> 897417.39 | AC16: =SUM(AC10,AC13:AC15) -> 1520858.4 | AD16: =SUM(AD10,AD13:AD15) -> 1826361.9 | AE16: =SUM(AE10,AE13:AE15) -> 2189135.7 | AF16: =SUM(AF10,AF13:AF15) -> 2615807.9 | AG16: =SUM(AG10,AG13:AG15) -> 3117099.2
B17: Impairment losses on loans and advances | E17: ='Quarterly Historical Financials'!AB18 -> 46660 | F17: ='Quarterly Historical Financials'!AC18 -> -178305.4 | G17: =Assumptions!N91 -> -26006.504 | H17: =Assumptions!O91 -> -39223.326 | I17: =Assumptions!P91 -> -40629.917 | J17: =Assumptions!Q91 -> -42086.949 | K17: =Assumptions!R91 -> -43596.233 | L17: =Assumptions!S91 -> -45159.641 | M17: =Assumptions!T91 -> -46779.114 | N17: =Assumptions!U91 -> -48456.664 | ... Z17: =Assumptions!AG91 -> -73955.71 | AB17: =SUMIF($E$2:$Z$2,AB$2,$E17:$Z17) -> -131645.4 | AC17: =SUMIF($E$2:$Z$2,AC$2,$E17:$Z17) -> -147946.7 | AD17: =SUMIF($E$2:$Z$2,AD$2,$E17:$Z17) -> -183991.65 | AE17: =SUMIF($E$2:$Z$2,AE$2,$E17:$Z17) -> -211838.15 | AF17: =SUMIF($E$2:$Z$2,AF$2,$E17:$Z17) -> -243899.13 | AG17: =SUMIF($E$2:$Z$2,AG$2,$E17:$Z17) -> -280812.42
B18: Personnel expenses | E18: ='Quarterly Historical Financials'!AB20 -> -46163 | F18: ='Quarterly Historical Financials'!AC20 -> -119879.86 | G18: =Assumptions!N76 -> -57328.043 | H18: =Assumptions!O76 -> -59652.86 | I18: =Assumptions!P76 -> -62503.14 | J18: =Assumptions!Q76 -> -65473.331 | K18: =Assumptions!R76 -> -68568.174 | L18: =Assumptions!S76 -> -71792.597 | M18: =Assumptions!T76 -> -75151.721 | N18: =Assumptions!U76 -> -78650.866 | ... Z18: =Assumptions!AG76 -> -133813.68 | AB18: =SUMIF($E$2:$Z$2,AB$2,$E18:$Z18) -> -166042.86 | AC18: =SUMIF($E$2:$Z$2,AC$2,$E18:$Z18) -> -244957.37 | AD18: =SUMIF($E$2:$Z$2,AD$2,$E18:$Z18) -> -294163.36 | AE18: =SUMIF($E$2:$Z$2,AE$2,$E18:$Z18) -> -352593.6 | AF18: =SUMIF($E$2:$Z$2,AF$2,$E18:$Z18) -> -421315.65 | AG18: =SUMIF($E$2:$Z$2,AG$2,$E18:$Z18) -> -502056.24
B19: Depreciation and amortisation | E19: ='Quarterly Historical Financials'!AB21 -> -15613 | F19: ='Quarterly Historical Financials'!AC21 -> -18327.089 | G19: =Assumptions!N144+Assumptions!N153+Assumptions!N162 -> -7706.1292 | H19: =Assumptions!O144+Assumptions!O153+Assumptions!O162 -> -7725.7472 | I19: =Assumptions!P144+Assumptions!P153+Assumptions!P162 -> -7745.5043 | J19: =Assumptions!Q144+Assumptions!Q153+Assumptions!Q162 -> -7765.4018 | K19: =Assumptions!R144+Assumptions!R153+Assumptions!R162 -> -7785.441 | L19: =Assumptions!S144+Assumptions!S153+Assumptions!S162 -> -7805.6233 | M19: =Assumptions!T144+Assumptions!T153+Assumptions!T162 -> -7825.9499 | N19: =Assumptions!U144+Assumptions!U153+Assumptions!U162 -> -7846.4222 | ... Z19: =Assumptions!AG144+Assumptions!AG153+Assumptions!AG162 -> -8103.9576 | AB19: =SUMIF($E$2:$Z$2,AB$2,$E19:$Z19) -> -33940.089 | AC19: =SUMIF($E$2:$Z$2,AC$2,$E19:$Z19) -> -30942.782 | AD19: =SUMIF($E$2:$Z$2,AD$2,$E19:$Z19) -> -31263.436 | AE19: =SUMIF($E$2:$Z$2,AE$2,$E19:$Z19) -> -31593.373 | AF19: =SUMIF($E$2:$Z$2,AF$2,$E19:$Z19) -> -31932.941 | AG19: =SUMIF($E$2:$Z$2,AG$2,$E19:$Z19) -> -32282.503
B20: Other expenses | E20: ='Quarterly Historical Financials'!AB22 -> -51147 | F20: ='Quarterly Historical Financials'!AC22 -> -25698.955 | G20: =Assumptions!N79 -> -46963.9 | H20: =Assumptions!O79 -> -48868.422 | I20: =Assumptions!P79 -> -51203.409 | J20: =Assumptions!Q79 -> -53636.629 | K20: =Assumptions!R79 -> -56171.966 | L20: =Assumptions!S79 -> -58813.457 | M20: =Assumptions!T79 -> -61565.295 | N20: =Assumptions!U79 -> -64431.842 | ... Z20: =Assumptions!AG79 -> -109621.96 | AB20: =SUMIF($E$2:$Z$2,AB$2,$E20:$Z20) -> -76845.955 | AC20: =SUMIF($E$2:$Z$2,AC$2,$E20:$Z20) -> -200672.36 | AD20: =SUMIF($E$2:$Z$2,AD$2,$E20:$Z20) -> -240982.56 | AE20: =SUMIF($E$2:$Z$2,AE$2,$E20:$Z20) -> -288849.39 | AF20: =SUMIF($E$2:$Z$2,AF$2,$E20:$Z20) -> -345147.42 | AG20: =SUMIF($E$2:$Z$2,AG$2,$E20:$Z20) -> -411291.2
B21: Finance cost on lease liability | E21: ='Quarterly Historical Financials'!AB23 -> -3166 | F21: ='Quarterly Historical Financials'!AC23 -> -416.745 | G21: =Assumptions!N203 -> -2180.6666 | H21: =Assumptions!O203 -> -2386.9413 | I21: =Assumptions!P203 -> -2612.728 | J21: =Assumptions!Q203 -> -2859.8725 | K21: =Assumptions!R203 -> -3130.395 | L21: =Assumptions!S203 -> -3426.5069 | M21: =Assumptions!T203 -> -3750.6287 | N21: =Assumptions!U203 -> -4105.41 | ... Z21: =Assumptions!AG203 -> -12144.682 | AB21: =SUMIF($E$2:$Z$2,AB$2,$E21:$Z21) -> -3582.745 | AC21: =SUMIF($E$2:$Z$2,AC$2,$E21:$Z21) -> -10040.208 | AD21: =SUMIF($E$2:$Z$2,AD$2,$E21:$Z21) -> -14412.941 | AE21: =SUMIF($E$2:$Z$2,AE$2,$E21:$Z21) -> -20690.094 | AF21: =SUMIF($E$2:$Z$2,AF$2,$E21:$Z21) -> -29701.086 | AG21: =SUMIF($E$2:$Z$2,AG$2,$E21:$Z21) -> -42636.563
B22: Total Operating Expenses | E22: =SUM(E17:E21) -> -69429 | F22: =SUM(F17:F21) -> -342628.05 | G22: =SUM(G17:G21) -> -140185.24 | H22: =SUM(H17:H21) -> -157857.3 | I22: =SUM(I17:I21) -> -164694.7 | J22: =SUM(J17:J21) -> -171822.18 | K22: =SUM(K17:K21) -> -179252.21 | L22: =SUM(L17:L21) -> -186997.82 | ... Z22: =SUM(Z17:Z21) -> -337639.98 | AB22: =SUM(AB17:AB21) -> -412057.05 | AC22: =SUM(AC17:AC21) -> -634559.42 | AD22: =SUM(AD17:AD21) -> -764813.95 | AE22: =SUM(AE17:AE21) -> -905564.61 | AF22: =SUM(AF17:AF21) -> -1071996.2 | AG22: =SUM(AG17:AG21) -> -1269078.9
B23: Share of profit from associate company | E23: ='Quarterly Historical Financials'!AB26 -> 422 | F23: ='Quarterly Historical Financials'!AC26 -> 295.116 | G23: 0 | H23: 0 | I23: 0 | J23: 0 | K23: 0 | L23: 0 | M23: 0 | N23: 0 | O23: 0 | P23: 0 | Q23: 0 | R23: 0 | S23: 0 | T23: 0 | U23: 0 | V23: 0 | W23: 0 | X23: 0 | Y23: 0 | Z23: 0 | AB23: =SUMIF($E$2:$Z$2,AB$2,$E23:$Z23) -> 717.116 | AC23: =SUMIF($E$2:$Z$2,AC$2,$E23:$Z23) -> 0 | AD23: =SUMIF($E$2:$Z$2,AD$2,$E23:$Z23) -> 0 | AE23: =SUMIF($E$2:$Z$2,AE$2,$E23:$Z23) -> 0 | AF23: =SUMIF($E$2:$Z$2,AF$2,$E23:$Z23) -> 0 | AG23: =SUMIF($E$2:$Z$2,AG$2,$E23:$Z23) -> 0
B24: Profit before income tax | E24: =SUM(E16,E22:E23) -> 154788 | F24: =SUM(F16,F22:F23) -> 331289.45 | G24: =SUM(G16,G22:G23) -> 215745.39 | H24: =SUM(H16,H22:H23) -> 212507.36 | I24: =SUM(I16,I22:I23) -> 223366.39 | J24: =SUM(J16,J22:J23) -> 234679.82 | K24: =SUM(K16,K22:K23) -> 246464.64 | L24: =SUM(L16,L22:L23) -> 258738.39 | ... Z24: =SUM(Z16,Z22:Z23) -> 493164.37 | AB24: =SUM(AB16,AB22:AB23) -> 486077.45 | AC24: =SUM(AC16,AC22:AC23) -> 886298.96 | AD24: =SUM(AD16,AD22:AD23) -> 1061547.9 | AE24: =SUM(AE16,AE22:AE23) -> 1283571.1 | AF24: =SUM(AF16,AF22:AF23) -> 1543811.7 | AG24: =SUM(AG16,AG22:AG23) -> 1848020.3
B25: Total Taxes | E25: =SUM('Quarterly Historical Financials'!AB28:AB31) -> -43024 | F25: =SUM('Quarterly Historical Financials'!AC28:AC31) -> -101178.39 | G25: =Assumptions!N117 -> -44555.86 | H25: =Assumptions!O117 -> -43887.138 | I25: =Assumptions!P117 -> -46129.751 | J25: =Assumptions!Q117 -> -48466.208 | K25: =Assumptions!R117 -> -50900.016 | L25: =Assumptions!S117 -> -53434.798 | M25: =Assumptions!T117 -> -56074.293 | N25: =Assumptions!U117 -> -58822.365 | ... Z25: =Assumptions!AG117 -> -101848.58 | AB25: =SUMIF($E$2:$Z$2,AB$2,$E25:$Z25) -> -144202.39 | AC25: =SUMIF($E$2:$Z$2,AC$2,$E25:$Z25) -> -183038.96 | AD25: =SUMIF($E$2:$Z$2,AD$2,$E25:$Z25) -> -219231.47 | AE25: =SUMIF($E$2:$Z$2,AE$2,$E25:$Z25) -> -265083.81 | AF25: =SUMIF($E$2:$Z$2,AF$2,$E25:$Z25) -> -318828.85 | AG25: =SUMIF($E$2:$Z$2,AG$2,$E25:$Z25) -> -381654.19
B26: Profit for the period | E26: =SUM(E24:E25) -> 111764 | F26: =SUM(F24:F25) -> 230111.06 | G26: =SUM(G24:G25) -> 171189.53 | H26: =SUM(H24:H25) -> 168620.22 | I26: =SUM(I24:I25) -> 177236.64 | J26: =SUM(J24:J25) -> 186213.61 | K26: =SUM(K24:K25) -> 195564.63 | L26: =SUM(L24:L25) -> 205303.59 | ... Z26: =SUM(Z24:Z25) -> 391315.79 | AB26: =SUM(AB24:AB25) -> 341875.06 | AC26: =SUM(AC24:AC25) -> 703260 | AD26: =SUM(AD24:AD25) -> 842316.45 | AE26: =SUM(AE24:AE25) -> 1018487.2 | AF26: =SUM(AF24:AF25) -> 1224982.8 | AG26: =SUM(AG24:AG25) -> 1466366.1
B28: Shares Outstanding | E28: ='Quarterly Historical Financials'!AB34 -> 349617.46 | F28: =E28 -> 349617.46 | G28: =F28 -> 349617.46 | H28: =G28 -> 349617.46 | I28: =H28 -> 349617.46 | J28: =I28 -> 349617.46 | K28: =J28 -> 349617.46 | L28: =K28 -> 349617.46 | M28: =L28 -> 349617.46 | ... Z28: =Y28 -> 349617.46 | AB28: =SUMIF($E$4:$Z$4,AB$4,$E28:$Z28) -> 349617.46 | AC28: =SUMIF($E$4:$Z$4,AC$4,$E28:$Z28) -> 349617.46 | AD28: =SUMIF($E$4:$Z$4,AD$4,$E28:$Z28) -> 349617.46 | AE28: =SUMIF($E$4:$Z$4,AE$4,$E28:$Z28) -> 349617.46 | AF28: =SUMIF($E$4:$Z$4,AF$4,$E28:$Z28) -> 349617.46 | AG28: =SUMIF($E$4:$Z$4,AG$4,$E28:$Z28) -> 349617.46
B29: EPS | E29: =E26/E28 -> 0.31967511 | F29: =F26/F28 -> 0.65817955 | G29: =G26/G28 -> 0.48964813 | H29: =H26/H28 -> 0.48229918 | I29: =I26/I28 -> 0.50694446 | J29: =J26/J28 -> 0.53262103 | K29: =K26/K28 -> 0.55936744 | L29: =L26/L28 -> 0.58722351 | ... Z29: =Z26/Z28 -> 1.1192684 | AB29: =AB26/AB28 -> 0.97785466 | AC29: =AC26/AC28 -> 2.0115128 | AD29: =AD26/AD28 -> 2.4092517 | AE29: =AE26/AE28 -> 2.9131475 | AF29: =AF26/AF28 -> 3.5037804 | AG29: =AG26/AG28 -> 4.1942016
B31: Statement of Financial Position
B32: Assets
B33: Cash and cash equivalents | E33: ='Quarterly Historical Financials'!AB41+'Quarterly Historical Financials'!AB42 -> 3312929 | F33: ='Quarterly Historical Financials'!AC41+'Quarterly Historical Financials'!AC42 -> 8162460.5 | G33: =G111 -> 6892248.5 | H33: =H111 -> 7295215.3 | I33: =I111 -> 7716511.2 | J33: =J111 -> 8156889.4 | K33: =K111 -> 8617133.3 | L33: =L111 -> 9098058 | M33: =M111 -> 9600511.4 | N33: =N111 -> 10125376 | ... Z33: =Z111 -> 18546972 | AB33: =SUMIF($E$4:$Z$4,AB$4,$E33:$Z33) -> 8162460.5 | AC33: =SUMIF($E$4:$Z$4,AC$4,$E33:$Z33) -> 8156889.4 | AD33: =SUMIF($E$4:$Z$4,AD$4,$E33:$Z33) -> 10125376 | AE33: =SUMIF($E$4:$Z$4,AE$4,$E33:$Z33) -> 12467879 | AF33: =SUMIF($E$4:$Z$4,AF$4,$E33:$Z33) -> 15249551 | AG33: =SUMIF($E$4:$Z$4,AG$4,$E33:$Z33) -> 18546972
B34: Trading assets (Investment securities) | E34: ='Quarterly Historical Financials'!AB43 -> 3580300 | F34: ='Quarterly Historical Financials'!AC43 -> 3178870.4 | G34: =Assumptions!N99 -> 4086092.7 | H34: =Assumptions!O99 -> 4232624.4 | I34: =Assumptions!P99 -> 4384410.9 | J34: =Assumptions!Q99 -> 4541640.6 | K34: =Assumptions!R99 -> 4704508.7 | L34: =Assumptions!S99 -> 4873217.5 | M34: =Assumptions!T99 -> 5047976.3 | N34: =Assumptions!U99 -> 5229002.2 | ... Z34: =Assumptions!AG99 -> 7980627.2 | AB34: =SUMIF($E$4:$Z$4,AB$4,$E34:$Z34) -> 3178870.4 | AC34: =SUMIF($E$4:$Z$4,AC$4,$E34:$Z34) -> 4541640.6 | AD34: =SUMIF($E$4:$Z$4,AD$4,$E34:$Z34) -> 5229002.2 | AE34: =SUMIF($E$4:$Z$4,AE$4,$E34:$Z34) -> 6020393.7 | AF34: =SUMIF($E$4:$Z$4,AF$4,$E34:$Z34) -> 6931559.6 | AG34: =SUMIF($E$4:$Z$4,AG$4,$E34:$Z34) -> 7980627.2
B35: Loans and advances to customers | E35: ='Quarterly Historical Financials'!AB44 -> 1516490 | F35: ='Quarterly Historical Financials'!AC44 -> 1947024.8 | G35: =Assumptions!N94 -> 2936526.5 | H35: =Assumptions!O94 -> 3041833.5 | I35: =Assumptions!P94 -> 3150917 | J35: =Assumptions!Q94 -> 3263912.3 | K35: =Assumptions!R94 -> 3380959.7 | L35: =Assumptions!S94 -> 3502204.6 | M35: =Assumptions!T94 -> 3627797.4 | N35: =Assumptions!U94 -> 3757894.1 | ... Z35: =Assumptions!AG94 -> 5735387.1 | AB35: =SUMIF($E$4:$Z$4,AB$4,$E35:$Z35) -> 1947024.8 | AC35: =SUMIF($E$4:$Z$4,AC$4,$E35:$Z35) -> 3263912.3 | AD35: =SUMIF($E$4:$Z$4,AD$4,$E35:$Z35) -> 3757894.1 | AE35: =SUMIF($E$4:$Z$4,AE$4,$E35:$Z35) -> 4326638.5 | AF35: =SUMIF($E$4:$Z$4,AF$4,$E35:$Z35) -> 4981460.3 | AG35: =SUMIF($E$4:$Z$4,AG$4,$E35:$Z35) -> 5735387.1
B36: Investment in associates | E36: ='Quarterly Historical Financials'!AB47 -> 2505 | F36: ='Quarterly Historical Financials'!AC47 -> 2799.382 | G36: =Assumptions!N105 -> 2799.382 | H36: =Assumptions!O105 -> 2799.382 | I36: =Assumptions!P105 -> 2799.382 | J36: =Assumptions!Q105 -> 2799.382 | K36: =Assumptions!R105 -> 2799.382 | L36: =Assumptions!S105 -> 2799.382 | M36: =Assumptions!T105 -> 2799.382 | N36: =Assumptions!U105 -> 2799.382 | ... Z36: =Assumptions!AG105 -> 2799.382 | AB36: =SUMIF($E$4:$Z$4,AB$4,$E36:$Z36) -> 2799.382 | AC36: =SUMIF($E$4:$Z$4,AC$4,$E36:$Z36) -> 2799.382 | AD36: =SUMIF($E$4:$Z$4,AD$4,$E36:$Z36) -> 2799.382 | AE36: =SUMIF($E$4:$Z$4,AE$4,$E36:$Z36) -> 2799.382 | AF36: =SUMIF($E$4:$Z$4,AF$4,$E36:$Z36) -> 2799.382 | AG36: =SUMIF($E$4:$Z$4,AG$4,$E36:$Z36) -> 2799.382
B37: Investment in subsidiary | E37: ='Quarterly Historical Financials'!AB48 -> 3025 | F37: ='Quarterly Historical Financials'!AC48 -> 0 | G37: =Assumptions!N111 -> 0 | H37: =Assumptions!O111 -> 0 | I37: =Assumptions!P111 -> 0 | J37: =Assumptions!Q111 -> 0 | K37: =Assumptions!R111 -> 0 | L37: =Assumptions!S111 -> 0 | M37: =Assumptions!T111 -> 0 | N37: =Assumptions!U111 -> 0 | ... Z37: =Assumptions!AG111 -> 0 | AB37: =SUMIF($E$4:$Z$4,AB$4,$E37:$Z37) -> 0 | AC37: =SUMIF($E$4:$Z$4,AC$4,$E37:$Z37) -> 0 | AD37: =SUMIF($E$4:$Z$4,AD$4,$E37:$Z37) -> 0 | AE37: =SUMIF($E$4:$Z$4,AE$4,$E37:$Z37) -> 0 | AF37: =SUMIF($E$4:$Z$4,AF$4,$E37:$Z37) -> 0 | AG37: =SUMIF($E$4:$Z$4,AG$4,$E37:$Z37) -> 0
B38: Current tax assets | E38: ='Quarterly Historical Financials'!AB49 -> 191807 | F38: ='Quarterly Historical Financials'!AC49 -> 244879.81 | G38: =Assumptions!N124 -> 244879.81 | H38: =Assumptions!O124 -> 244879.81 | I38: =Assumptions!P124 -> 244879.81 | J38: =Assumptions!Q124 -> 244879.81 | K38: =Assumptions!R124 -> 244879.81 | L38: =Assumptions!S124 -> 244879.81 | M38: =Assumptions!T124 -> 244879.81 | N38: =Assumptions!U124 -> 244879.81 | ... Z38: =Assumptions!AG124 -> 244879.81 | AB38: =SUMIF($E$4:$Z$4,AB$4,$E38:$Z38) -> 244879.81 | AC38: =SUMIF($E$4:$Z$4,AC$4,$E38:$Z38) -> 244879.81 | AD38: =SUMIF($E$4:$Z$4,AD$4,$E38:$Z38) -> 244879.81 | AE38: =SUMIF($E$4:$Z$4,AE$4,$E38:$Z38) -> 244879.81 | AF38: =SUMIF($E$4:$Z$4,AF$4,$E38:$Z38) -> 244879.81 | AG38: =SUMIF($E$4:$Z$4,AG$4,$E38:$Z38) -> 244879.81
B39: Deferred tax asset | E39: ='Quarterly Historical Financials'!AB50 -> 8827 | F39: ='Quarterly Historical Financials'!AC50 -> 0 | G39: =Assumptions!N130 -> 0 | H39: =Assumptions!O130 -> 0 | I39: =Assumptions!P130 -> 0 | J39: =Assumptions!Q130 -> 0 | K39: =Assumptions!R130 -> 0 | L39: =Assumptions!S130 -> 0 | M39: =Assumptions!T130 -> 0 | N39: =Assumptions!U130 -> 0 | ... Z39: =Assumptions!AG130 -> 0 | AB39: =SUMIF($E$4:$Z$4,AB$4,$E39:$Z39) -> 0 | AC39: =SUMIF($E$4:$Z$4,AC$4,$E39:$Z39) -> 0 | AD39: =SUMIF($E$4:$Z$4,AD$4,$E39:$Z39) -> 0 | AE39: =SUMIF($E$4:$Z$4,AE$4,$E39:$Z39) -> 0 | AF39: =SUMIF($E$4:$Z$4,AF$4,$E39:$Z39) -> 0 | AG39: =SUMIF($E$4:$Z$4,AG$4,$E39:$Z39) -> 0
B40: Growth and Fiscal levies | E40: ='Quarterly Historical Financials'!AB51 -> 37747 | F40: ='Quarterly Historical Financials'!AC51 -> 0 | G40: =Assumptions!N136 -> 0 | H40: =Assumptions!O136 -> 0 | I40: =Assumptions!P136 -> 0 | J40: =Assumptions!Q136 -> 0 | K40: =Assumptions!R136 -> 0 | L40: =Assumptions!S136 -> 0 | M40: =Assumptions!T136 -> 0 | N40: =Assumptions!U136 -> 0 | ... Z40: =Assumptions!AG136 -> 0 | AB40: =SUMIF($E$4:$Z$4,AB$4,$E40:$Z40) -> 0 | AC40: =SUMIF($E$4:$Z$4,AC$4,$E40:$Z40) -> 0 | AD40: =SUMIF($E$4:$Z$4,AD$4,$E40:$Z40) -> 0 | AE40: =SUMIF($E$4:$Z$4,AE$4,$E40:$Z40) -> 0 | AF40: =SUMIF($E$4:$Z$4,AF$4,$E40:$Z40) -> 0 | AG40: =SUMIF($E$4:$Z$4,AG$4,$E40:$Z40) -> 0
B41: Intangible assets | E41: ='Quarterly Historical Financials'!AB52 -> 33244 | F41: ='Quarterly Historical Financials'!AC52 -> 31109.297 | G41: =Assumptions!N145 -> 31406.565 | H41: =Assumptions!O145 -> 31706.674 | I41: =Assumptions!P145 -> 32009.65 | J41: =Assumptions!Q145 -> 32315.522 | K41: =Assumptions!R145 -> 32624.316 | L41: =Assumptions!S145 -> 32936.061 | M41: =Assumptions!T145 -> 33250.785 | N41: =Assumptions!U145 -> 33568.516 | ... Z41: =Assumptions!AG145 -> 37626.608 | AB41: =SUMIF($E$4:$Z$4,AB$4,$E41:$Z41) -> 31109.297 | AC41: =SUMIF($E$4:$Z$4,AC$4,$E41:$Z41) -> 32315.522 | AD41: =SUMIF($E$4:$Z$4,AD$4,$E41:$Z41) -> 33568.516 | AE41: =SUMIF($E$4:$Z$4,AE$4,$E41:$Z41) -> 34870.094 | AF41: =SUMIF($E$4:$Z$4,AF$4,$E41:$Z41) -> 36222.139 | AG41: =SUMIF($E$4:$Z$4,AG$4,$E41:$Z41) -> 37626.608
B42: Other assets | E42: ='Quarterly Historical Financials'!AB53 -> 6363787 | F42: ='Quarterly Historical Financials'!AC53 -> 5017670.6 | G42: =Assumptions!N171 -> 5112929.4 | H42: =Assumptions!O171 -> 5209996.7 | I42: =Assumptions!P171 -> 5308906.7 | J42: =Assumptions!Q171 -> 5409694.6 | K42: =Assumptions!R171 -> 5512395.8 | L42: =Assumptions!S171 -> 5617046.8 | M42: =Assumptions!T171 -> 5723684.6 | N42: =Assumptions!U171 -> 5832346.8 | ... Z42: =Assumptions!AG171 -> 7308952.5 | AB42: =SUMIF($E$4:$Z$4,AB$4,$E42:$Z42) -> 5017670.6 | AC42: =SUMIF($E$4:$Z$4,AC$4,$E42:$Z42) -> 5409694.6 | AD42: =SUMIF($E$4:$Z$4,AD$4,$E42:$Z42) -> 5832346.8 | AE42: =SUMIF($E$4:$Z$4,AE$4,$E42:$Z42) -> 6288020.4 | AF42: =SUMIF($E$4:$Z$4,AF$4,$E42:$Z42) -> 6779295.1 | AG42: =SUMIF($E$4:$Z$4,AG$4,$E42:$Z42) -> 7308952.5
B43: Property and equipment | E43: ='Quarterly Historical Financials'!AB54 -> 583596 | F43: ='Quarterly Historical Financials'!AC54 -> 568767.64 | G43: =Assumptions!N154 -> 569276.49 | H43: =Assumptions!O154 -> 569785.8 | I43: =Assumptions!P154 -> 570295.56 | J43: =Assumptions!Q154 -> 570805.78 | K43: =Assumptions!R154 -> 571316.45 | L43: =Assumptions!S154 -> 571827.58 | M43: =Assumptions!T154 -> 572339.17 | N43: =Assumptions!U154 -> 572851.22 | ... Z43: =Assumptions!AG154 -> 579031.63 | AB43: =SUMIF($E$4:$Z$4,AB$4,$E43:$Z43) -> 568767.64 | AC43: =SUMIF($E$4:$Z$4,AC$4,$E43:$Z43) -> 570805.78 | AD43: =SUMIF($E$4:$Z$4,AD$4,$E43:$Z43) -> 572851.22 | AE43: =SUMIF($E$4:$Z$4,AE$4,$E43:$Z43) -> 574903.99 | AF43: =SUMIF($E$4:$Z$4,AF$4,$E43:$Z43) -> 576964.12 | AG43: =SUMIF($E$4:$Z$4,AG$4,$E43:$Z43) -> 579031.63
B44: Right-of-Use Assets | E44: ='Quarterly Historical Financials'!AB55 -> 22696 | F44: ='Quarterly Historical Financials'!AC55 -> 39409.09 | G44: =Assumptions!N163 -> 39409.09 | H44: =Assumptions!O163 -> 39409.09 | I44: =Assumptions!P163 -> 39409.09 | J44: =Assumptions!Q163 -> 39409.09 | K44: =Assumptions!R163 -> 39409.09 | L44: =Assumptions!S163 -> 39409.09 | M44: =Assumptions!T163 -> 39409.09 | N44: =Assumptions!U163 -> 39409.09 | ... Z44: =Assumptions!AG163 -> 39409.09 | AB44: =SUMIF($E$4:$Z$4,AB$4,$E44:$Z44) -> 39409.09 | AC44: =SUMIF($E$4:$Z$4,AC$4,$E44:$Z44) -> 39409.09 | AD44: =SUMIF($E$4:$Z$4,AD$4,$E44:$Z44) -> 39409.09 | AE44: =SUMIF($E$4:$Z$4,AE$4,$E44:$Z44) -> 39409.09 | AF44: =SUMIF($E$4:$Z$4,AF$4,$E44:$Z44) -> 39409.09 | AG44: =SUMIF($E$4:$Z$4,AG$4,$E44:$Z44) -> 39409.09
B45: Total Assets | E45: =SUM(E33:E44) -> 15656953 | F45: =SUM(F33:F44) -> 19192992 | G45: =SUM(G33:G44) -> 19915568 | H45: =SUM(H33:H44) -> 20668251 | I45: =SUM(I33:I44) -> 21450139 | J45: =SUM(J33:J44) -> 22262346 | K45: =SUM(K33:K44) -> 23106027 | L45: =SUM(L33:L44) -> 23982379 | ... Z45: =SUM(Z33:Z44) -> 40475685 | AB45: =SUM(AB33:AB44) -> 19192992 | AC45: =SUM(AC33:AC44) -> 22262346 | AD45: =SUM(AD33:AD44) -> 25838127 | AE45: =SUM(AE33:AE44) -> 29999794 | AF45: =SUM(AF33:AF44) -> 34842141 | AG45: =SUM(AG33:AG44) -> 40475685
B47: Liabilities
B48: Total Deposits | E48: =SUM('Quarterly Historical Financials'!AB59:AB60) -> 13833495 | F48: =SUM('Quarterly Historical Financials'!AC59:AC60) -> 16642450 | G48: =Assumptions!N85 -> 17239266 | H48: =Assumptions!O85 -> 17857485 | I48: =Assumptions!P85 -> 18497873 | J48: =Assumptions!Q85 -> 19161227 | K48: =Assumptions!R85 -> 19848369 | L48: =Assumptions!S85 -> 20560153 | M48: =Assumptions!T85 -> 21297463 | N48: =Assumptions!U85 -> 22061213 | ... Z48: =Assumptions!AG85 -> 33670346 | AB48: =SUMIF($E$4:$Z$4,AB$4,$E48:$Z48) -> 16642450 | AC48: =SUMIF($E$4:$Z$4,AC$4,$E48:$Z48) -> 19161227 | AD48: =SUMIF($E$4:$Z$4,AD$4,$E48:$Z48) -> 22061213 | AE48: =SUMIF($E$4:$Z$4,AE$4,$E48:$Z48) -> 25400101 | AF48: =SUMIF($E$4:$Z$4,AF$4,$E48:$Z48) -> 29244319 | AG48: =SUMIF($E$4:$Z$4,AG$4,$E48:$Z48) -> 33670346
B49: Current tax liabilities | E49: ='Quarterly Historical Financials'!AB61 -> 0 | F49: ='Quarterly Historical Financials'!AC61 -> 0 | G49: =Assumptions!N185 -> 0 | H49: =Assumptions!O185 -> 0 | I49: =Assumptions!P185 -> 0 | J49: =Assumptions!Q185 -> 0 | K49: =Assumptions!R185 -> 0 | L49: =Assumptions!S185 -> 0 | M49: =Assumptions!T185 -> 0 | N49: =Assumptions!U185 -> 0 | ... Z49: =Assumptions!AG185 -> 0 | AB49: =SUMIF($E$4:$Z$4,AB$4,$E49:$Z49) -> 0 | AC49: =SUMIF($E$4:$Z$4,AC$4,$E49:$Z49) -> 0 | AD49: =SUMIF($E$4:$Z$4,AD$4,$E49:$Z49) -> 0 | AE49: =SUMIF($E$4:$Z$4,AE$4,$E49:$Z49) -> 0 | AF49: =SUMIF($E$4:$Z$4,AF$4,$E49:$Z49) -> 0 | AG49: =SUMIF($E$4:$Z$4,AG$4,$E49:$Z49) -> 0
B50: Deferred tax liabilities | E50: ='Quarterly Historical Financials'!AB63 -> 0 | F50: ='Quarterly Historical Financials'!AC63 -> 173127.59 | G50: =Assumptions!N179 -> 173127.59 | H50: =Assumptions!O179 -> 173127.59 | I50: =Assumptions!P179 -> 173127.59 | J50: =Assumptions!Q179 -> 173127.59 | K50: =Assumptions!R179 -> 173127.59 | L50: =Assumptions!S179 -> 173127.59 | M50: =Assumptions!T179 -> 173127.59 | N50: =Assumptions!U179 -> 173127.59 | ... Z50: =Assumptions!AG179 -> 173127.59 | AB50: =SUMIF($E$4:$Z$4,AB$4,$E50:$Z50) -> 173127.59 | AC50: =SUMIF($E$4:$Z$4,AC$4,$E50:$Z50) -> 173127.59 | AD50: =SUMIF($E$4:$Z$4,AD$4,$E50:$Z50) -> 173127.59 | AE50: =SUMIF($E$4:$Z$4,AE$4,$E50:$Z50) -> 173127.59 | AF50: =SUMIF($E$4:$Z$4,AF$4,$E50:$Z50) -> 173127.59 | AG50: =SUMIF($E$4:$Z$4,AG$4,$E50:$Z50) -> 173127.59
B51: Other liabilities | E51: ='Quarterly Historical Financials'!AB64+'Quarterly Historical Financials'!AB62 -> 23750 | F51: ='Quarterly Historical Financials'!AC64+'Quarterly Historical Financials'!AC62 -> 130178.53 | G51: =Assumptions!N193 -> 127723.99 | H51: =Assumptions!O193 -> 134060.27 | I51: =Assumptions!P193 -> 140710.88 | J51: =Assumptions!Q193 -> 147691.43 | K51: =Assumptions!R193 -> 155018.28 | L51: =Assumptions!S193 -> 162708.6 | M51: =Assumptions!T193 -> 170780.44 | N51: =Assumptions!U193 -> 179252.71 | ... Z51: =Assumptions!AG193 -> 320477.14 | AB51: =SUMIF($E$4:$Z$4,AB$4,$E51:$Z51) -> 130178.53 | AC51: =SUMIF($E$4:$Z$4,AC$4,$E51:$Z51) -> 147691.43 | AD51: =SUMIF($E$4:$Z$4,AD$4,$E51:$Z51) -> 179252.71 | AE51: =SUMIF($E$4:$Z$4,AE$4,$E51:$Z51) -> 217558.56 | AF51: =SUMIF($E$4:$Z$4,AF$4,$E51:$Z51) -> 264050.27 | AG51: =SUMIF($E$4:$Z$4,AG$4,$E51:$Z51) -> 320477.14
B52: Lease liabilities | E52: ='Quarterly Historical Financials'!AB65 -> 25116 | F52: ='Quarterly Historical Financials'!AC65 -> 38841.151 | G52: =Assumptions!N201 -> 42515.232 | H52: =Assumptions!O201 -> 46536.854 | I52: =Assumptions!P201 -> 50938.891 | J52: =Assumptions!Q201 -> 55757.328 | K52: =Assumptions!R201 -> 61031.553 | L52: =Assumptions!S201 -> 66804.68 | M52: =Assumptions!T201 -> 73123.901 | N52: =Assumptions!U201 -> 80040.874 | ... Z52: =Assumptions!AG201 -> 236778.04 | AB52: =SUMIF($E$4:$Z$4,AB$4,$E52:$Z52) -> 38841.151 | AC52: =SUMIF($E$4:$Z$4,AC$4,$E52:$Z52) -> 55757.328 | AD52: =SUMIF($E$4:$Z$4,AD$4,$E52:$Z52) -> 80040.874 | AE52: =SUMIF($E$4:$Z$4,AE$4,$E52:$Z52) -> 114900.44 | AF52: =SUMIF($E$4:$Z$4,AF$4,$E52:$Z52) -> 164942.11 | AG52: =SUMIF($E$4:$Z$4,AG$4,$E52:$Z52) -> 236778.04
B53: Total Liabilities | E53: =SUM(E48:E52) -> 13882361 | F53: =SUM(F48:F52) -> 16984597 | G53: =SUM(G48:G52) -> 17582633 | H53: =SUM(H48:H52) -> 18211209 | I53: =SUM(I48:I52) -> 18862651 | J53: =SUM(J48:J52) -> 19537803 | K53: =SUM(K48:K52) -> 20237547 | L53: =SUM(L48:L52) -> 20962794 | ... Z53: =SUM(Z48:Z52) -> 34400729 | AB53: =SUM(AB48:AB52) -> 16984597 | AC53: =SUM(AC48:AC52) -> 19537803 | AD53: =SUM(AD48:AD52) -> 22493634 | AE53: =SUM(AE48:AE52) -> 25905688 | AF53: =SUM(AF48:AF52) -> 29846439 | AG53: =SUM(AG48:AG52) -> 34400729
B55: Equity
B56: Stated capital | E56: ='Quarterly Historical Financials'!AB69+'Quarterly Historical Financials'!AB72 -> 521733 | F56: ='Quarterly Historical Financials'!AC69+'Quarterly Historical Financials'!AC72 -> 727506.62 | G56: =Assumptions!N211 -> 726051.15 | H56: =Assumptions!O211 -> 726051.15 | I56: =Assumptions!P211 -> 726051.15 | J56: =Assumptions!Q211 -> 726051.15 | K56: =Assumptions!R211 -> 726051.15 | L56: =Assumptions!S211 -> 726051.15 | M56: =Assumptions!T211 -> 726051.15 | N56: =Assumptions!U211 -> 726051.15 | ... Z56: =Assumptions!AG211 -> 726051.15 | AB56: =SUMIF($E$4:$Z$4,AB$4,$E56:$Z56) -> 727506.62 | AC56: =SUMIF($E$4:$Z$4,AC$4,$E56:$Z56) -> 726051.15 | AD56: =SUMIF($E$4:$Z$4,AD$4,$E56:$Z56) -> 726051.15 | AE56: =SUMIF($E$4:$Z$4,AE$4,$E56:$Z56) -> 726051.15 | AF56: =SUMIF($E$4:$Z$4,AF$4,$E56:$Z56) -> 726051.15 | AG56: =SUMIF($E$4:$Z$4,AG$4,$E56:$Z56) -> 726051.15
B57: Retained earnings | E57: ='Quarterly Historical Financials'!AB70 -> 354517 | F57: ='Quarterly Historical Financials'!AC70 -> 454973.95 | G57: =Assumptions!N218 -> 580970.53 | H57: =Assumptions!O218 -> 705076.09 | I57: =Assumptions!P218 -> 835523.38 | J57: =Assumptions!Q218 -> 972577.78 | K57: =Assumptions!R218 -> 1116514.6 | L57: =Assumptions!S218 -> 1267619.3 | M57: =Assumptions!T218 -> 1426188.2 | N57: =Assumptions!U218 -> 1592528.1 | ... Z57: =Assumptions!AG218 -> 4322991.1 | AB57: =SUMIF($E$4:$Z$4,AB$4,$E57:$Z57) -> 454973.95 | AC57: =SUMIF($E$4:$Z$4,AC$4,$E57:$Z57) -> 972577.78 | AD57: =SUMIF($E$4:$Z$4,AD$4,$E57:$Z57) -> 1592528.1 | AE57: =SUMIF($E$4:$Z$4,AE$4,$E57:$Z57) -> 2342141.1 | AF57: =SUMIF($E$4:$Z$4,AF$4,$E57:$Z57) -> 3243736.3 | AG57: =SUMIF($E$4:$Z$4,AG$4,$E57:$Z57) -> 4322991.1
B58: Revaluation reserve | E58: ='Quarterly Historical Financials'!AB71 -> 325693 | F58: ='Quarterly Historical Financials'!AC71 -> 325693.41 | G58: =Assumptions!N224 -> 325693.41 | H58: =Assumptions!O224 -> 325693.41 | I58: =Assumptions!P224 -> 325693.41 | J58: =Assumptions!Q224 -> 325693.41 | K58: =Assumptions!R224 -> 325693.41 | L58: =Assumptions!S224 -> 325693.41 | M58: =Assumptions!T224 -> 325693.41 | N58: =Assumptions!U224 -> 325693.41 | ... Z58: =Assumptions!AG224 -> 325693.41 | AB58: =SUMIF($E$4:$Z$4,AB$4,$E58:$Z58) -> 325693.41 | AC58: =SUMIF($E$4:$Z$4,AC$4,$E58:$Z58) -> 325693.41 | AD58: =SUMIF($E$4:$Z$4,AD$4,$E58:$Z58) -> 325693.41 | AE58: =SUMIF($E$4:$Z$4,AE$4,$E58:$Z58) -> 325693.41 | AF58: =SUMIF($E$4:$Z$4,AF$4,$E58:$Z58) -> 325693.41 | AG58: =SUMIF($E$4:$Z$4,AG$4,$E58:$Z58) -> 325693.41
B59: Statutory reserve fund | E59: ='Quarterly Historical Financials'!AB73 -> 382743 | F59: ='Quarterly Historical Financials'!AC73 -> 503644.92 | G59: =Assumptions!N230 -> 503644.92 | H59: =Assumptions!O230 -> 503644.92 | I59: =Assumptions!P230 -> 503644.92 | J59: =Assumptions!Q230 -> 503644.92 | K59: =Assumptions!R230 -> 503644.92 | L59: =Assumptions!S230 -> 503644.92 | M59: =Assumptions!T230 -> 503644.92 | N59: =Assumptions!U230 -> 503644.92 | ... Z59: =Assumptions!AG230 -> 503644.92 | AB59: =SUMIF($E$4:$Z$4,AB$4,$E59:$Z59) -> 503644.92 | AC59: =SUMIF($E$4:$Z$4,AC$4,$E59:$Z59) -> 503644.92 | AD59: =SUMIF($E$4:$Z$4,AD$4,$E59:$Z59) -> 503644.92 | AE59: =SUMIF($E$4:$Z$4,AE$4,$E59:$Z59) -> 503644.92 | AF59: =SUMIF($E$4:$Z$4,AF$4,$E59:$Z59) -> 503644.92 | AG59: =SUMIF($E$4:$Z$4,AG$4,$E59:$Z59) -> 503644.92
B60: Credit risk reserve | E60: ='Quarterly Historical Financials'!AB74 -> 189906 | F60: ='Quarterly Historical Financials'!AC74 -> 196575.75 | G60: =Assumptions!N236 -> 196575.75 | H60: =Assumptions!O236 -> 196575.75 | I60: =Assumptions!P236 -> 196575.75 | J60: =Assumptions!Q236 -> 196575.75 | K60: =Assumptions!R236 -> 196575.75 | L60: =Assumptions!S236 -> 196575.75 | M60: =Assumptions!T236 -> 196575.75 | N60: =Assumptions!U236 -> 196575.75 | ... Z60: =Assumptions!AG236 -> 196575.75 | AB60: =SUMIF($E$4:$Z$4,AB$4,$E60:$Z60) -> 196575.75 | AC60: =SUMIF($E$4:$Z$4,AC$4,$E60:$Z60) -> 196575.75 | AD60: =SUMIF($E$4:$Z$4,AD$4,$E60:$Z60) -> 196575.75 | AE60: =SUMIF($E$4:$Z$4,AE$4,$E60:$Z60) -> 196575.75 | AF60: =SUMIF($E$4:$Z$4,AF$4,$E60:$Z60) -> 196575.75 | AG60: =SUMIF($E$4:$Z$4,AG$4,$E60:$Z60) -> 196575.75
B61: Other reserves | E61: ='Quarterly Historical Financials'!AB75 -> 0 | F61: ='Quarterly Historical Financials'!AC75 -> 0 | G61: =Assumptions!N242 -> 0 | H61: =Assumptions!O242 -> 0 | I61: =Assumptions!P242 -> 0 | J61: =Assumptions!Q242 -> 0 | K61: =Assumptions!R242 -> 0 | L61: =Assumptions!S242 -> 0 | M61: =Assumptions!T242 -> 0 | N61: =Assumptions!U242 -> 0 | ... Z61: =Assumptions!AG242 -> 0 | AB61: =SUMIF($E$4:$Z$4,AB$4,$E61:$Z61) -> 0 | AC61: =SUMIF($E$4:$Z$4,AC$4,$E61:$Z61) -> 0 | AD61: =SUMIF($E$4:$Z$4,AD$4,$E61:$Z61) -> 0 | AE61: =SUMIF($E$4:$Z$4,AE$4,$E61:$Z61) -> 0 | AF61: =SUMIF($E$4:$Z$4,AF$4,$E61:$Z61) -> 0 | AG61: =SUMIF($E$4:$Z$4,AG$4,$E61:$Z61) -> 0
B62: Total Equity | E62: =SUM(E56:E61) -> 1774592 | F62: =SUM(F56:F61) -> 2208394.7 | G62: =SUM(G56:G61) -> 2332935.8 | H62: =SUM(H56:H61) -> 2457041.3 | I62: =SUM(I56:I61) -> 2587488.6 | J62: =SUM(J56:J61) -> 2724543 | K62: =SUM(K56:K61) -> 2868479.8 | L62: =SUM(L56:L61) -> 3019584.6 | ... Z62: =SUM(Z56:Z61) -> 6074956.3 | AB62: =SUM(AB56:AB61) -> 2208394.7 | AC62: =SUM(AC56:AC61) -> 2724543 | AD62: =SUM(AD56:AD61) -> 3344493.3 | AE62: =SUM(AE56:AE61) -> 4094106.4 | AF62: =SUM(AF56:AF61) -> 4995701.5 | AG62: =SUM(AG56:AG61) -> 6074956.3
B63: Total Equity and Liabilities | E63: =E53+E62 -> 15656953 | F63: =F53+F62 -> 19192992 | G63: =G53+G62 -> 19915568 | H63: =H53+H62 -> 20668251 | I63: =I53+I62 -> 21450139 | J63: =J53+J62 -> 22262346 | K63: =K53+K62 -> 23106027 | L63: =L53+L62 -> 23982379 | ... Z63: =Z53+Z62 -> 40475685 | AB63: =AB53+AB62 -> 19192992 | AC63: =AC53+AC62 -> 22262346 | AD63: =AD53+AD62 -> 25838127 | AE63: =AE53+AE62 -> 29999794 | AF63: =AF53+AF62 -> 34842141 | AG63: =AG53+AG62 -> 40475685
B64: Check | E64: =E45-E63 -> 0 | F64: =F45-F63 -> -0.001000002 | G64: =G45-G63 -> 0 | H64: =H45-H63 -> 0 | I64: =I45-I63 -> 0 | J64: =J45-J63 -> 0 | K64: =K45-K63 -> 0 | L64: =L45-L63 -> 0 | ... Z64: =Z45-Z63 -> 0 | AB64: =AB45-AB63 -> -0.001000002 | AC64: =AC45-AC63 -> 0 | AD64: =AD45-AD63 -> 0 | AE64: =AE45-AE63 -> 0 | AF64: =AF45-AF63 -> 0 | AG64: =AG45-AG63 -> 0
B67: Statement of Cashflow
B68: Cash flows from operating activities
B69: Profit before tax | F69: =F24 -> 331289.45 | G69: =G24 -> 215745.39 | H69: =H24 -> 212507.36 | I69: =I24 -> 223366.39 | J69: =J24 -> 234679.82 | K69: =K24 -> 246464.64 | L69: =L24 -> 258738.39 | M69: =M24 -> 271519.18 | ... Z69: =Z24 -> 493164.37 | AB69: =SUMIF($E$2:$Z$2,AB$2,$E69:$Z69) -> 331289.45 | AC69: =SUMIF($E$2:$Z$2,AC$2,$E69:$Z69) -> 886298.96 | AD69: =SUMIF($E$2:$Z$2,AD$2,$E69:$Z69) -> 1061547.9 | AE69: =SUMIF($E$2:$Z$2,AE$2,$E69:$Z69) -> 1283571.1 | AF69: =SUMIF($E$2:$Z$2,AF$2,$E69:$Z69) -> 1543811.7 | AG69: =SUMIF($E$2:$Z$2,AG$2,$E69:$Z69) -> 1848020.3
B70: Adjusted for :
B71: Depreciation and amortisation | F71: =-F19 -> 18327.089 | G71: =-G19 -> 7706.1292 | H71: =-H19 -> 7725.7472 | I71: =-I19 -> 7745.5043 | J71: =-J19 -> 7765.4018 | K71: =-K19 -> 7785.441 | L71: =-L19 -> 7805.6233 | M71: =-M19 -> 7825.9499 | ... Z71: =-Z19 -> 8103.9576 | AB71: =SUMIF($E$2:$Z$2,AB$2,$E71:$Z71) -> 18327.089 | AC71: =SUMIF($E$2:$Z$2,AC$2,$E71:$Z71) -> 30942.782 | AD71: =SUMIF($E$2:$Z$2,AD$2,$E71:$Z71) -> 31263.436 | AE71: =SUMIF($E$2:$Z$2,AE$2,$E71:$Z71) -> 31593.373 | AF71: =SUMIF($E$2:$Z$2,AF$2,$E71:$Z71) -> 31932.941 | AG71: =SUMIF($E$2:$Z$2,AG$2,$E71:$Z71) -> 32282.503
B72: Impairment on financial assets | F72: =-F17 -> 178305.4 | G72: =-G17 -> 26006.504 | H72: =-H17 -> 39223.326 | I72: =-I17 -> 40629.917 | J72: =-J17 -> 42086.949 | K72: =-K17 -> 43596.233 | L72: =-L17 -> 45159.641 | M72: =-M17 -> 46779.114 | ... Z72: =-Z17 -> 73955.71 | AB72: =SUMIF($E$2:$Z$2,AB$2,$E72:$Z72) -> 178305.4 | AC72: =SUMIF($E$2:$Z$2,AC$2,$E72:$Z72) -> 147946.7 | AD72: =SUMIF($E$2:$Z$2,AD$2,$E72:$Z72) -> 183991.65 | AE72: =SUMIF($E$2:$Z$2,AE$2,$E72:$Z72) -> 211838.15 | AF72: =SUMIF($E$2:$Z$2,AF$2,$E72:$Z72) -> 243899.13 | AG72: =SUMIF($E$2:$Z$2,AG$2,$E72:$Z72) -> 280812.42
B73: Share of profit of associate | F73: =-F23 -> -295.116 | G73: =-G23 -> 0 | H73: =-H23 -> 0 | I73: =-I23 -> 0 | J73: =-J23 -> 0 | K73: =-K23 -> 0 | L73: =-L23 -> 0 | M73: =-M23 -> 0 | ... Z73: =-Z23 -> 0 | AB73: =SUMIF($E$2:$Z$2,AB$2,$E73:$Z73) -> -295.116 | AC73: =SUMIF($E$2:$Z$2,AC$2,$E73:$Z73) -> 0 | AD73: =SUMIF($E$2:$Z$2,AD$2,$E73:$Z73) -> 0 | AE73: =SUMIF($E$2:$Z$2,AE$2,$E73:$Z73) -> 0 | AF73: =SUMIF($E$2:$Z$2,AF$2,$E73:$Z73) -> 0 | AG73: =SUMIF($E$2:$Z$2,AG$2,$E73:$Z73) -> 0
B74: Changes in operating assets and liabilities:
B75: Trading assets (Investment securities) | F75: =E34-F34 -> 401429.63 | G75: =F34-G34 -> -907222.31 | H75: =G34-H34 -> -146531.7 | I75: =H34-I34 -> -151786.49 | J75: =I34-J34 -> -157229.72 | K75: =J34-K34 -> -162868.14 | L75: =K34-L34 -> -168708.77 | M75: =L34-M34 -> -174758.85 | ... Z75: =Y34-Z34 -> -276286.01 | AB75: =SUMIF($E$2:$Z$2,AB$2,$E75:$Z75) -> 401429.63 | AC75: =SUMIF($E$2:$Z$2,AC$2,$E75:$Z75) -> -1362770.2 | AD75: =SUMIF($E$2:$Z$2,AD$2,$E75:$Z75) -> -687361.65 | AE75: =SUMIF($E$2:$Z$2,AE$2,$E75:$Z75) -> -791391.47 | AF75: =SUMIF($E$2:$Z$2,AF$2,$E75:$Z75) -> -911165.84 | AG75: =SUMIF($E$2:$Z$2,AG$2,$E75:$Z75) -> -1049067.7
B76: Loans and advances to customers | F76: =E35-F35 -> -430534.82 | G76: =F35-G35 -> -989501.69 | H76: =G35-H35 -> -105307.02 | I76: =H35-I35 -> -109083.44 | J76: =I35-J35 -> -112995.29 | K76: =J35-K35 -> -117047.42 | L76: =K35-L35 -> -121244.87 | M76: =L35-M35 -> -125592.84 | ... Z76: =Y35-Z35 -> -198556.73 | AB76: =SUMIF($E$2:$Z$2,AB$2,$E76:$Z76) -> -430534.82 | AC76: =SUMIF($E$2:$Z$2,AC$2,$E76:$Z76) -> -1316887.4 | AD76: =SUMIF($E$2:$Z$2,AD$2,$E76:$Z76) -> -493981.87 | AE76: =SUMIF($E$2:$Z$2,AE$2,$E76:$Z76) -> -568744.33 | AF76: =SUMIF($E$2:$Z$2,AF$2,$E76:$Z76) -> -654821.82 | AG76: =SUMIF($E$2:$Z$2,AG$2,$E76:$Z76) -> -753926.85
B77: Current tax assets | F77: =-Assumptions!M123 -> -53072.81 | G77: =-Assumptions!N123 -> 0 | H77: =-Assumptions!O123 -> 0 | I77: =-Assumptions!P123 -> 0 | J77: =-Assumptions!Q123 -> 0 | K77: =-Assumptions!R123 -> 0 | L77: =-Assumptions!S123 -> 0 | M77: =-Assumptions!T123 -> 0 | ... Z77: =-Assumptions!AG123 -> 0 | AB77: =SUMIF($E$2:$Z$2,AB$2,$E77:$Z77) -> -53072.81 | AC77: =SUMIF($E$2:$Z$2,AC$2,$E77:$Z77) -> 0 | AD77: =SUMIF($E$2:$Z$2,AD$2,$E77:$Z77) -> 0 | AE77: =SUMIF($E$2:$Z$2,AE$2,$E77:$Z77) -> 0 | AF77: =SUMIF($E$2:$Z$2,AF$2,$E77:$Z77) -> 0 | AG77: =SUMIF($E$2:$Z$2,AG$2,$E77:$Z77) -> 0
B78: Deferred tax asset | F78: =-Assumptions!M129 -> 8827 | G78: =-Assumptions!N129 -> 0 | H78: =-Assumptions!O129 -> 0 | I78: =-Assumptions!P129 -> 0 | J78: =-Assumptions!Q129 -> 0 | K78: =-Assumptions!R129 -> 0 | L78: =-Assumptions!S129 -> 0 | M78: =-Assumptions!T129 -> 0 | ... Z78: =-Assumptions!AG129 -> 0 | AB78: =SUMIF($E$2:$Z$2,AB$2,$E78:$Z78) -> 8827 | AC78: =SUMIF($E$2:$Z$2,AC$2,$E78:$Z78) -> 0 | AD78: =SUMIF($E$2:$Z$2,AD$2,$E78:$Z78) -> 0 | AE78: =SUMIF($E$2:$Z$2,AE$2,$E78:$Z78) -> 0 | AF78: =SUMIF($E$2:$Z$2,AF$2,$E78:$Z78) -> 0 | AG78: =SUMIF($E$2:$Z$2,AG$2,$E78:$Z78) -> 0
B79: Growth and Fiscal levies | F79: =-Assumptions!M135 -> 37747 | G79: =-Assumptions!N135 -> 0 | H79: =-Assumptions!O135 -> 0 | I79: =-Assumptions!P135 -> 0 | J79: =-Assumptions!Q135 -> 0 | K79: =-Assumptions!R135 -> 0 | L79: =-Assumptions!S135 -> 0 | M79: =-Assumptions!T135 -> 0 | ... Z79: =-Assumptions!AG135 -> 0 | AB79: =SUMIF($E$2:$Z$2,AB$2,$E79:$Z79) -> 37747 | AC79: =SUMIF($E$2:$Z$2,AC$2,$E79:$Z79) -> 0 | AD79: =SUMIF($E$2:$Z$2,AD$2,$E79:$Z79) -> 0 | AE79: =SUMIF($E$2:$Z$2,AE$2,$E79:$Z79) -> 0 | AF79: =SUMIF($E$2:$Z$2,AF$2,$E79:$Z79) -> 0 | AG79: =SUMIF($E$2:$Z$2,AG$2,$E79:$Z79) -> 0
B80: Other assets | F80: =E42-F42 -> 1346116.4 | G80: =F42-G42 -> -95258.811 | H80: =G42-H42 -> -97067.267 | I80: =H42-I42 -> -98910.057 | J80: =I42-J42 -> -100787.83 | K80: =J42-K42 -> -102701.26 | L80: =K42-L42 -> -104651 | M80: =L42-M42 -> -106637.77 | ... Z80: =Y42-Z42 -> -136172.84 | AB80: =SUMIF($E$2:$Z$2,AB$2,$E80:$Z80) -> 1346116.4 | AC80: =SUMIF($E$2:$Z$2,AC$2,$E80:$Z80) -> -392023.97 | AD80: =SUMIF($E$2:$Z$2,AD$2,$E80:$Z80) -> -422652.28 | AE80: =SUMIF($E$2:$Z$2,AE$2,$E80:$Z80) -> -455673.54 | AF80: =SUMIF($E$2:$Z$2,AF$2,$E80:$Z80) -> -491274.72 | AG80: =SUMIF($E$2:$Z$2,AG$2,$E80:$Z80) -> -529657.36
B81: Total Deposits | F81: =F48-E48 -> 2808954.6 | G81: =G48-F48 -> 596816.24 | H81: =H48-G48 -> 618218.72 | I81: =I48-H48 -> 640388.71 | J81: =J48-I48 -> 663353.74 | K81: =K48-J48 -> 687142.32 | L81: =L48-K48 -> 711783.99 | M81: =M48-L48 -> 737309.33 | ... Z81: =Z48-Y48 -> 1165653.4 | AB81: =SUMIF($E$2:$Z$2,AB$2,$E81:$Z81) -> 2808954.6 | AC81: =SUMIF($E$2:$Z$2,AC$2,$E81:$Z81) -> 2518777.4 | AD81: =SUMIF($E$2:$Z$2,AD$2,$E81:$Z81) -> 2899985.7 | AE81: =SUMIF($E$2:$Z$2,AE$2,$E81:$Z81) -> 3338888.5 | AF81: =SUMIF($E$2:$Z$2,AF$2,$E81:$Z81) -> 3844217.8 | AG81: =SUMIF($E$2:$Z$2,AG$2,$E81:$Z81) -> 4426026.9
B82: Current tax liabilities | F82: =Assumptions!M184 -> 0 | G82: =Assumptions!N184 -> 0 | H82: =Assumptions!O184 -> 0 | I82: =Assumptions!P184 -> 0 | J82: =Assumptions!Q184 -> 0 | K82: =Assumptions!R184 -> 0 | L82: =Assumptions!S184 -> 0 | M82: =Assumptions!T184 -> 0 | ... Z82: =Assumptions!AG184 -> 0 | AB82: =SUMIF($E$2:$Z$2,AB$2,$E82:$Z82) -> 0 | AC82: =SUMIF($E$2:$Z$2,AC$2,$E82:$Z82) -> 0 | AD82: =SUMIF($E$2:$Z$2,AD$2,$E82:$Z82) -> 0 | AE82: =SUMIF($E$2:$Z$2,AE$2,$E82:$Z82) -> 0 | AF82: =SUMIF($E$2:$Z$2,AF$2,$E82:$Z82) -> 0 | AG82: =SUMIF($E$2:$Z$2,AG$2,$E82:$Z82) -> 0
B83: Deferred tax liabilities | F83: =Assumptions!M178 -> 173127.59 | G83: =Assumptions!N178 -> 0 | H83: =Assumptions!O178 -> 0 | I83: =Assumptions!P178 -> 0 | J83: =Assumptions!Q178 -> 0 | K83: =Assumptions!R178 -> 0 | L83: =Assumptions!S178 -> 0 | M83: =Assumptions!T178 -> 0 | ... Z83: =Assumptions!AG178 -> 0 | AB83: =SUMIF($E$2:$Z$2,AB$2,$E83:$Z83) -> 173127.59 | AC83: =SUMIF($E$2:$Z$2,AC$2,$E83:$Z83) -> 0 | AD83: =SUMIF($E$2:$Z$2,AD$2,$E83:$Z83) -> 0 | AE83: =SUMIF($E$2:$Z$2,AE$2,$E83:$Z83) -> 0 | AF83: =SUMIF($E$2:$Z$2,AF$2,$E83:$Z83) -> 0 | AG83: =SUMIF($E$2:$Z$2,AG$2,$E83:$Z83) -> 0
B84: Other liabilities | F84: =Assumptions!M192 -> 97937.188 | G84: =Assumptions!N192 -> 6036.7986 | H84: =Assumptions!O192 -> 6336.2791 | I84: =Assumptions!P192 -> 6650.6165 | J84: =Assumptions!Q192 -> 6980.548 | K84: =Assumptions!R192 -> 7326.8471 | L84: =Assumptions!S192 -> 7690.3258 | M84: =Assumptions!T192 -> 8071.8364 | ... Z84: =Assumptions!AG192 -> 15147.162 | AB84: =SUMIF($E$2:$Z$2,AB$2,$E84:$Z84) -> 97937.188 | AC84: =SUMIF($E$2:$Z$2,AC$2,$E84:$Z84) -> 26004.242 | AD84: =SUMIF($E$2:$Z$2,AD$2,$E84:$Z84) -> 31561.283 | AE84: =SUMIF($E$2:$Z$2,AE$2,$E84:$Z84) -> 38305.848 | AF84: =SUMIF($E$2:$Z$2,AF$2,$E84:$Z84) -> 46491.711 | AG84: =SUMIF($E$2:$Z$2,AG$2,$E84:$Z84) -> 56426.871
B85: Lease liabilities | F85: =F52-E52 -> 13725.151 | G85: =G52-F52 -> 3674.0814 | H85: =H52-G52 -> 4021.6219 | I85: =I52-H52 -> 4402.0372 | J85: =J52-I52 -> 4818.4368 | K85: =K52-J52 -> 5274.2248 | L85: =L52-K52 -> 5773.1269 | M85: =M52-L52 -> 6319.2214 | ... Z85: =Z52-Y52 -> 20461.884 | AB85: =SUMIF($E$2:$Z$2,AB$2,$E85:$Z85) -> 13725.151 | AC85: =SUMIF($E$2:$Z$2,AC$2,$E85:$Z85) -> 16916.177 | AD85: =SUMIF($E$2:$Z$2,AD$2,$E85:$Z85) -> 24283.545 | AE85: =SUMIF($E$2:$Z$2,AE$2,$E85:$Z85) -> 34859.564 | AF85: =SUMIF($E$2:$Z$2,AF$2,$E85:$Z85) -> 50041.673 | AG85: =SUMIF($E$2:$Z$2,AG$2,$E85:$Z85) -> 71835.925
B86: Cash used in operating activities | F86: =SUM(F69,F71:F73,F75:F85) -> 4931883.8 | G86: =SUM(G69,G71:G73,G75:G85) -> -1135997.7 | H86: =SUM(H69,H71:H73,H75:H85) -> 539127.06 | I86: =SUM(I69,I71:I73,I75:I85) -> 563403.18 | J86: =SUM(J69,J71:J73,J75:J85) -> 588672.06 | K86: =SUM(K69,K71:K73,K75:K85) -> 614972.89 | L86: =SUM(L69,L71:L73,L75:L85) -> 642346.45 | M86: =SUM(M69,M71:M73,M75:M85) -> 670835.17 | ... Z86: =SUM(Z69,Z71:Z73,Z75:Z85) -> 1165470.9 | AB86: =SUM(AB69,AB71:AB73,AB75:AB85) -> 4931883.8 | AC86: =SUM(AC69,AC71:AC73,AC75:AC85) -> 555204.64 | AD86: =SUM(AD69,AD71:AD73,AD75:AD85) -> 2628637.7 | AE86: =SUM(AE69,AE71:AE73,AE75:AE85) -> 3123247.2 | AF86: =SUM(AF69,AF71:AF73,AF75:AF85) -> 3703132.5 | AG86: =SUM(AG69,AG71:AG73,AG75:AG85) -> 4382753.1
B87: Tax and levies paid | F87: =Assumptions!M118 -> 0 | G87: =Assumptions!N118 -> -44555.86 | H87: =Assumptions!O118 -> -43887.138 | I87: =Assumptions!P118 -> -46129.751 | J87: =Assumptions!Q118 -> -48466.208 | K87: =Assumptions!R118 -> -50900.016 | L87: =Assumptions!S118 -> -53434.798 | M87: =Assumptions!T118 -> -56074.293 | ... Z87: =Assumptions!AG118 -> -101848.58 | AB87: =SUMIF($E$2:$Z$2,AB$2,$E87:$Z87) -> 0 | AC87: =SUMIF($E$2:$Z$2,AC$2,$E87:$Z87) -> -183038.96 | AD87: =SUMIF($E$2:$Z$2,AD$2,$E87:$Z87) -> -219231.47 | AE87: =SUMIF($E$2:$Z$2,AE$2,$E87:$Z87) -> -265083.81 | AF87: =SUMIF($E$2:$Z$2,AF$2,$E87:$Z87) -> -318828.85 | AG87: =SUMIF($E$2:$Z$2,AG$2,$E87:$Z87) -> -381654.19
B88: Net cash generated from operating activities | F88: =SUM(F86:F87) -> 4931883.8 | G88: =SUM(G86:G87) -> -1180553.5 | H88: =SUM(H86:H87) -> 495239.92 | I88: =SUM(I86:I87) -> 517273.43 | J88: =SUM(J86:J87) -> 540205.85 | K88: =SUM(K86:K87) -> 564072.87 | L88: =SUM(L86:L87) -> 588911.65 | M88: =SUM(M86:M87) -> 614760.88 | ... Z88: =SUM(Z86:Z87) -> 1063622.4 | AB88: =SUM(AB86:AB87) -> 4931883.8 | AC88: =SUM(AC86:AC87) -> 372165.68 | AD88: =SUM(AD86:AD87) -> 2409406.2 | AE88: =SUM(AE86:AE87) -> 2858163.4 | AF88: =SUM(AF86:AF87) -> 3384303.7 | AG88: =SUM(AG86:AG87) -> 4001098.9
B90: Cash flows from investing activities
B91: Purchase of property and equipment | F91: =-Assumptions!M152 -> 1941.704 | G91: =-Assumptions!N152 -> -6745.9 | H91: =-Assumptions!O152 -> -6751.9352 | I91: =-Assumptions!P152 -> -6757.9759 | J91: =-Assumptions!Q152 -> -6764.022 | K91: =-Assumptions!R152 -> -6770.0734 | L91: =-Assumptions!S152 -> -6776.1303 | M91: =-Assumptions!T152 -> -6782.1926 | ... Z91: =-Assumptions!AG152 -> -6861.498 | AB91: =SUMIF($E$2:$Z$2,AB$2,$E91:$Z91) -> 1941.704 | AC91: =SUMIF($E$2:$Z$2,AC$2,$E91:$Z91) -> -27019.833 | AD91: =SUMIF($E$2:$Z$2,AD$2,$E91:$Z91) -> -27116.657 | AE91: =SUMIF($E$2:$Z$2,AE$2,$E91:$Z91) -> -27213.827 | AF91: =SUMIF($E$2:$Z$2,AF$2,$E91:$Z91) -> -27311.346 | AG91: =SUMIF($E$2:$Z$2,AG$2,$E91:$Z91) -> -27409.215
B92: Purchase of Right-of-Use Assets | F92: =-Assumptions!M161 -> -16713.09 | G92: =-Assumptions!N161 -> 0 | H92: =-Assumptions!O161 -> 0 | I92: =-Assumptions!P161 -> 0 | J92: =-Assumptions!Q161 -> 0 | K92: =-Assumptions!R161 -> 0 | L92: =-Assumptions!S161 -> 0 | M92: =-Assumptions!T161 -> 0 | ... Z92: =-Assumptions!AG161 -> 0 | AB92: =SUMIF($E$2:$Z$2,AB$2,$E92:$Z92) -> -16713.09 | AC92: =SUMIF($E$2:$Z$2,AC$2,$E92:$Z92) -> 0 | AD92: =SUMIF($E$2:$Z$2,AD$2,$E92:$Z92) -> 0 | AE92: =SUMIF($E$2:$Z$2,AE$2,$E92:$Z92) -> 0 | AF92: =SUMIF($E$2:$Z$2,AF$2,$E92:$Z92) -> 0 | AG92: =SUMIF($E$2:$Z$2,AG$2,$E92:$Z92) -> 0
B93: Purchase of intangible assets | F93: =-Assumptions!M143 -> -3305.727 | G93: =-Assumptions!N143 -> -1766.3489 | H93: =-Assumptions!O143 -> -1783.2274 | I93: =-Assumptions!P143 -> -1800.2672 | J93: =-Assumptions!Q143 -> -1817.4699 | K93: =-Assumptions!R143 -> -1834.8369 | L93: =-Assumptions!S143 -> -1852.3699 | M93: =-Assumptions!T143 -> -1870.0704 | ... Z93: =-Assumptions!AG143 -> -2116.1727 | AB93: =SUMIF($E$2:$Z$2,AB$2,$E93:$Z93) -> -3305.727 | AC93: =SUMIF($E$2:$Z$2,AC$2,$E93:$Z93) -> -7167.3134 | AD93: =SUMIF($E$2:$Z$2,AD$2,$E93:$Z93) -> -7445.2171 | AE93: =SUMIF($E$2:$Z$2,AE$2,$E93:$Z93) -> -7733.8963 | AF93: =SUMIF($E$2:$Z$2,AF$2,$E93:$Z93) -> -8033.7686 | AG93: =SUMIF($E$2:$Z$2,AG$2,$E93:$Z93) -> -8345.268
B94: Investment in associates | F94: =-Assumptions!M104 -> -294.382 | G94: =-Assumptions!N104 -> 0 | H94: =-Assumptions!O104 -> 0 | I94: =-Assumptions!P104 -> 0 | J94: =-Assumptions!Q104 -> 0 | K94: =-Assumptions!R104 -> 0 | L94: =-Assumptions!S104 -> 0 | M94: =-Assumptions!T104 -> 0 | ... Z94: =-Assumptions!AG104 -> 0 | AB94: =SUMIF($E$2:$Z$2,AB$2,$E94:$Z94) -> -294.382 | AC94: =SUMIF($E$2:$Z$2,AC$2,$E94:$Z94) -> 0 | AD94: =SUMIF($E$2:$Z$2,AD$2,$E94:$Z94) -> 0 | AE94: =SUMIF($E$2:$Z$2,AE$2,$E94:$Z94) -> 0 | AF94: =SUMIF($E$2:$Z$2,AF$2,$E94:$Z94) -> 0 | AG94: =SUMIF($E$2:$Z$2,AG$2,$E94:$Z94) -> 0
B95: Investment in subsidiary | F95: =-Assumptions!M110 -> 3025 | G95: =-Assumptions!N110 -> 0 | H95: =-Assumptions!O110 -> 0 | I95: =-Assumptions!P110 -> 0 | J95: =-Assumptions!Q110 -> 0 | K95: =-Assumptions!R110 -> 0 | L95: =-Assumptions!S110 -> 0 | M95: =-Assumptions!T110 -> 0 | ... Z95: =-Assumptions!AG110 -> 0 | AB95: =SUMIF($E$2:$Z$2,AB$2,$E95:$Z95) -> 3025 | AC95: =SUMIF($E$2:$Z$2,AC$2,$E95:$Z95) -> 0 | AD95: =SUMIF($E$2:$Z$2,AD$2,$E95:$Z95) -> 0 | AE95: =SUMIF($E$2:$Z$2,AE$2,$E95:$Z95) -> 0 | AF95: =SUMIF($E$2:$Z$2,AF$2,$E95:$Z95) -> 0 | AG95: =SUMIF($E$2:$Z$2,AG$2,$E95:$Z95) -> 0
B96: Net cash flows from investing activities | F96: =SUM(F91:F95) -> -15346.495 | G96: =SUM(G91:G95) -> -8512.2489 | H96: =SUM(H91:H95) -> -8535.1627 | I96: =SUM(I91:I95) -> -8558.2431 | J96: =SUM(J91:J95) -> -8581.4918 | K96: =SUM(K91:K95) -> -8604.9103 | L96: =SUM(L91:L95) -> -8628.5002 | M96: =SUM(M91:M95) -> -8652.263 | ... Z96: =SUM(Z91:Z95) -> -8977.6707 | AB96: =SUM(AB91:AB95) -> -15346.495 | AC96: =SUM(AC91:AC95) -> -34187.146 | AD96: =SUM(AD91:AD95) -> -34561.874 | AE96: =SUM(AE91:AE95) -> -34947.724 | AF96: =SUM(AF91:AF95) -> -35345.115 | AG96: =SUM(AG91:AG95) -> -35754.483
B98: Cash flows from financing activities
B99: Changes in:
B100: Stated capital | F100: =-Assumptions!M210 -> -204318.15 | G100: =-Assumptions!N210 -> 0 | H100: =-Assumptions!O210 -> 0 | I100: =-Assumptions!P210 -> 0 | J100: =-Assumptions!Q210 -> 0 | K100: =-Assumptions!R210 -> 0 | L100: =-Assumptions!S210 -> 0 | M100: =-Assumptions!T210 -> 0 | ... Z100: =-Assumptions!AG210 -> 0 | AB100: =SUMIF($E$2:$Z$2,AB$2,$E100:$Z100) -> -204318.15 | AC100: =SUMIF($E$2:$Z$2,AC$2,$E100:$Z100) -> 0 | AD100: =SUMIF($E$2:$Z$2,AD$2,$E100:$Z100) -> 0 | AE100: =SUMIF($E$2:$Z$2,AE$2,$E100:$Z100) -> 0 | AF100: =SUMIF($E$2:$Z$2,AF$2,$E100:$Z100) -> 0 | AG100: =SUMIF($E$2:$Z$2,AG$2,$E100:$Z100) -> 0
B101: Revaluation reserve | F101: =-Assumptions!M223 -> -0.414 | G101: =-Assumptions!N223 -> 0 | H101: =-Assumptions!O223 -> 0 | I101: =-Assumptions!P223 -> 0 | J101: =-Assumptions!Q223 -> 0 | K101: =-Assumptions!R223 -> 0 | L101: =-Assumptions!S223 -> 0 | M101: =-Assumptions!T223 -> 0 | ... Z101: =-Assumptions!AG223 -> 0 | AB101: =SUMIF($E$2:$Z$2,AB$2,$E101:$Z101) -> -0.414 | AC101: =SUMIF($E$2:$Z$2,AC$2,$E101:$Z101) -> 0 | AD101: =SUMIF($E$2:$Z$2,AD$2,$E101:$Z101) -> 0 | AE101: =SUMIF($E$2:$Z$2,AE$2,$E101:$Z101) -> 0 | AF101: =SUMIF($E$2:$Z$2,AF$2,$E101:$Z101) -> 0 | AG101: =SUMIF($E$2:$Z$2,AG$2,$E101:$Z101) -> 0
B102: Statutory reserve fund | F102: =-Assumptions!M229 -> -120901.92 | G102: =-Assumptions!N229 -> 0 | H102: =-Assumptions!O229 -> 0 | I102: =-Assumptions!P229 -> 0 | J102: =-Assumptions!Q229 -> 0 | K102: =-Assumptions!R229 -> 0 | L102: =-Assumptions!S229 -> 0 | M102: =-Assumptions!T229 -> 0 | ... Z102: =-Assumptions!AG229 -> 0 | AB102: =SUMIF($E$2:$Z$2,AB$2,$E102:$Z102) -> -120901.92 | AC102: =SUMIF($E$2:$Z$2,AC$2,$E102:$Z102) -> 0 | AD102: =SUMIF($E$2:$Z$2,AD$2,$E102:$Z102) -> 0 | AE102: =SUMIF($E$2:$Z$2,AE$2,$E102:$Z102) -> 0 | AF102: =SUMIF($E$2:$Z$2,AF$2,$E102:$Z102) -> 0 | AG102: =SUMIF($E$2:$Z$2,AG$2,$E102:$Z102) -> 0
B103: Credit risk reserve | F103: =-Assumptions!M235 -> -6669.754 | G103: =-Assumptions!N235 -> 0 | H103: =-Assumptions!O235 -> 0 | I103: =-Assumptions!P235 -> 0 | J103: =-Assumptions!Q235 -> 0 | K103: =-Assumptions!R235 -> 0 | L103: =-Assumptions!S235 -> 0 | M103: =-Assumptions!T235 -> 0 | ... Z103: =-Assumptions!AG235 -> 0 | AB103: =SUMIF($E$2:$Z$2,AB$2,$E103:$Z103) -> -6669.754 | AC103: =SUMIF($E$2:$Z$2,AC$2,$E103:$Z103) -> 0 | AD103: =SUMIF($E$2:$Z$2,AD$2,$E103:$Z103) -> 0 | AE103: =SUMIF($E$2:$Z$2,AE$2,$E103:$Z103) -> 0 | AF103: =SUMIF($E$2:$Z$2,AF$2,$E103:$Z103) -> 0 | AG103: =SUMIF($E$2:$Z$2,AG$2,$E103:$Z103) -> 0
B104: Other reserves | F104: =-Assumptions!M241 -> 0 | G104: =-Assumptions!N241 -> 0 | H104: =-Assumptions!O241 -> 0 | I104: =-Assumptions!P241 -> 0 | J104: =-Assumptions!Q241 -> 0 | K104: =-Assumptions!R241 -> 0 | L104: =-Assumptions!S241 -> 0 | M104: =-Assumptions!T241 -> 0 | ... Z104: =-Assumptions!AG241 -> 0 | AB104: =SUMIF($E$2:$Z$2,AB$2,$E104:$Z104) -> 0 | AC104: =SUMIF($E$2:$Z$2,AC$2,$E104:$Z104) -> 0 | AD104: =SUMIF($E$2:$Z$2,AD$2,$E104:$Z104) -> 0 | AE104: =SUMIF($E$2:$Z$2,AE$2,$E104:$Z104) -> 0 | AF104: =SUMIF($E$2:$Z$2,AF$2,$E104:$Z104) -> 0 | AG104: =SUMIF($E$2:$Z$2,AG$2,$E104:$Z104) -> 0
B105: Dividends Paid | F105: =Assumptions!M217 -> -129654.12 | G105: =Assumptions!N217 -> -45192.948 | H105: =Assumptions!O217 -> -44514.664 | I105: =Assumptions!P217 -> -46789.344 | J105: =Assumptions!Q217 -> -49159.209 | K105: =Assumptions!R217 -> -51627.817 | L105: =Assumptions!S217 -> -54198.842 | M105: =Assumptions!T217 -> -56876.079 | ... Z105: =Assumptions!AG217 -> -103304.88 | AB105: =SUMIF($E$2:$Z$2,AB$2,$E105:$Z105) -> -129654.12 | AC105: =SUMIF($E$2:$Z$2,AC$2,$E105:$Z105) -> -185656.16 | AD105: =SUMIF($E$2:$Z$2,AD$2,$E105:$Z105) -> -222366.18 | AE105: =SUMIF($E$2:$Z$2,AE$2,$E105:$Z105) -> -268874.15 | AF105: =SUMIF($E$2:$Z$2,AF$2,$E105:$Z105) -> -323387.67 | AG105: =SUMIF($E$2:$Z$2,AG$2,$E105:$Z105) -> -387111.32
B106: Net cash generated from financing activities | F106: =SUM(F100:F105) -> -461544.36 | G106: =SUM(G100:G105) -> -45192.948 | H106: =SUM(H100:H105) -> -44514.664 | I106: =SUM(I100:I105) -> -46789.344 | J106: =SUM(J100:J105) -> -49159.209 | K106: =SUM(K100:K105) -> -51627.817 | L106: =SUM(L100:L105) -> -54198.842 | M106: =SUM(M100:M105) -> -56876.079 | ... Z106: =SUM(Z100:Z105) -> -103304.88 | AB106: =SUM(AB100:AB105) -> -461544.36 | AC106: =SUM(AC100:AC105) -> -185656.16 | AD106: =SUM(AD100:AD105) -> -222366.18 | AE106: =SUM(AE100:AE105) -> -268874.15 | AF106: =SUM(AF100:AF105) -> -323387.67 | AG106: =SUM(AG100:AG105) -> -387111.32
B108: Net increase/decrease in cash and cash equivalents | F108: =F88+F96+F106 -> 4454992.9 | G108: =G88+G96+G106 -> -1234258.7 | H108: =H88+H96+H106 -> 442190.09 | I108: =I88+I96+I106 -> 461925.85 | J108: =J88+J96+J106 -> 482465.15 | K108: =K88+K96+K106 -> 503840.15 | L108: =L88+L96+L106 -> 526084.31 | M108: =M88+M96+M106 -> 549232.54 | ... Z108: =Z88+Z96+Z106 -> 951339.8 | AB108: =AB88+AB96+AB106 -> 4454992.9 | AC108: =AC88+AC96+AC106 -> 152322.37 | AD108: =AD88+AD96+AD106 -> 2152478.2 | AE108: =AE88+AE96+AE106 -> 2554341.5 | AF108: =AF88+AF96+AF106 -> 3025570.9 | AG108: =AG88+AG96+AG106 -> 3578233.1
B109: Adjustments | F109: =-(F108+F110-(F63-SUM(F34:F44))) -> 394538.64 | G109: =-(G108+G110-(G63-SUM(G34:G44))) -> -35953.32 | H109: =-(H108+H110-(H63-SUM(H34:H44))) -> -39223.326 | I109: =-(I108+I110-(I63-SUM(I34:I44))) -> -40629.917 | J109: =-(J108+J110-(J63-SUM(J34:J44))) -> -42086.949 | K109: =-(K108+K110-(K63-SUM(K34:K44))) -> -43596.233 | L109: =-(L108+L110-(L63-SUM(L34:L44))) -> -45159.641 | M109: =-(M108+M110-(M63-SUM(M34:M44))) -> -46779.114 | ... Z109: =-(Z108+Z110-(Z63-SUM(Z34:Z44))) -> -73955.71 | AB109: =SUMIF($E$2:$Z$2,AB$2,$E109:$Z109) -> 394538.64 | AC109: =SUMIF($E$2:$Z$2,AC$2,$E109:$Z109) -> -157893.51 | AD109: =SUMIF($E$2:$Z$2,AD$2,$E109:$Z109) -> -183991.65 | AE109: =SUMIF($E$2:$Z$2,AE$2,$E109:$Z109) -> -211838.15 | AF109: =SUMIF($E$2:$Z$2,AF$2,$E109:$Z109) -> -243899.13 | AG109: =SUMIF($E$2:$Z$2,AG$2,$E109:$Z109) -> -280812.42
B110: Cash and cash equivalents at start of period | F110: =E111 -> 3312929 | G110: =F111 -> 8162460.5 | H110: =G111 -> 6892248.5 | I110: =H111 -> 7295215.3 | J110: =I111 -> 7716511.2 | K110: =J111 -> 8156889.4 | L110: =K111 -> 8617133.3 | M110: =L111 -> 9098058 | ... Z110: =Y111 -> 17669588 | AB110: =SUMIF($E$4:$Z$4,AB$4,$E110:$Z110) -> 3312929 | AC110: =AB111 -> 8162460.5 | AD110: =AC111 -> 8156889.4 | AE110: =AD111 -> 10125376 | AF110: =AE111 -> 12467879 | AG110: =AF111 -> 15249551
...

Sheet Assumptions
D1: FIRST ATLANTIC BANK LIMITED
D2: Scenario>>>>> | E2: All amounts in thousands of GHS unless stated otherwise | J2: Year | M2: =YEAR(M4) -> 2025 | N2: =YEAR(N4) -> 2026 | O2: =YEAR(O4) -> 2026 | P2: =YEAR(P4) -> 2026 | Q2: =YEAR(Q4) -> 2026 | R2: =YEAR(R4) -> 2027 | S2: =YEAR(S4) -> 2027 | T2: =YEAR(T4) -> 2027 | ... AG2: =YEAR(AG4) -> 2030 | AI2: =YEAR(AI4) -> 2025 | AJ2: =YEAR(AJ4) -> 2026 | AK2: =YEAR(AK4) -> 2027 | AL2: =YEAR(AL4) -> 2028 | AM2: =YEAR(AM4) -> 2029 | AN2: =YEAR(AN4) -> 2030
D3: Conservative | F3: 1 | J3: Start Date | M3: =H8 -> 45931 | N3: =M4+1 -> 46023 | O3: =N4+1 -> 46113 | P3: =O4+1 -> 46204 | Q3: =P4+1 -> 46296 | R3: =Q4+1 -> 46388 | S3: =R4+1 -> 46478 | T3: =S4+1 -> 46569 | U3: =T4+1 -> 46661 | ... AG3: =AF4+1 -> 47757 | AI3: =M3 -> 45931 | AJ3: =AI4+1 -> 46023 | AK3: =AJ4+1 -> 46388 | AL3: =AK4+1 -> 46753 | AM3: =AL4+1 -> 47119 | AN3: =AM4+1 -> 47484
D4: Moderate | F4: 2 | G4: 1 | J4: End Date | M4: =EOMONTH(M3,2) -> 46022 | N4: =EOMONTH(N3,2) -> 46112 | O4: =EOMONTH(O3,2) -> 46203 | P4: =EOMONTH(P3,2) -> 46295 | Q4: =EOMONTH(Q3,2) -> 46387 | R4: =EOMONTH(R3,2) -> 46477 | S4: =EOMONTH(S3,2) -> 46568 | T4: =EOMONTH(T3,2) -> 46660 | ... AG4: =EOMONTH(AG3,2) -> 47848 | AI4: =EOMONTH(AI3,2) -> 46022 | AJ4: =EOMONTH(AJ3,11) -> 46387 | AK4: =EOMONTH(AK3,11) -> 46752 | AL4: =EOMONTH(AL3,11) -> 47118 | AM4: =EOMONTH(AM3,11) -> 47483 | AN4: =EOMONTH(AN3,11) -> 47848
D5: Optimistic | F5: 3 | J5: Period | M5: =M4-M3+1 -> 92 | N5: =N4-N3+1 -> 90 | O5: =O4-O3+1 -> 91 | P5: =P4-P3+1 -> 92 | Q5: =Q4-Q3+1 -> 92 | R5: =R4-R3+1 -> 90 | S5: =S4-S3+1 -> 91 | T5: =T4-T3+1 -> 92 | ... AG5: =AG4-AG3+1 -> 92 | AI5: =AI4-AI3+1 -> 92 | AJ5: =AJ4-AJ3+1 -> 365 | AK5: =AK4-AK3+1 -> 365 | AL5: =AL4-AL3+1 -> 366 | AM5: =AM4-AM3+1 -> 365 | AN5: =AN4-AN3+1 -> 365
B7: 1 | D7: General Model Assumptions
D8: Start Date | H8: ='Quarterly Historical Financials'!AB4+1 -> 45931
B13: 2 | D13: Interest Assumptions
D14: Interest Income | E14: Unit | F14: Conservative | G14: Moderate | H14: Optimistic | I14: Live
D15: Interest Rate | E15: % of gen. assets | F15: =AVERAGE('Quarterly Historical Financials'!$D94:$D95) -> 0.027623396 | G15: =AVERAGE('Quarterly Historical Financials'!$D93:$D95) -> 0.029276024 | H15: =AVERAGE('Quarterly Historical Financials'!$D92:$D95) -> 0.034839546 | I15: =CHOOSE($G$4,F15,G15,H15) -> 0.027623396
K16: Cash and cash equivalents | M16: ='Quarterly Financial Projections'!F33 -> 8162460.5 | N16: ='Quarterly Financial Projections'!G33 -> 6892248.5 | O16: ='Quarterly Financial Projections'!H33 -> 7295215.3 | P16: ='Quarterly Financial Projections'!I33 -> 7716511.2 | Q16: ='Quarterly Financial Projections'!J33 -> 8156889.4 | R16: ='Quarterly Financial Projections'!K33 -> 8617133.3 | S16: ='Quarterly Financial Projections'!L33 -> 9098058 | T16: ='Quarterly Financial Projections'!M33 -> 9600511.4 | ... AG16: ='Quarterly Financial Projections'!Z33 -> 18546972 | AI16: =SUMIF($M$4:$AG$4,AI$4,$M16:$AG16) -> 8162460.5 | AJ16: =SUMIF($M$4:$AG$4,AJ$4,$M16:$AG16) -> 8156889.4 | AK16: =SUMIF($M$4:$AG$4,AK$4,$M16:$AG16) -> 10125376 | AL16: =SUMIF($M$4:$AG$4,AL$4,$M16:$AG16) -> 12467879 | AM16: =SUMIF($M$4:$AG$4,AM$4,$M16:$AG16) -> 15249551 | AN16: =SUMIF($M$4:$AG$4,AN$4,$M16:$AG16) -> 18546972
K17: Trading assets (Investment securities) | M17: =M99 -> 3178870.4 | N17: =N99 -> 4086092.7 | O17: =O99 -> 4232624.4 | P17: =P99 -> 4384410.9 | Q17: =Q99 -> 4541640.6 | R17: =R99 -> 4704508.7 | S17: =S99 -> 4873217.5 | T17: =T99 -> 5047976.3 | ... AG17: =AG99 -> 7980627.2 | AI17: =SUMIF($M$4:$AG$4,AI$4,$M17:$AG17) -> 3178870.4 | AJ17: =SUMIF($M$4:$AG$4,AJ$4,$M17:$AG17) -> 4541640.6 | AK17: =SUMIF($M$4:$AG$4,AK$4,$M17:$AG17) -> 5229002.2 | AL17: =SUMIF($M$4:$AG$4,AL$4,$M17:$AG17) -> 6020393.7 | AM17: =SUMIF($M$4:$AG$4,AM$4,$M17:$AG17) -> 6931559.6 | AN17: =SUMIF($M$4:$AG$4,AN$4,$M17:$AG17) -> 7980627.2
K18: Loans and advances to customers | M18: =M94 -> 1947024.8 | N18: =N94 -> 2936526.5 | O18: =O94 -> 3041833.5 | P18: =P94 -> 3150917 | Q18: =Q94 -> 3263912.3 | R18: =R94 -> 3380959.7 | S18: =S94 -> 3502204.6 | T18: =T94 -> 3627797.4 | ... AG18: =AG94 -> 5735387.1 | AI18: =SUMIF($M$4:$AG$4,AI$4,$M18:$AG18) -> 1947024.8 | AJ18: =SUMIF($M$4:$AG$4,AJ$4,$M18:$AG18) -> 3263912.3 | AK18: =SUMIF($M$4:$AG$4,AK$4,$M18:$AG18) -> 3757894.1 | AL18: =SUMIF($M$4:$AG$4,AL$4,$M18:$AG18) -> 4326638.5 | AM18: =SUMIF($M$4:$AG$4,AM$4,$M18:$AG18) -> 4981460.3 | AN18: =SUMIF($M$4:$AG$4,AN$4,$M18:$AG18) -> 5735387.1
K19: Total Income generating assets | M19: =SUM(M16:M18) -> 13288356 | N19: =SUM(N16:N18) -> 13914868 | O19: =SUM(O16:O18) -> 14569673 | P19: =SUM(P16:P18) -> 15251839 | Q19: =SUM(Q16:Q18) -> 15962442 | R19: =SUM(R16:R18) -> 16702602 | S19: =SUM(S16:S18) -> 17473480 | T19: =SUM(T16:T18) -> 18276285 | ... AG19: =SUM(AG16:AG18) -> 32262986 | AI19: =SUM(AI16:AI18) -> 13288356 | AJ19: =SUM(AJ16:AJ18) -> 15962442 | AK19: =SUM(AK16:AK18) -> 19112272 | AL19: =SUM(AL16:AL18) -> 22814911 | AM19: =SUM(AM16:AM18) -> 27162571 | AN19: =SUM(AN16:AN18) -> 32262986
K21: Interest Income | M21: ='Quarterly Historical Financials'!AC9 -> 681759.57 | N21: =N19*$I$15 -> 384375.91 | O21: =O19*$I$15 -> 402463.86 | P21: =P19*$I$15 -> 421307.6 | Q21: =Q19*$I$15 -> 440936.87 | R21: =R19*$I$15 -> 461382.59 | S21: =S19*$I$15 -> 482676.87 | T21: =T19*$I$15 -> 504853.07 | U21: =U19*$I$15 -> 527945.88 | ... AG21: =AG19*$I$15 -> 891213.25 | AI21: =SUMIF($M$2:$AG$2,AI$2,$M21:$AG21) -> 681759.57 | AJ21: =SUMIF($M$2:$AG$2,AJ$2,$M21:$AG21) -> 1649084.2 | AK21: =SUMIF($M$2:$AG$2,AK$2,$M21:$AG21) -> 1976858.4 | AL21: =SUMIF($M$2:$AG$2,AL$2,$M21:$AG21) -> 2362334.8 | AM21: =SUMIF($M$2:$AG$2,AM$2,$M21:$AG21) -> 2815137.9 | AN21: =SUMIF($M$2:$AG$2,AN$2,$M21:$AG21) -> 3346506.3
D24: Interest Expense | E24: Unit | F24: Conservative | G24: Moderate | H24: Optimistic | I24: Live
D25: Interest Rate | E25: % of incur. liab. | F25: =AVERAGE('Quarterly Historical Financials'!$D107:$D108) -> -0.0060437957 | G25: =AVERAGE('Quarterly Historical Financials'!$D106:$D107)/1.2 -> -0.0061649646 | H25: =AVERAGE('Quarterly Historical Financials'!$D105:$D106)/1.3 -> -0.0069636484 | I25: =CHOOSE($G$4,F25,G25,H25) -> -0.0060437957
K26: Total Deposits | M26: =M85 -> 16642450 | N26: =N85 -> 17239266 | O26: =O85 -> 17857485 | P26: =P85 -> 18497873 | Q26: =Q85 -> 19161227 | R26: =R85 -> 19848369 | S26: =S85 -> 20560153 | T26: =T85 -> 21297463 | ... AG26: =AG85 -> 33670346 | AI26: =SUMIF($M$4:$AG$4,AI$4,$M26:$AG26) -> 16642450 | AJ26: =SUMIF($M$4:$AG$4,AJ$4,$M26:$AG26) -> 19161227 | AK26: =SUMIF($M$4:$AG$4,AK$4,$M26:$AG26) -> 22061213 | AL26: =SUMIF($M$4:$AG$4,AL$4,$M26:$AG26) -> 25400101 | AM26: =SUMIF($M$4:$AG$4,AM$4,$M26:$AG26) -> 29244319 | AN26: =SUMIF($M$4:$AG$4,AN$4,$M26:$AG26) -> 33670346
K27: Total expense incurring liabilities | M27: =SUM(M26:M26) -> 16642450 | N27: =SUM(N26:N26) -> 17239266 | O27: =SUM(O26:O26) -> 17857485 | P27: =SUM(P26:P26) -> 18497873 | Q27: =SUM(Q26:Q26) -> 19161227 | R27: =SUM(R26:R26) -> 19848369 | S27: =SUM(S26:S26) -> 20560153 | T27: =SUM(T26:T26) -> 21297463 | ... AG27: =SUM(AG26:AG26) -> 33670346 | AI27: =SUM(AI26:AI26) -> 16642450 | AJ27: =SUM(AJ26:AJ26) -> 19161227 | AK27: =SUM(AK26:AK26) -> 22061213 | AL27: =SUM(AL26:AL26) -> 25400101 | AM27: =SUM(AM26:AM26) -> 29244319 | AN27: =SUM(AN26:AN26) -> 33670346
K29: Interest Expense | M29: ='Quarterly Historical Financials'!AC10 -> -102371.52 | N29: =N27*$I25 -> -104190.6 | O29: =O27*$I25 -> -107926.99 | P29: =P27*$I25 -> -111797.37 | Q29: =Q27*$I25 -> -115806.54 | R29: =R27*$I25 -> -119959.49 | S29: =S27*$I25 -> -124261.37 | T29: =T27*$I25 -> -128717.51 | U29: =U27*$I25 -> -133333.46 | ... AG29: =AG27*$I25 -> -203496.69 | AI29: =SUMIF($M$2:$AG$2,AI$2,$M29:$AG29) -> -102371.52 | AJ29: =SUMIF($M$2:$AG$2,AJ$2,$M29:$AG29) -> -439721.5 | AK29: =SUMIF($M$2:$AG$2,AK$2,$M29:$AG29) -> -506271.83 | AL29: =SUMIF($M$2:$AG$2,AL$2,$M29:$AG29) -> -582894.33 | AM29: =SUMIF($M$2:$AG$2,AM$2,$M29:$AG29) -> -671113.38 | AN29: =SUMIF($M$2:$AG$2,AN$2,$M29:$AG29) -> -772684.07
B32: 3 | D32: Fees & Commissions Assumptions
D33: Fees & Commission Income | E33: Unit | F33: Conservative | G33: Moderate | H33: Optimistic | I33: Live
D34: Income rate | E34: % of gen. assets | F34: =AVERAGE('Quarterly Historical Financials'!$D124:$D125) -> 0.0039583729 | G34: =AVERAGE('Quarterly Historical Financials'!$D123:$D124) -> 0.0055470728 | H34: =AVERAGE('Quarterly Historical Financials'!$D122:$D123)/1.2 -> 0.0072811603 | I34: =CHOOSE($G$4,F34,G34,H34) -> 0.0039583729
K35: Loan Disbursement | M35: =M90 -> 608840.22 | N35: =N90 -> 1015508.2 | O35: =O90 -> 144530.34 | P35: =P90 -> 149713.36 | Q35: =Q90 -> 155082.24 | R35: =R90 -> 160643.66 | S35: =S90 -> 166404.51 | T35: =T90 -> 172371.96 | ... AG35: =AG90 -> 272512.44 | AI35: =SUMIF($M$2:$AG$2,AI$2,$M35:$AG35) -> 608840.22 | AJ35: =SUMIF($M$2:$AG$2,AJ$2,$M35:$AG35) -> 1464834.1 | AK35: =SUMIF($M$2:$AG$2,AK$2,$M35:$AG35) -> 677973.53 | AL35: =SUMIF($M$2:$AG$2,AL$2,$M35:$AG35) -> 780582.48 | AM35: =SUMIF($M$2:$AG$2,AM$2,$M35:$AG35) -> 898720.95 | AN35: =SUMIF($M$2:$AG$2,AN$2,$M35:$AG35) -> 1034739.3
K36: Total Deposit | M36: =M85 -> 16642450 | N36: =N85 -> 17239266 | O36: =O85 -> 17857485 | P36: =P85 -> 18497873 | Q36: =Q85 -> 19161227 | R36: =R85 -> 19848369 | S36: =S85 -> 20560153 | T36: =T85 -> 21297463 | ... AG36: =AG85 -> 33670346 | AI36: =SUMIF($M$4:$AG$4,AI$4,$M36:$AG36) -> 16642450 | AJ36: =SUMIF($M$4:$AG$4,AJ$4,$M36:$AG36) -> 19161227 | AK36: =SUMIF($M$4:$AG$4,AK$4,$M36:$AG36) -> 22061213 | AL36: =SUMIF($M$4:$AG$4,AL$4,$M36:$AG36) -> 25400101 | AM36: =SUMIF($M$4:$AG$4,AM$4,$M36:$AG36) -> 29244319 | AN36: =SUMIF($M$4:$AG$4,AN$4,$M36:$AG36) -> 33670346
K37: Total Income generating assets | M37: =SUM(M35:M36) -> 17251290 | N37: =SUM(N35:N36) -> 18254774 | O37: =SUM(O35:O36) -> 18002015 | P37: =SUM(P35:P36) -> 18647587 | Q37: =SUM(Q35:Q36) -> 19316309 | R37: =SUM(R35:R36) -> 20009013 | S37: =SUM(S35:S36) -> 20726558 | T37: =SUM(T35:T36) -> 21469835 | ... AG37: =SUM(AG35:AG36) -> 33942858 | AI37: =SUM(AI35:AI36) -> 17251290 | AJ37: =SUM(AJ35:AJ36) -> 20626061 | AK37: =SUM(AK35:AK36) -> 22739186 | AL37: =SUM(AL35:AL36) -> 26180684 | AM37: =SUM(AM35:AM36) -> 30143040 | AN37: =SUM(AN35:AN36) -> 34705085
K39: Fees & Commission Income | M39: ='Quarterly Historical Financials'!AC12 -> 76446.237 | N39: =N37*$I34 -> 72259.202 | O39: =O37*$I34 -> 71258.687 | P39: =P37*$I34 -> 73814.101 | Q39: =Q37*$I34 -> 76461.154 | R39: =R37*$I34 -> 79203.134 | S39: =S37*$I34 -> 82043.444 | T39: =T37*$I34 -> 84985.61 | U39: =U37*$I34 -> 88033.286 | ... AG39: =AG37*$I34 -> 134358.49 | AI39: =SUMIF($M$2:$AG$2,AI$2,$M39:$AG39) -> 76446.237 | AJ39: =SUMIF($M$2:$AG$2,AJ$2,$M39:$AG39) -> 293793.14 | AK39: =SUMIF($M$2:$AG$2,AK$2,$M39:$AG39) -> 334265.47 | AL39: =SUMIF($M$2:$AG$2,AL$2,$M39:$AG39) -> 384855.4 | AM39: =SUMIF($M$2:$AG$2,AM$2,$M39:$AG39) -> 443101.94 | AN39: =SUMIF($M$2:$AG$2,AN$2,$M39:$AG39) -> 510163.89
D42: Fees & Commission Expense | E42: Unit | F42: Conservative | G42: Moderate | H42: Optimistic | I42: Live
D43: Expense Rate | E43: % of fees & comm. | F43: =AVERAGE('Quarterly Historical Financials'!$D133:$D134) -> -0.26653248 | G43: =AVERAGE('Quarterly Historical Financials'!$D132:$D133) -> -0.31674644 | H43: =AVERAGE('Quarterly Historical Financials'!$D131:$D132) -> -0.3588455 | I43: =CHOOSE($G$4,F43,G43,H43) -> -0.26653248
K44: Fees & Commission Expense | M44: ='Quarterly Historical Financials'!AC13 -> -29426.085 | N44: =N39*$I43 -> -19259.425 | O44: =O39*$I43 -> -18992.755 | P44: =P39*$I43 -> -19673.856 | Q44: =Q39*$I43 -> -20379.381 | R44: =R39*$I43 -> -21110.208 | S44: =S39*$I43 -> -21867.243 | T44: =T39*$I43 -> -22651.426 | U44: =U39*$I43 -> -23463.73 | ... AG44: =AG39*$I43 -> -35810.902 | AI44: =SUMIF($M$2:$AG$2,AI$2,$M44:$AG44) -> -29426.085 | AJ44: =SUMIF($M$2:$AG$2,AJ$2,$M44:$AG44) -> -78305.416 | AK44: =SUMIF($M$2:$AG$2,AK$2,$M44:$AG44) -> -89092.607 | AL44: =SUMIF($M$2:$AG$2,AL$2,$M44:$AG44) -> -102576.47 | AM44: =SUMIF($M$2:$AG$2,AM$2,$M44:$AG44) -> -118101.06 | AN44: =SUMIF($M$2:$AG$2,AN$2,$M44:$AG44) -> -135975.25
B47: 4 | D47: Trading & Other Income Assumptions
D48: Net trading Income | E48: Unit | F48: Conservative | G48: Moderate | H48: Optimistic | I48: Live
D49: Net trading rate | E49: % of trad. assets | F49: =AVERAGE('Quarterly Historical Financials'!$D148:$D149) -> 0.0054653931 | G49: =AVERAGE('Quarterly Historical Financials'!$D147:$D148) -> 0.012295688 | H49: =AVERAGE('Quarterly Historical Financials'!$D146:$D147) -> 0.020889395 | I49: =CHOOSE($G$4,F49,G49,H49) -> 0.0054653931
K50: Trading assets (Investment securities) | M50: =M99 -> 3178870.4 | N50: =N99 -> 4086092.7 | O50: =O99 -> 4232624.4 | P50: =P99 -> 4384410.9 | Q50: =Q99 -> 4541640.6 | R50: =R99 -> 4704508.7 | S50: =S99 -> 4873217.5 | T50: =T99 -> 5047976.3 | ... AG50: =AG99 -> 7980627.2 | AI50: =SUMIF($M$4:$AG$4,AI$4,$M50:$AG50) -> 3178870.4 | AJ50: =SUMIF($M$4:$AG$4,AJ$4,$M50:$AG50) -> 4541640.6 | AK50: =SUMIF($M$4:$AG$4,AK$4,$M50:$AG50) -> 5229002.2 | AL50: =SUMIF($M$4:$AG$4,AL$4,$M50:$AG50) -> 6020393.7 | AM50: =SUMIF($M$4:$AG$4,AM$4,$M50:$AG50) -> 6931559.6 | AN50: =SUMIF($M$4:$AG$4,AN$4,$M50:$AG50) -> 7980627.2
K51: Non-pledged trading assets | M51: ='Quarterly Historical Financials'!AC45 -> 0 | N51: 0 | O51: 0 | P51: 0 | Q51: 0 | R51: 0 | S51: 0 | T51: 0 | U51: 0 | V51: 0 | W51: 0 | X51: 0 | Y51: 0 | Z51: 0 | AA51: 0 | AB51: 0 | AC51: 0 | AD51: 0 | AE51: 0 | AF51: 0 | AG51: 0 | AI51: =SUMIF($M$4:$AG$4,AI$4,$M51:$AG51) -> 0 | AJ51: =SUMIF($M$4:$AG$4,AJ$4,$M51:$AG51) -> 0 | AK51: =SUMIF($M$4:$AG$4,AK$4,$M51:$AG51) -> 0 | AL51: =SUMIF($M$4:$AG$4,AL$4,$M51:$AG51) -> 0 | AM51: =SUMIF($M$4:$AG$4,AM$4,$M51:$AG51) -> 0 | AN51: =SUMIF($M$4:$AG$4,AN$4,$M51:$AG51) -> 0
K52: Pledged trading assets | M52: ='Quarterly Historical Financials'!AC46 -> 0 | N52: 0 | O52: 0 | P52: 0 | Q52: 0 | R52: 0 | S52: 0 | T52: 0 | U52: 0 | V52: 0 | W52: 0 | X52: 0 | Y52: 0 | Z52: 0 | AA52: 0 | AB52: 0 | AC52: 0 | AD52: 0 | AE52: 0 | AF52: 0 | AG52: 0 | AI52: =SUMIF($M$4:$AG$4,AI$4,$M52:$AG52) -> 0 | AJ52: =SUMIF($M$4:$AG$4,AJ$4,$M52:$AG52) -> 0 | AK52: =SUMIF($M$4:$AG$4,AK$4,$M52:$AG52) -> 0 | AL52: =SUMIF($M$4:$AG$4,AL$4,$M52:$AG52) -> 0 | AM52: =SUMIF($M$4:$AG$4,AM$4,$M52:$AG52) -> 0 | AN52: =SUMIF($M$4:$AG$4,AN$4,$M52:$AG52) -> 0
K53: Trading assets | M53: =SUM(M50:M52) -> 3178870.4 | N53: =SUM(N50:N52) -> 4086092.7 | O53: =SUM(O50:O52) -> 4232624.4 | P53: =SUM(P50:P52) -> 4384410.9 | Q53: =SUM(Q50:Q52) -> 4541640.6 | R53: =SUM(R50:R52) -> 4704508.7 | S53: =SUM(S50:S52) -> 4873217.5 | T53: =SUM(T50:T52) -> 5047976.3 | ... AG53: =SUM(AG50:AG52) -> 7980627.2 | AI53: =SUM(AI50:AI52) -> 3178870.4 | AJ53: =SUM(AJ50:AJ52) -> 4541640.6 | AK53: =SUM(AK50:AK52) -> 5229002.2 | AL53: =SUM(AL50:AL52) -> 6020393.7 | AM53: =SUM(AM50:AM52) -> 6931559.6 | AN53: =SUM(AN50:AN52) -> 7980627.2
K55: Net trading Income | M55: ='Quarterly Historical Financials'!AC15 -> 46887.804 | N55: =N53*$I49 -> 22332.103 | O55: =O53*$I49 -> 23132.956 | P55: =P53*$I49 -> 23962.529 | Q55: =Q53*$I49 -> 24821.851 | R55: =R53*$I49 -> 25711.99 | S55: =S53*$I49 -> 26634.049 | T55: =T53*$I49 -> 27589.175 | U55: =U53*$I49 -> 28578.553 | ... AG55: =AG53*$I49 -> 43617.265 | AI55: =SUMIF($M$2:$AG$2,AI$2,$M55:$AG55) -> 46887.804 | AJ55: =SUMIF($M$2:$AG$2,AJ$2,$M55:$AG55) -> 94249.439 | AK55: =SUMIF($M$2:$AG$2,AK$2,$M55:$AG55) -> 108513.77 | AL55: =SUMIF($M$2:$AG$2,AL$2,$M55:$AG55) -> 124936.95 | AM55: =SUMIF($M$2:$AG$2,AM$2,$M55:$AG55) -> 143845.73 | AN55: =SUMIF($M$2:$AG$2,AN$2,$M55:$AG55) -> 165616.28
D57: Other Income | E57: Unit | F57: Conservative | G57: Moderate | H57: Optimistic | I57: Live
D58: Net trading rate | E58: % of Rev. | F58: =AVERAGE('Quarterly Historical Financials'!$D156:$D157) -> 0.00086321314 | G58: =AVERAGE('Quarterly Historical Financials'!$D155:$D156) -> 0.0010393349 | H58: =AVERAGE('Quarterly Historical Financials'!$D154:$D155)/4.5 -> 0.0019593525 | I58: =CHOOSE($G$4,F58,G58,H58) -> 0.00086321314
K59: Interest Income | M59: =M21 -> 681759.57 | N59: =N21 -> 384375.91 | O59: =O21 -> 402463.86 | P59: =P21 -> 421307.6 | Q59: =Q21 -> 440936.87 | R59: =R21 -> 461382.59 | S59: =S21 -> 482676.87 | T59: =T21 -> 504853.07 | ... AG59: =AG21 -> 891213.25 | AI59: =SUMIF($M$2:$AG$2,AI$2,$M59:$AG59) -> 681759.57 | AJ59: =SUMIF($M$2:$AG$2,AJ$2,$M59:$AG59) -> 1649084.2 | AK59: =SUMIF($M$2:$AG$2,AK$2,$M59:$AG59) -> 1976858.4 | AL59: =SUMIF($M$2:$AG$2,AL$2,$M59:$AG59) -> 2362334.8 | AM59: =SUMIF($M$2:$AG$2,AM$2,$M59:$AG59) -> 2815137.9 | AN59: =SUMIF($M$2:$AG$2,AN$2,$M59:$AG59) -> 3346506.3
K60: Fees & Commission Income | M60: =M39 -> 76446.237 | N60: =N39 -> 72259.202 | O60: =O39 -> 71258.687 | P60: =P39 -> 73814.101 | Q60: =Q39 -> 76461.154 | R60: =R39 -> 79203.134 | S60: =S39 -> 82043.444 | T60: =T39 -> 84985.61 | ... AG60: =AG39 -> 134358.49 | AI60: =SUMIF($M$2:$AG$2,AI$2,$M60:$AG60) -> 76446.237 | AJ60: =SUMIF($M$2:$AG$2,AJ$2,$M60:$AG60) -> 293793.14 | AK60: =SUMIF($M$2:$AG$2,AK$2,$M60:$AG60) -> 334265.47 | AL60: =SUMIF($M$2:$AG$2,AL$2,$M60:$AG60) -> 384855.4 | AM60: =SUMIF($M$2:$AG$2,AM$2,$M60:$AG60) -> 443101.94 | AN60: =SUMIF($M$2:$AG$2,AN$2,$M60:$AG60) -> 510163.89
K61: Net trading Income | M61: =M55 -> 46887.804 | N61: =N55 -> 22332.103 | O61: =O55 -> 23132.956 | P61: =P55 -> 23962.529 | Q61: =Q55 -> 24821.851 | R61: =R55 -> 25711.99 | S61: =S55 -> 26634.049 | T61: =T55 -> 27589.175 | ... AG61: =AG55 -> 43617.265 | AI61: =SUMIF($M$2:$AG$2,AI$2,$M61:$AG61) -> 46887.804 | AJ61: =SUMIF($M$2:$AG$2,AJ$2,$M61:$AG61) -> 94249.439 | AK61: =SUMIF($M$2:$AG$2,AK$2,$M61:$AG61) -> 108513.77 | AL61: =SUMIF($M$2:$AG$2,AL$2,$M61:$AG61) -> 124936.95 | AM61: =SUMIF($M$2:$AG$2,AM$2,$M61:$AG61) -> 143845.73 | AN61: =SUMIF($M$2:$AG$2,AN$2,$M61:$AG61) -> 165616.28
K62: Revenue | M62: =SUM(M59:M61) -> 805093.61 | N62: =SUM(N59:N61) -> 478967.21 | O62: =SUM(O59:O61) -> 496855.5 | P62: =SUM(P59:P61) -> 519084.23 | Q62: =SUM(Q59:Q61) -> 542219.88 | R62: =SUM(R59:R61) -> 566297.71 | S62: =SUM(S59:S61) -> 591354.36 | T62: =SUM(T59:T61) -> 617427.86 | ... AG62: =SUM(AG59:AG61) -> 1069189 | AI62: =SUM(AI59:AI61) -> 805093.61 | AJ62: =SUM(AJ59:AJ61) -> 2037126.8 | AK62: =SUM(AK59:AK61) -> 2419637.6 | AL62: =SUM(AL59:AL61) -> 2872127.2 | AM62: =SUM(AM59:AM61) -> 3402085.6 | AN62: =SUM(AN59:AN61) -> 4022286.5
K64: Other Income | M64: ='Quarterly Historical Financials'!AC16 -> 326.388 | N64: =N62*$I58 -> 413.45079 | O64: =O62*$I58 -> 428.8922 | P64: =P62*$I58 -> 448.08032 | Q64: =Q62*$I58 -> 468.05132 | R64: =R62*$I58 -> 488.83563 | S64: =S62*$I58 -> 510.46485 | T64: =T62*$I58 -> 532.97184 | U64: =U62*$I58 -> 556.39069 | ... AG64: =AG62*$I58 -> 922.938 | AI64: =SUMIF($M$2:$AG$2,AI$2,$M64:$AG64) -> 326.388 | AJ64: =SUMIF($M$2:$AG$2,AJ$2,$M64:$AG64) -> 1758.4746 | AK64: =SUMIF($M$2:$AG$2,AK$2,$M64:$AG64) -> 2088.663 | AL64: =SUMIF($M$2:$AG$2,AL$2,$M64:$AG64) -> 2479.2579 | AM64: =SUMIF($M$2:$AG$2,AM$2,$M64:$AG64) -> 2936.725 | AN64: =SUMIF($M$2:$AG$2,AN$2,$M64:$AG64) -> 3472.0905
B67: 5 | D67: Personal & Other Expenses Assumptions
D68: Personal Expenses | E68: Unit | F68: Conservative | G68: Moderate | H68: Optimistic | I68: Live
D69: Expense Rate | E69: % of op. income | F69: =AVERAGE('Quarterly Historical Financials'!$D167:$D168) -> -0.16106521 | G69: =AVERAGE('Quarterly Historical Financials'!$D166:$D167)/1.1 -> -0.20062126 | H69: =AVERAGE('Quarterly Historical Financials'!$D165:$D166) -> -0.25505653 | I69: =CHOOSE($G$4,F69,G69,H69) -> -0.16106521
K70: Net Interest Income | M70: =M21+M29 -> 579388.04 | N70: =N21+N29 -> 280185.31 | O70: =O21+O29 -> 294536.87 | P70: =P21+P29 -> 309510.23 | Q70: =Q21+Q29 -> 325130.33 | R70: =R21+R29 -> 341423.1 | S70: =S21+S29 -> 358415.5 | T70: =T21+T29 -> 376135.56 | ... AG70: =AG21+AG29 -> 687716.56 | AI70: =SUMIF($M$2:$AG$2,AI$2,$M70:$AG70) -> 579388.04 | AJ70: =SUMIF($M$2:$AG$2,AJ$2,$M70:$AG70) -> 1209362.7 | AK70: =SUMIF($M$2:$AG$2,AK$2,$M70:$AG70) -> 1470586.6 | AL70: =SUMIF($M$2:$AG$2,AL$2,$M70:$AG70) -> 1779440.5 | AM70: =SUMIF($M$2:$AG$2,AM$2,$M70:$AG70) -> 2144024.6 | AN70: =SUMIF($M$2:$AG$2,AN$2,$M70:$AG70) -> 2573822.2
K71: Net Fees and Commission Income | M71: =M39+M44 -> 47020.152 | N71: =N39+N44 -> 52999.777 | O71: =O39+O44 -> 52265.932 | P71: =P39+P44 -> 54140.245 | Q71: =Q39+Q44 -> 56081.773 | R71: =R39+R44 -> 58092.926 | S71: =S39+S44 -> 60176.201 | T71: =T39+T44 -> 62334.185 | ... AG71: =AG39+AG44 -> 98547.587 | AI71: =SUMIF($M$2:$AG$2,AI$2,$M71:$AG71) -> 47020.152 | AJ71: =SUMIF($M$2:$AG$2,AJ$2,$M71:$AG71) -> 215487.73 | AK71: =SUMIF($M$2:$AG$2,AK$2,$M71:$AG71) -> 245172.87 | AL71: =SUMIF($M$2:$AG$2,AL$2,$M71:$AG71) -> 282278.94 | AM71: =SUMIF($M$2:$AG$2,AM$2,$M71:$AG71) -> 325000.88 | AN71: =SUMIF($M$2:$AG$2,AN$2,$M71:$AG71) -> 374188.64
K72: Net trading income | M72: =M55 -> 46887.804 | N72: =N55 -> 22332.103 | O72: =O55 -> 23132.956 | P72: =P55 -> 23962.529 | Q72: =Q55 -> 24821.851 | R72: =R55 -> 25711.99 | S72: =S55 -> 26634.049 | T72: =T55 -> 27589.175 | ... AG72: =AG55 -> 43617.265 | AI72: =SUMIF($M$2:$AG$2,AI$2,$M72:$AG72) -> 46887.804 | AJ72: =SUMIF($M$2:$AG$2,AJ$2,$M72:$AG72) -> 94249.439 | AK72: =SUMIF($M$2:$AG$2,AK$2,$M72:$AG72) -> 108513.77 | AL72: =SUMIF($M$2:$AG$2,AL$2,$M72:$AG72) -> 124936.95 | AM72: =SUMIF($M$2:$AG$2,AM$2,$M72:$AG72) -> 143845.73 | AN72: =SUMIF($M$2:$AG$2,AN$2,$M72:$AG72) -> 165616.28
K73: Other income | M73: =M64 -> 326.388 | N73: =N64 -> 413.45079 | O73: =O64 -> 428.8922 | P73: =P64 -> 448.08032 | Q73: =Q64 -> 468.05132 | R73: =R64 -> 488.83563 | S73: =S64 -> 510.46485 | T73: =T64 -> 532.97184 | ... AG73: =AG64 -> 922.938 | AI73: =SUMIF($M$2:$AG$2,AI$2,$M73:$AG73) -> 326.388 | AJ73: =SUMIF($M$2:$AG$2,AJ$2,$M73:$AG73) -> 1758.4746 | AK73: =SUMIF($M$2:$AG$2,AK$2,$M73:$AG73) -> 2088.663 | AL73: =SUMIF($M$2:$AG$2,AL$2,$M73:$AG73) -> 2479.2579 | AM73: =SUMIF($M$2:$AG$2,AM$2,$M73:$AG73) -> 2936.725 | AN73: =SUMIF($M$2:$AG$2,AN$2,$M73:$AG73) -> 3472.0905
K74: Operating Income | M74: =SUM(M70:M73) -> 673622.39 | N74: =SUM(N70:N73) -> 355930.64 | O74: =SUM(O70:O73) -> 370364.65 | P74: =SUM(P70:P73) -> 388061.08 | Q74: =SUM(Q70:Q73) -> 406502 | R74: =SUM(R70:R73) -> 425716.85 | S74: =SUM(S70:S73) -> 445736.22 | T74: =SUM(T70:T73) -> 466591.89 | ... AG74: =SUM(AG70:AG73) -> 830804.35 | AI74: =SUM(AI70:AI73) -> 673622.39 | AJ74: =SUM(AJ70:AJ73) -> 1520858.4 | AK74: =SUM(AK70:AK73) -> 1826361.9 | AL74: =SUM(AL70:AL73) -> 2189135.7 | AM74: =SUM(AM70:AM73) -> 2615807.9 | AN74: =SUM(AN70:AN73) -> 3117099.2
K76: Personal Expenses | M76: ='Quarterly Historical Financials'!AC20 -> -119879.86 | N76: =N74*$I69 -> -57328.043 | O76: =O74*$I69 -> -59652.86 | P76: =P74*$I69 -> -62503.14 | Q76: =Q74*$I69 -> -65473.331 | R76: =R74*$I69 -> -68568.174 | S76: =S74*$I69 -> -71792.597 | T76: =T74*$I69 -> -75151.721 | U76: =U74*$I69 -> -78650.866 | ... AG76: =AG74*$I69 -> -133813.68 | AI76: =SUMIF($M$2:$AG$2,AI$2,$M76:$AG76) -> -119879.86 | AJ76: =SUMIF($M$2:$AG$2,AJ$2,$M76:$AG76) -> -244957.37 | AK76: =SUMIF($M$2:$AG$2,AK$2,$M76:$AG76) -> -294163.36 | AL76: =SUMIF($M$2:$AG$2,AL$2,$M76:$AG76) -> -352593.6 | AM76: =SUMIF($M$2:$AG$2,AM$2,$M76:$AG76) -> -421315.65 | AN76: =SUMIF($M$2:$AG$2,AN$2,$M76:$AG76) -> -502056.24
D78: Other Expenses | E78: Unit | F78: Conservative | G78: Moderate | H78: Optimistic | I78: Live
D79: Expense Rate | E79: % of op. income | F79: =AVERAGE('Quarterly Historical Financials'!$D174:$D175) -> -0.13194678 | G79: =AVERAGE('Quarterly Historical Financials'!$D173:$D174)/1.1 -> -0.20120099 | H79: =AVERAGE('Quarterly Historical Financials'!$D172:$D173) -> -0.26778135 | I79: =CHOOSE($G$4,F79,G79,H79) -> -0.13194678 | K79: Other Expenses | M79: ='Quarterly Historical Financials'!AC22 -> -25698.955 | N79: =N74*$I79 -> -46963.9 | O79: =O74*$I79 -> -48868.422 | P79: =P74*$I79 -> -51203.409 | Q79: =Q74*$I79 -> -53636.629 | R79: =R74*$I79 -> -56171.966 | S79: =S74*$I79 -> -58813.457 | T79: =T74*$I79 -> -61565.295 | U79: =U74*$I79 -> -64431.842 | ... AG79: =AG74*$I79 -> -109621.96 | AI79: =SUMIF($M$2:$AG$2,AI$2,$M79:$AG79) -> -25698.955 | AJ79: =SUMIF($M$2:$AG$2,AJ$2,$M79:$AG79) -> -200672.36 | AK79: =SUMIF($M$2:$AG$2,AK$2,$M79:$AG79) -> -240982.56 | AL79: =SUMIF($M$2:$AG$2,AL$2,$M79:$AG79) -> -288849.39 | AM79: =SUMIF($M$2:$AG$2,AM$2,$M79:$AG79) -> -345147.42 | AN79: =SUMIF($M$2:$AG$2,AN$2,$M79:$AG79) -> -411291.2
B82: 6 | D82: Balance Sheet
D83: Total Deposits | E83: Unit | F83: Conservative | G83: Moderate | H83: Optimistic | I83: Live
D84: Growth Rate | E84: q-o-q growth | F84: =AVERAGE('Quarterly Historical Financials'!$D194:$D195)/2 -> 0.035861081 | G84: =AVERAGE('Quarterly Historical Financials'!$D193:$D194)/2 -> 0.052100784 | H84: =AVERAGE('Quarterly Historical Financials'!$D192:$D193)/2 -> 0.061738613 | I84: =CHOOSE($G$4,F84,G84,H84) -> 0.035861081
K85: Total Deposits | L85: ='Quarterly Historical Financials'!AB190 -> 13833495 | M85: ='Quarterly Historical Financials'!AC190 -> 16642450 | N85: =M85*(1+$I84) -> 17239266 | O85: =N85*(1+$I84) -> 17857485 | P85: =O85*(1+$I84) -> 18497873 | Q85: =P85*(1+$I84) -> 19161227 | R85: =Q85*(1+$I84) -> 19848369 | S85: =R85*(1+$I84) -> 20560153 | T85: =S85*(1+$I84) -> 21297463 | U85: =T85*(1+$I84) -> 22061213 | ... AG85: =AF85*(1+$I84) -> 33670346 | AI85: =SUMIF($M$4:$AG$4,AI$4,$M85:$AG85) -> 16642450 | AJ85: =SUMIF($M$4:$AG$4,AJ$4,$M85:$AG85) -> 19161227 | AK85: =SUMIF($M$4:$AG$4,AK$4,$M85:$AG85) -> 22061213 | AL85: =SUMIF($M$4:$AG$4,AL$4,$M85:$AG85) -> 25400101 | AM85: =SUMIF($M$4:$AG$4,AM$4,$M85:$AG85) -> 29244319 | AN85: =SUMIF($M$4:$AG$4,AN$4,$M85:$AG85) -> 33670346
D87: Loans | E87: Unit | F87: Conservative | G87: Moderate | H87: Optimistic | I87: Live
D88: Loan-to-Deposit Ratio | E88: x | F88: =AVERAGE('Quarterly Historical Financials'!$D203:$D204) -> 0.17033942 | G88: =AVERAGE('Quarterly Historical Financials'!$D202:$D203) -> 0.21970258 | H88: =AVERAGE('Quarterly Historical Financials'!$D201:$D202) -> 0.25160932 | I88: =CHOOSE($G$4,F88,G88,H88) -> 0.17033942
D89: Impairment | E89: % of Loans | F89: =AVERAGE('Quarterly Historical Financials'!$D210:$D211) -> -0.013357048 | G89: =AVERAGE('Quarterly Historical Financials'!$D209:$D210) -> -0.013062437 | H89: =AVERAGE('Quarterly Historical Financials'!$D208:$D209) -> -0.011708222 | I89: =CHOOSE($G$4,F89,G89,H89) -> -0.013357048 | K89: Beginning Balance | L89: ='Quarterly Historical Financials'!AA199 -> 1414797 | M89: ='Quarterly Historical Financials'!AB199 -> 1516490 | N89: =M92 -> 1947024.8 | O89: =N92 -> 2936526.5 | P89: =O92 -> 3041833.5 | Q89: =P92 -> 3150917 | R89: =Q92 -> 3263912.3 | S89: =R92 -> 3380959.7 | T89: =S92 -> 3502204.6 | U89: =T92 -> 3627797.4 | ... AG89: =AF92 -> 5536830.4 | AI89: =SUMIF($M$4:$AG$4,AI$4,$M89:$AG89) -> 1516490 | AJ89: =AI92 -> 1947024.8 | AK89: =AJ92 -> 3263912.3 | AL89: =AK92 -> 3757894.1 | AM89: =AL92 -> 4326638.5 | AN89: =AM92 -> 4981460.3
K90: Disbursements | L90: =L92-SUM(L89,L91) -> 55033 | M90: =M92-SUM(M89,M91) -> 608840.22 | N90: =N92-SUM(N89,N91) -> 1015508.2 | O90: =O92-SUM(O89,O91) -> 144530.34 | P90: =P92-SUM(P89,P91) -> 149713.36 | Q90: =Q92-SUM(Q89,Q91) -> 155082.24 | R90: =R92-SUM(R89,R91) -> 160643.66 | S90: =S92-SUM(S89,S91) -> 166404.51 | ... AG90: =AG92-SUM(AG89,AG91) -> 272512.44 | AI90: =SUMIF($M$2:$AG$2,AI$2,$M90:$AG90) -> 608840.22 | AJ90: =SUMIF($M$2:$AG$2,AJ$2,$M90:$AG90) -> 1464834.1 | AK90: =SUMIF($M$2:$AG$2,AK$2,$M90:$AG90) -> 677973.53 | AL90: =SUMIF($M$2:$AG$2,AL$2,$M90:$AG90) -> 780582.48 | AM90: =SUMIF($M$2:$AG$2,AM$2,$M90:$AG90) -> 898720.95 | AN90: =SUMIF($M$2:$AG$2,AN$2,$M90:$AG90) -> 1034739.3
K91: Impairment | L91: ='Quarterly Historical Financials'!AB206 -> 46660 | M91: ='Quarterly Historical Financials'!AC206 -> -178305.4 | N91: =N89*$I89 -> -26006.504 | O91: =O89*$I89 -> -39223.326 | P91: =P89*$I89 -> -40629.917 | Q91: =Q89*$I89 -> -42086.949 | R91: =R89*$I89 -> -43596.233 | S91: =S89*$I89 -> -45159.641 | T91: =T89*$I89 -> -46779.114 | U91: =U89*$I89 -> -48456.664 | ... AG91: =AG89*$I89 -> -73955.71 | AI91: =SUMIF($M$2:$AG$2,AI$2,$M91:$AG91) -> -178305.4 | AJ91: =SUMIF($M$2:$AG$2,AJ$2,$M91:$AG91) -> -147946.7 | AK91: =SUMIF($M$2:$AG$2,AK$2,$M91:$AG91) -> -183991.65 | AL91: =SUMIF($M$2:$AG$2,AL$2,$M91:$AG91) -> -211838.15 | AM91: =SUMIF($M$2:$AG$2,AM$2,$M91:$AG91) -> -243899.13 | AN91: =SUMIF($M$2:$AG$2,AN$2,$M91:$AG91) -> -280812.42
K92: Net Book Value | L92: =L94 -> 1516490 | M92: =M94 -> 1947024.8 | N92: =N94 -> 2936526.5 | O92: =O94 -> 3041833.5 | P92: =P94 -> 3150917 | Q92: =Q94 -> 3263912.3 | R92: =R94 -> 3380959.7 | S92: =S94 -> 3502204.6 | ... AG92: =AG94 -> 5735387.1 | AI92: =SUM(AI89:AI91) -> 1947024.8 | AJ92: =SUM(AJ89:AJ91) -> 3263912.3 | AK92: =SUM(AK89:AK91) -> 3757894.1 | AL92: =SUM(AL89:AL91) -> 4326638.5 | AM92: =SUM(AM89:AM91) -> 4981460.3 | AN92: =SUM(AN89:AN91) -> 5735387.1
K94: Loans and advances to customers | L94: ='Quarterly Historical Financials'!AB199 -> 1516490 | M94: ='Quarterly Historical Financials'!AC199 -> 1947024.8 | N94: =N85*$I88 -> 2936526.5 | O94: =O85*$I88 -> 3041833.5 | P94: =P85*$I88 -> 3150917 | Q94: =Q85*$I88 -> 3263912.3 | R94: =R85*$I88 -> 3380959.7 | S94: =S85*$I88 -> 3502204.6 | T94: =T85*$I88 -> 3627797.4 | U94: =U85*$I88 -> 3757894.1 | ... AG94: =AG85*$I88 -> 5735387.1 | AI94: =SUMIF($M$4:$AG$4,AI$4,$M94:$AG94) -> 1947024.8 | AJ94: =SUMIF($M$4:$AG$4,AJ$4,$M94:$AG94) -> 3263912.3 | AK94: =SUMIF($M$4:$AG$4,AK$4,$M94:$AG94) -> 3757894.1 | AL94: =SUMIF($M$4:$AG$4,AL$4,$M94:$AG94) -> 4326638.5 | AM94: =SUMIF($M$4:$AG$4,AM$4,$M94:$AG94) -> 4981460.3 | AN94: =SUMIF($M$4:$AG$4,AN$4,$M94:$AG94) -> 5735387.1
D97: Investments | E97: Unit | F97: Conservative | G97: Moderate | H97: Optimistic | I97: Live
D98: Investment-to-Deposit Ratio | E98: x | F98: =AVERAGE('Quarterly Historical Financials'!$D219:$D220) -> 0.23702243 | G98: =AVERAGE('Quarterly Historical Financials'!$D218:$D219)*0.95 -> 0.28385814 | H98: =AVERAGE('Quarterly Historical Financials'!$D217:$D218)*0.75 -> 0.31550251 | I98: =CHOOSE($G$4,F98,G98,H98) -> 0.23702243
K99: Trading assets (Investment securities) | L99: ='Quarterly Historical Financials'!AB215 -> 3580300 | M99: ='Quarterly Historical Financials'!AC215 -> 3178870.4 | N99: =N85*$I98 -> 4086092.7 | O99: =O85*$I98 -> 4232624.4 | P99: =P85*$I98 -> 4384410.9 | Q99: =Q85*$I98 -> 4541640.6 | R99: =R85*$I98 -> 4704508.7 | S99: =S85*$I98 -> 4873217.5 | T99: =T85*$I98 -> 5047976.3 | U99: =U85*$I98 -> 5229002.2 | ... AG99: =AG85*$I98 -> 7980627.2 | AI99: =SUMIF($M$4:$AG$4,AI$4,$M99:$AG99) -> 3178870.4 | AJ99: =SUMIF($M$4:$AG$4,AJ$4,$M99:$AG99) -> 4541640.6 | AK99: =SUMIF($M$4:$AG$4,AK$4,$M99:$AG99) -> 5229002.2 | AL99: =SUMIF($M$4:$AG$4,AL$4,$M99:$AG99) -> 6020393.7 | AM99: =SUMIF($M$4:$AG$4,AM$4,$M99:$AG99) -> 6931559.6 | AN99: =SUMIF($M$4:$AG$4,AN$4,$M99:$AG99) -> 7980627.2
F100: =-Assumptions!M210 -> -204318.15
D101: Investment in associates | E101: Unit | F101: =-Assumptions!M223 -> -0.414 | G101: Moderate | H101: Optimistic | I101: Live
D102: Net additions rate | E102: % of begin. bal. | F102: =AVERAGE('Quarterly Historical Financials'!$D231:$D231) -> 0 | G102: =AVERAGE('Quarterly Historical Financials'!$D231:$D231) -> 0 | H102: =AVERAGE('Quarterly Historical Financials'!$D231:$D231) -> 0 | I102: =CHOOSE($G$4,F102,G102,H102) -> 0
F103: =-Assumptions!M235 -> -6669.754 | K103: Beginning Balance | L103: ='Quarterly Historical Financials'!AB224 -> 2082 | M103: ='Quarterly Historical Financials'!AC224 -> 2505 | N103: =M105 -> 2799.382 | O103: =N105 -> 2799.382 | P103: =O105 -> 2799.382 | Q103: =P105 -> 2799.382 | R103: =Q105 -> 2799.382 | S103: =R105 -> 2799.382 | T103: =S105 -> 2799.382 | U103: =T105 -> 2799.382 | ... AG103: =AF105 -> 2799.382 | AI103: =SUMIF($M$4:$AG$4,AI$4,$M103:$AG103) -> 2505 | AJ103: =SUMIF($M$4:$AG$4,AJ$4,$M103:$AG103) -> 2799.382 | AK103: =SUMIF($M$4:$AG$4,AK$4,$M103:$AG103) -> 2799.382 | AL103: =SUMIF($M$4:$AG$4,AL$4,$M103:$AG103) -> 2799.382 | AM103: =SUMIF($M$4:$AG$4,AM$4,$M103:$AG103) -> 2799.382 | AN103: =SUMIF($M$4:$AG$4,AN$4,$M103:$AG103) -> 2799.382
F104: =-Assumptions!M241 -> 0 | K104: Net Addtions | L104: ='Quarterly Historical Financials'!AB225 -> 423 | M104: ='Quarterly Historical Financials'!AC225 -> 294.382 | N104: =N103*$I102 -> 0 | O104: =O103*$I102 -> 0 | P104: =P103*$I102 -> 0 | Q104: =Q103*$I102 -> 0 | R104: =R103*$I102 -> 0 | S104: =S103*$I102 -> 0 | T104: =T103*$I102 -> 0 | U104: =U103*$I102 -> 0 | ... AG104: =AG103*$I102 -> 0 | AI104: =SUMIF($M$2:$AG$2,AI$2,$M104:$AG104) -> 294.382 | AJ104: =SUMIF($M$2:$AG$2,AJ$2,$M104:$AG104) -> 0 | AK104: =SUMIF($M$2:$AG$2,AK$2,$M104:$AG104) -> 0 | AL104: =SUMIF($M$2:$AG$2,AL$2,$M104:$AG104) -> 0 | AM104: =SUMIF($M$2:$AG$2,AM$2,$M104:$AG104) -> 0 | AN104: =SUMIF($M$2:$AG$2,AN$2,$M104:$AG104) -> 0
K105: Closing Balance | L105: =SUM(L103:L104) -> 2505 | M105: =SUM(M103:M104) -> 2799.382 | N105: =SUM(N103:N104) -> 2799.382 | O105: =SUM(O103:O104) -> 2799.382 | P105: =SUM(P103:P104) -> 2799.382 | Q105: =SUM(Q103:Q104) -> 2799.382 | R105: =SUM(R103:R104) -> 2799.382 | S105: =SUM(S103:S104) -> 2799.382 | ... AG105: =SUM(AG103:AG104) -> 2799.382 | AI105: =SUM(AI103:AI104) -> 2799.382 | AJ105: =SUM(AJ103:AJ104) -> 2799.382 | AK105: =SUM(AK103:AK104) -> 2799.382 | AL105: =SUM(AL103:AL104) -> 2799.382 | AM105: =SUM(AM103:AM104) -> 2799.382 | AN105: =SUM(AN103:AN104) -> 2799.382
K106: =SUM(K100:K105) -> 0 | L106: =SUM(L100:L105) -> 5010 | M106: =SUM(M100:M105) -> 5598.764 | N106: =SUM(N100:N105) -> 5598.764 | O106: =SUM(O100:O105) -> 5598.764 | P106: =SUM(P100:P105) -> 5598.764 | Q106: =SUM(Q100:Q105) -> 5598.764 | R106: =SUM(R100:R105) -> 5598.764 | ... AG106: =SUM(AG100:AG105) -> 5598.764
D107: Investment in subsidiary | E107: Unit | F107: Conservative | G107: Moderate | H107: Optimistic | I107: Live
D108: Net additions rate | E108: % of begin. bal. | F108: =AVERAGE('Quarterly Historical Financials'!$D243:$D243) -> 0 | G108: =AVERAGE('Quarterly Historical Financials'!$D243:$D243) -> 0 | H108: =AVERAGE('Quarterly Historical Financials'!$D243:$D243) -> 0 | I108: =CHOOSE($G$4,F108,G108,H108) -> 0
K109: Beginning Balance | L109: ='Quarterly Historical Financials'!AB236 -> 3025 | M109: ='Quarterly Historical Financials'!AC236 -> 3025 | N109: =M111 -> 0 | O109: =N111 -> 0 | P109: =O111 -> 0 | Q109: =P111 -> 0 | R109: =Q111 -> 0 | S109: =R111 -> 0 | T109: =S111 -> 0 | U109: =T111 -> 0 | ... AG109: =AF111 -> 0 | AI109: =SUMIF($M$4:$AG$4,AI$4,$M109:$AG109) -> 3025 | AJ109: =SUMIF($M$4:$AG$4,AJ$4,$M109:$AG109) -> 0 | AK109: =SUMIF($M$4:$AG$4,AK$4,$M109:$AG109) -> 0 | AL109: =SUMIF($M$4:$AG$4,AL$4,$M109:$AG109) -> 0 | AM109: =SUMIF($M$4:$AG$4,AM$4,$M109:$AG109) -> 0 | AN109: =SUMIF($M$4:$AG$4,AN$4,$M109:$AG109) -> 0
K110: Net Addtions | L110: ='Quarterly Historical Financials'!AB237 -> 0 | M110: ='Quarterly Historical Financials'!AC237 -> -3025 | N110: =N109*$I108 -> 0 | O110: =O109*$I108 -> 0 | P110: =P109*$I108 -> 0 | Q110: =Q109*$I108 -> 0 | R110: =R109*$I108 -> 0 | S110: =S109*$I108 -> 0 | T110: =T109*$I108 -> 0 | U110: =U109*$I108 -> 0 | ... AG110: =AG109*$I108 -> 0 | AI110: =SUMIF($M$2:$AG$2,AI$2,$M110:$AG110) -> -3025 | AJ110: =SUMIF($M$2:$AG$2,AJ$2,$M110:$AG110) -> 0 | AK110: =SUMIF($M$2:$AG$2,AK$2,$M110:$AG110) -> 0 | AL110: =SUMIF($M$2:$AG$2,AL$2,$M110:$AG110) -> 0 | AM110: =SUMIF($M$2:$AG$2,AM$2,$M110:$AG110) -> 0 | AN110: =SUMIF($M$2:$AG$2,AN$2,$M110:$AG110) -> 0
K111: Closing Balance | L111: =SUM(L109:L110) -> 3025 | M111: =SUM(M109:M110) -> 0 | N111: =SUM(N109:N110) -> 0 | O111: =SUM(O109:O110) -> 0 | P111: =SUM(P109:P110) -> 0 | Q111: =SUM(Q109:Q110) -> 0 | R111: =SUM(R109:R110) -> 0 | S111: =SUM(S109:S110) -> 0 | ... AG111: =SUM(AG109:AG110) -> 0 | AI111: =SUM(AI109:AI110) -> 0 | AJ111: =SUM(AJ109:AJ110) -> 0 | AK111: =SUM(AK109:AK110) -> 0 | AL111: =SUM(AL109:AL110) -> 0 | AM111: =SUM(AM109:AM110) -> 0 | AN111: =SUM(AN109:AN110) -> 0
B113: 7 | D113: Tax Schedule
D114: Tax Expense | E114: Unit | F114: Conservative | G114: Moderate | H114: Optimistic | I114: Live
D115: Effective tax rate | E115: % of profit before tax | F115: =AVERAGE('Quarterly Historical Financials'!$D185:$D186) -> -0.20652056 | G115: =AVERAGE('Quarterly Historical Financials'!$D184:$D185) -> -0.29089362 | H115: =AVERAGE('Quarterly Historical Financials'!$D183:$D184) -> -0.34133928 | I115: =CHOOSE($G$4,F115,G115,H115) -> -0.20652056
D116: Tax Payment | E116: % of total taxes | F116: 1 | G116: 1 | H116: 1 | I116: =CHOOSE($G$4,F116,G116,H116) -> 1 | K116: Profit before Taxes | L116: ='Quarterly Historical Financials'!AB179 -> 154788 | M116: ='Quarterly Historical Financials'!AC179 -> 331289.45 | N116: ='Quarterly Financial Projections'!G24 -> 215745.39 | O116: ='Quarterly Financial Projections'!H24 -> 212507.36 | P116: ='Quarterly Financial Projections'!I24 -> 223366.39 | Q116: ='Quarterly Financial Projections'!J24 -> 234679.82 | R116: ='Quarterly Financial Projections'!K24 -> 246464.64 | S116: ='Quarterly Financial Projections'!L24 -> 258738.39 | T116: ='Quarterly Financial Projections'!M24 -> 271519.18 | U116: ='Quarterly Financial Projections'!N24 -> 284825.71 | ... AG116: ='Quarterly Financial Projections'!Z24 -> 493164.37 | AI116: =SUMIF($M$2:$AG$2,AI$2,$M116:$AG116) -> 331289.45 | AJ116: =SUMIF($M$2:$AG$2,AJ$2,$M116:$AG116) -> 886298.96 | AK116: =SUMIF($M$2:$AG$2,AK$2,$M116:$AG116) -> 1061547.9 | AL116: =SUMIF($M$2:$AG$2,AL$2,$M116:$AG116) -> 1283571.1 | AM116: =SUMIF($M$2:$AG$2,AM$2,$M116:$AG116) -> 1543811.7 | AN116: =SUMIF($M$2:$AG$2,AN$2,$M116:$AG116) -> 1848020.3
K117: Total Taxes | L117: ='Quarterly Historical Financials'!AB181 -> -43024 | M117: ='Quarterly Historical Financials'!AC181 -> -101178.39 | N117: =N116*$I115 -> -44555.86 | O117: =O116*$I115 -> -43887.138 | P117: =P116*$I115 -> -46129.751 | Q117: =Q116*$I115 -> -48466.208 | R117: =R116*$I115 -> -50900.016 | S117: =S116*$I115 -> -53434.798 | T117: =T116*$I115 -> -56074.293 | U117: =U116*$I115 -> -58822.365 | ... AG117: =AG116*$I115 -> -101848.58 | AI117: =SUMIF($M$2:$AG$2,AI$2,$M117:$AG117) -> -101178.39 | AJ117: =SUMIF($M$2:$AG$2,AJ$2,$M117:$AG117) -> -183038.96 | AK117: =SUMIF($M$2:$AG$2,AK$2,$M117:$AG117) -> -219231.47 | AL117: =SUMIF($M$2:$AG$2,AL$2,$M117:$AG117) -> -265083.81 | AM117: =SUMIF($M$2:$AG$2,AM$2,$M117:$AG117) -> -318828.85 | AN117: =SUMIF($M$2:$AG$2,AN$2,$M117:$AG117) -> -381654.19
K118: Taxes Paid | L118: ='Raw Historical Financials'!Y105 -> 0 | M118: ='Raw Historical Financials'!Z105 -> 0 | N118: =N117*$I116 -> -44555.86 | O118: =O117*$I116 -> -43887.138 | P118: =P117*$I116 -> -46129.751 | Q118: =Q117*$I116 -> -48466.208 | R118: =R117*$I116 -> -50900.016 | S118: =S117*$I116 -> -53434.798 | T118: =T117*$I116 -> -56074.293 | U118: =U117*$I116 -> -58822.365 | ... AG118: =AG117*$I116 -> -101848.58 | AI118: =SUMIF($M$2:$AG$2,AI$2,$M118:$AG118) -> 0 | AJ118: =SUMIF($M$2:$AG$2,AJ$2,$M118:$AG118) -> -183038.96 | AK118: =SUMIF($M$2:$AG$2,AK$2,$M118:$AG118) -> -219231.47 | AL118: =SUMIF($M$2:$AG$2,AL$2,$M118:$AG118) -> -265083.81 | AM118: =SUMIF($M$2:$AG$2,AM$2,$M118:$AG118) -> -318828.85 | AN118: =SUMIF($M$2:$AG$2,AN$2,$M118:$AG118) -> -381654.19
D120: Current tax assets | E120: Unit | F120: Conservative | G120: Moderate | H120: Optimistic | I120: Live
D121: Net additions rate | E121: % of begin. bal. | F121: =AVERAGE('Quarterly Historical Financials'!$D263:$D263) -> 0 | G121: =AVERAGE('Quarterly Historical Financials'!$D263:$D263) -> 0 | H121: =AVERAGE('Quarterly Historical Financials'!$D263:$D263) -> 0 | I121: =CHOOSE($G$4,F121,G121,H121) -> 0
K122: Beginning Balance | L122: ='Quarterly Historical Financials'!AB256 -> 188481 | M122: ='Quarterly Historical Financials'!AC256 -> 191807 | N122: =M124 -> 244879.81 | O122: =N124 -> 244879.81 | P122: =O124 -> 244879.81 | Q122: =P124 -> 244879.81 | R122: =Q124 -> 244879.81 | S122: =R124 -> 244879.81 | T122: =S124 -> 244879.81 | U122: =T124 -> 244879.81 | ... AG122: =AF124 -> 244879.81 | AI122: =SUMIF($M$4:$AG$4,AI$4,$M122:$AG122) -> 191807 | AJ122: =AI124 -> 244879.81 | AK122: =AJ124 -> 244879.81 | AL122: =AK124 -> 244879.81 | AM122: =AL124 -> 244879.81 | AN122: =AM124 -> 244879.81
K123: Net Addtions | L123: ='Quarterly Historical Financials'!AB257 -> 3326 | M123: ='Quarterly Historical Financials'!AC257 -> 53072.81 | N123: =N122*$I121 -> 0 | O123: =O122*$I121 -> 0 | P123: =P122*$I121 -> 0 | Q123: =Q122*$I121 -> 0 | R123: =R122*$I121 -> 0 | S123: =S122*$I121 -> 0 | T123: =T122*$I121 -> 0 | U123: =U122*$I121 -> 0 | ... AG123: =AG122*$I121 -> 0 | AI123: =SUMIF($M$2:$AG$2,AI$2,$M123:$AG123) -> 53072.81 | AJ123: =SUMIF($M$2:$AG$2,AJ$2,$M123:$AG123) -> 0 | AK123: =SUMIF($M$2:$AG$2,AK$2,$M123:$AG123) -> 0 | AL123: =SUMIF($M$2:$AG$2,AL$2,$M123:$AG123) -> 0 | AM123: =SUMIF($M$2:$AG$2,AM$2,$M123:$AG123) -> 0 | AN123: =SUMIF($M$2:$AG$2,AN$2,$M123:$AG123) -> 0
K124: Closing Balance | L124: =SUM(L122:L123) -> 191807 | M124: =SUM(M122:M123) -> 244879.81 | N124: =SUM(N122:N123) -> 244879.81 | O124: =SUM(O122:O123) -> 244879.81 | P124: =SUM(P122:P123) -> 244879.81 | Q124: =SUM(Q122:Q123) -> 244879.81 | R124: =SUM(R122:R123) -> 244879.81 | S124: =SUM(S122:S123) -> 244879.81 | ... AG124: =SUM(AG122:AG123) -> 244879.81 | AI124: =SUM(AI122:AI123) -> 244879.81 | AJ124: =SUM(AJ122:AJ123) -> 244879.81 | AK124: =SUM(AK122:AK123) -> 244879.81 | AL124: =SUM(AL122:AL123) -> 244879.81 | AM124: =SUM(AM122:AM123) -> 244879.81 | AN124: =SUM(AN122:AN123) -> 244879.81
D126: Deferred tax asset | E126: Unit | F126: Conservative | G126: Moderate | H126: Optimistic | I126: Live
D127: Net additions rate | E127: % of begin. bal. | F127: =AVERAGE('Quarterly Historical Financials'!$D274:$D275) -> 0 | G127: =AVERAGE('Quarterly Historical Financials'!$D274:$D274) -> 0 | H127: =AVERAGE('Quarterly Historical Financials'!$D272:$D272) -> 0 | I127: =CHOOSE($G$4,F127,G127,H127) -> 0
K128: Beginning Balance | L128: ='Quarterly Historical Financials'!AB267 -> 8827 | M128: ='Quarterly Historical Financials'!AC267 -> 8827 | N128: =M130 -> 0 | O128: =N130 -> 0 | P128: =O130 -> 0 | Q128: =P130 -> 0 | R128: =Q130 -> 0 | S128: =R130 -> 0 | T128: =S130 -> 0 | U128: =T130 -> 0 | ... AG128: =AF130 -> 0 | AI128: =SUMIF($M$4:$AG$4,AI$4,$M128:$AG128) -> 8827 | AJ128: =AI130 -> 0 | AK128: =AJ130 -> 0 | AL128: =AK130 -> 0 | AM128: =AL130 -> 0 | AN128: =AM130 -> 0
K129: Net Addtions | L129: ='Quarterly Historical Financials'!AB268 -> 0 | M129: ='Quarterly Historical Financials'!AC268 -> -8827 | N129: =N128*$I127 -> 0 | O129: =O128*$I127 -> 0 | P129: =P128*$I127 -> 0 | Q129: =Q128*$I127 -> 0 | R129: =R128*$I127 -> 0 | S129: =S128*$I127 -> 0 | T129: =T128*$I127 -> 0 | U129: =U128*$I127 -> 0 | ... AG129: =AG128*$I127 -> 0 | AI129: =SUMIF($M$2:$AG$2,AI$2,$M129:$AG129) -> -8827 | AJ129: =SUMIF($M$2:$AG$2,AJ$2,$M129:$AG129) -> 0 | AK129: =SUMIF($M$2:$AG$2,AK$2,$M129:$AG129) -> 0 | AL129: =SUMIF($M$2:$AG$2,AL$2,$M129:$AG129) -> 0 | AM129: =SUMIF($M$2:$AG$2,AM$2,$M129:$AG129) -> 0 | AN129: =SUMIF($M$2:$AG$2,AN$2,$M129:$AG129) -> 0
K130: Closing Balance | L130: =SUM(L128:L129) -> 8827 | M130: =SUM(M128:M129) -> 0 | N130: =SUM(N128:N129) -> 0 | O130: =SUM(O128:O129) -> 0 | P130: =SUM(P128:P129) -> 0 | Q130: =SUM(Q128:Q129) -> 0 | R130: =SUM(R128:R129) -> 0 | S130: =SUM(S128:S129) -> 0 | ... AG130: =SUM(AG128:AG129) -> 0 | AI130: =SUM(AI128:AI129) -> 0 | AJ130: =SUM(AJ128:AJ129) -> 0 | AK130: =SUM(AK128:AK129) -> 0 | AL130: =SUM(AL128:AL129) -> 0 | AM130: =SUM(AM128:AM129) -> 0 | AN130: =SUM(AN128:AN129) -> 0
D132: Growth and Fiscal levies | E132: Unit | F132: Conservative | G132: Moderate | H132: Optimistic | I132: Live
D133: Net additions rate | E133: % of begin. bal. | F133: =AVERAGE('Quarterly Historical Financials'!$D293:$D293) -> 0 | G133: =AVERAGE('Quarterly Historical Financials'!$D293:$D293) -> 0 | H133: =AVERAGE('Quarterly Historical Financials'!$D293:$D293) -> 0 | I133: =CHOOSE($G$4,F133,G133,H133) -> 0
...

Sheet Comps
B1: All amounts in thousands of GHS unless stated otherwise
B2: Company | C2: Ticker | D2: Price | F2: Shares Outstanding | H2: Operating Income | J2: Operating Profit | L2: Net Profit | N2: Market Capitalization | P2: Cash | R2: Investments | T2: Loans | V2: Total Assets | X2: Total Deposits | Z2: Borrowings | AB2: Total Liabilities | AD2: Total Equity | AF2: Price-to-Earnings (P/E) | AH2: Earnings Per Share (EPS) | AJ2: Price-to-Deposit (P/D) | AL2: Price-to-Book (P/B) | AN2: Cash-to-Deposit | AP2: Investment-to-Deposit | AR2: Loan-to-Deposit | AT2: Return on Assets (ROA) | AV2: Return on Equity (ROE) | AX2: Cost-to-Income
D3: 2024 | E3: 2025 | F3: 2024 | G3: Q3 2025 | H3: 2024 | I3: Q3 2025 | J3: 2024 | K3: Q3 2025 | L3: 2024 | M3: Q3 2025 | N3: 2024 | O3: Q3 2025 | P3: 2024 | Q3: Q3 2025 | R3: 2024 | S3: Q3 2025 | T3: 2024 | U3: Q3 2025 | V3: 2024 | W3: Q3 2025 | X3: 2024 | Y3: Q3 2025 | Z3: 2024 | AA3: Q3 2025 | AB3: 2024 | AC3: Q3 2025 | AD3: 2024 | AE3: Q3 2025 | AF3: 2024 | AG3: Q3 2025 | AH3: 2024 | AI3: Q3 2025 | AJ3: 2024 | AK3: Q3 2025 | AL3: 2024 | AM3: Q3 2025 | AN3: 2024 | AO3: Q3 2025 | AP3: 2024 | AQ3: Q3 2025 | AR3: 2024 | AS3: Q3 2025 | AT3: 2024 | AU3: Q3 2025 | AV3: 2024 | AW3: Q3 2025 | AX3: 2024 | AY3: Q3 2025
B4: Access Bank Ghana | C4: GSE.ACCESS | D4: 5.2 | E4: =C45 -> 16.2 | F4: 173947 | G4: 173947 | H4: 1967987 | I4: 1224917 | J4: 959201 | K4: 680995 | L4: 536912 | M4: 442651 | N4: =D4*F4 -> 904524.4 | O4: =E4*G4 -> 2817941.4 | P4: 3944691 | Q4: 4246012 | R4: 5548283 | S4: 6208430 | T4: 3699019 | U4: 3591249 | V4: 16561742 | W4: 19404182 | X4: =115742+13042304 -> 13158046 | Y4: =530328+14015293 -> 14545621 | Z4: 959328 | AA4: 916001 | AB4: 14804021 | AC4: 17267213 | AD4: 1757721 | AE4: 2136969 | AF4: =N4/L4 -> 1.6846791 | AG4: =O4/M4 -> 6.3660568 | AH4: =L4/F4 -> 3.0866413 | AI4: =M4/G4 -> 2.5447464 | AJ4: =N4/X4 -> 0.068743064 | AK4: =O4/Y4 -> 0.19373125 | AL4: =N4/AD4 -> 0.51460067 | AM4: =O4/AE4 -> 1.3186627 | AN4: =P4/X4 -> 0.29979307 | AO4: =Q4/Y4 -> 0.29190998 | AP4: =R4/X4 -> 0.42166466 | AQ4: =S4/Y4 -> 0.42682468 | AR4: =T4/X4 -> 0.28112221 | AS4: =U4/Y4 -> 0.24689554 | AT4: =L4/V4 -> 0.032418812 | AU4: =M4/W4 -> 0.022812144 | AV4: =M4/AD4 -> 0.25183234 | AW4: =N4/AE4 -> 0.42327446 | AX4: =(H4-J4)/H4 -> 0.5125979 | AY4: =(I4-K4)/I4 -> 0.44404805
B5: Agricultural Development Bank | C5: GSE.ADB | D5: 5.06 | E5: =C46 -> 5.06 | F5: 1660317.6 | G5: =282254/0.17 -> 1660317.6 | H5: 1004751 | I5: 1173756 | J5: -255091 | K5: 447489 | L5: 35061 | M5: 282254 | N5: =D5*F5 -> 8401207.3 | O5: =E5*G5 -> 8401207.3 | P5: 7176917 | Q5: 6465541 | R5: 3804236 | S5: 6448667 | T5: 2574527 | U5: 2360188 | V5: 14604777 | W5: 16222716 | X5: 12045885 | Y5: 12851137 | Z5: 929864 | AA5: 1328365 | AB5: 13326732 | AC5: 14662416 | AD5: 1278045 | AE5: 1560300 | AF5: =N5/L5 -> 239.61688 | AG5: =O5/M5 -> 29.764706 | AH5: =L5/F5 -> 0.021117044 | AI5: =M5/G5 -> 0.17 | AJ5: =N5/X5 -> 0.6974338 | AK5: =O5/Y5 -> 0.65373261 | AL5: =N5/AD5 -> 6.5734832 | AM5: =O5/AE5 -> 5.3843538 | AN5: =P5/X5 -> 0.59579823 | AO5: =Q5/Y5 -> 0.50311043 | AP5: =R5/X5 -> 0.31581208 | AQ5: =S5/Y5 -> 0.50179739 | AR5: =T5/X5 -> 0.21372668 | AS5: =U5/Y5 -> 0.18365597 | AT5: =L5/V5 -> 0.0024006529 | AU5: =M5/W5 -> 0.01739869 | AV5: =M5/AD5 -> 0.22084825 | AW5: =N5/AE5 -> 5.3843538 | AX5: =(H5-J5)/H5 -> 1.2538848 | AY5: =(I5-K5)/I5 -> 0.61875466
B6: CalBank | C6: GSE.CAL | D6: 0.35 | E6: =C52 -> 0.64 | F6: 854075 | G6: 854075 | H6: 802511 | I6: 564814 | J6: 414158 | K6: 354356 | L6: 267720 | M6: 223877 | N6: =D6*F6 -> 298926.25 | O6: =E6*G6 -> 546608 | P6: 2808619 | Q6: 2217340 | R6: 4905669 | S6: 5190103 | T6: 2101996 | U6: 1275992 | V6: 11688797 | W6: 10894291 | X6: =226138+9431527 -> 9657665 | Y6: =190708+8542803 -> 8733511 | Z6: 1537162 | AA6: 1356729 | AB6: 11416233 | AC6: 10397850 | AD6: 272564 | AE6: 496441 | AF6: =N6/L6 -> 1.116563 | AG6: =O6/M6 -> 2.441555 | AH6: =L6/F6 -> 0.31346193 | AI6: =M6/G6 -> 0.26212803 | AJ6: =N6/X6 -> 0.030952228 | AK6: =O6/Y6 -> 0.062587429 | AL6: =N6/AD6 -> 1.0967195 | AM6: =O6/AE6 -> 1.1010533 | AN6: =P6/X6 -> 0.2908176 | AO6: =Q6/Y6 -> 0.25388873 | AP6: =R6/X6 -> 0.50795601 | AQ6: =S6/Y6 -> 0.59427451 | AR6: =T6/X6 -> 0.21765054 | AS6: =U6/Y6 -> 0.14610298 | AT6: =L6/V6 -> 0.022903982 | AU6: =M6/W6 -> 0.020549938 | AV6: =M6/AD6 -> 0.82137406 | AW6: =N6/AE6 -> 0.60213852 | AX6: =(H6-J6)/H6 -> 0.48392234 | AY6: =(I6-K6)/I6 -> 0.3726147
B7: Ecobank Ghana | C7: GSE.EGH | D7: 6.5 | E7: =C58 -> 25 | F7: 322551 | G7: 322551 | H7: 5359271 | I7: 3751823 | J7: 2357827 | K7: 2108766 | L7: 1699624 | M7: 1416058 | N7: =D7*F7 -> 2096581.5 | O7: =E7*G7 -> 8063775 | P7: 20742337 | Q7: 19819733 | R7: 10481612 | S7: 10283270 | T7: 10600525 | U7: 12118312 | V7: 46002475 | W7: 49899168 | X7: =5998760+32454666 -> 38453426 | Y7: =6116669+34543958 -> 40660627 | Z7: 394001 | AA7: 487562 | AB7: 40602803 | AC7: 43183855 | AD7: 5399672 | AE7: 6715313 | AF7: =N7/L7 -> 1.2335561 | AG7: =O7/M7 -> 5.6945231 | AH7: =L7/F7 -> 5.2693187 | AI7: =M7/G7 -> 4.3901833 | AJ7: =N7/X7 -> 0.054522619 | AK7: =O7/Y7 -> 0.198319 | AL7: =N7/AD7 -> 0.38827942 | AM7: =O7/AE7 -> 1.200804 | AN7: =P7/X7 -> 0.53941454 | AO7: =Q7/Y7 -> 0.48744288 | AP7: =R7/X7 -> 0.27257941 | AQ7: =S7/Y7 -> 0.25290486 | AR7: =T7/X7 -> 0.2756718 | AS7: =U7/Y7 -> 0.29803554 | AT7: =L7/V7 -> 0.03694636 | AU7: =M7/W7 -> 0.028378389 | AV7: =M7/AD7 -> 0.26224889 | AW7: =N7/AE7 -> 0.31220905 | AX7: =(H7-J7)/H7 -> 0.56004707 | AY7: =(I7-K7)/I7 -> 0.43793564
B8: GCB Bank | C8: GSE.GCB | D8: 6.37 | E8: =C63 -> 20.11 | F8: 265000 | G8: 265000 | H8: 4476729 | I8: 4346527 | J8: 1892018 | K8: 2023672 | L8: 1200872 | M8: 1297420 | N8: =D8*F8 -> 1688050 | O8: =E8*G8 -> 5329150 | P8: 14443976 | Q8: 11242971 | R8: 13473412 | S8: 19339862 | T8: 10229504 | U8: 13768492 | V8: 42796072 | W8: 50229864 | X8: =558181+33970718 -> 34528899 | Y8: =217854+37539455 -> 37757309 | Z8: 2742194 | AA8: 5132199 | AB8: 38453734 | AC8: 44563707 | AD8: 4342338 | AE8: 5666157 | AF8: =N8/L8 -> 1.4056869 | AG8: =O8/M8 -> 4.107498 | AH8: =L8/F8 -> 4.5315925 | AI8: =M8/G8 -> 4.8959245 | AJ8: =N8/X8 -> 0.048888034 | AK8: =O8/Y8 -> 0.14114221 | AL8: =N8/AD8 -> 0.38874219 | AM8: =O8/AE8 -> 0.94052283 | AN8: =P8/X8 -> 0.41831557 | AO8: =Q8/Y8 -> 0.29776939 | AP8: =R8/X8 -> 0.39020682 | AQ8: =S8/Y8 -> 0.51221505 | AR8: =T8/X8 -> 0.2962592 | AS8: =U8/Y8 -> 0.36465766 | AT8: =L8/V8 -> 0.028060332 | AU8: =M8/W8 -> 0.025829654 | AV8: =M8/AD8 -> 0.29878374 | AW8: =N8/AE8 -> 0.29791797 | AX8: =(H8-J8)/H8 -> 0.57736597 | AY8: =(I8-K8)/I8 -> 0.53441633
B9: Republic Bank Ghana | C9: GSE.RBGH | D9: 0.66 | E9: =C73 -> 1.3 | F9: 852000 | G9: 852000 | H9: 869167 | I9: 749789 | J9: 329039 | K9: 308561 | L9: 210679 | M9: 202378 | N9: =D9*F9 -> 562320 | O9: =E9*G9 -> 1107600 | P9: 4470758 | Q9: 4024490 | R9: 1627456 | S9: 1790105 | T9: 3054049 | U9: 3121579 | V9: 9593329 | W9: 9832466 | X9: 6056125 | Y9: 6001396 | Z9: 1732880 | AA9: 1790105 | AB9: 8537633 | AC9: 8574392 | AD9: 1055696 | AE9: 1258074 | AF9: =N9/L9 -> 2.6690842 | AG9: =O9/M9 -> 5.4729269 | AH9: =L9/F9 -> 0.24727582 | AI9: =M9/G9 -> 0.23753286 | AJ9: =N9/X9 -> 0.092851452 | AK9: =O9/Y9 -> 0.18455706 | AL9: =N9/AD9 -> 0.53265334 | AM9: =O9/AE9 -> 0.88039336 | AN9: =P9/X9 -> 0.73822089 | AO9: =Q9/Y9 -> 0.67059231 | AP9: =R9/X9 -> 0.26872893 | AQ9: =S9/Y9 -> 0.29828143 | AR9: =T9/X9 -> 0.50429095 | AS9: =U9/Y9 -> 0.52014215 | AT9: =L9/V9 -> 0.02196099 | AU9: =M9/W9 -> 0.020582629 | AV9: =M9/AD9 -> 0.19170102 | AW9: =N9/AE9 -> 0.44696894 | AX9: =(H9-J9)/H9 -> 0.62143178 | AY9: =(I9-K9)/I9 -> 0.58846956
B10: Societe Generale Ghana | C10: GSE.SOGEGH | D10: 1.5 | E10: =C78 -> 4.49 | F10: 709141.37 | G10: 709141.37 | H10: 1455550.9 | I10: 1035792 | J10: 838400.95 | K10: 529984 | L10: 551299.25 | M10: 344303 | N10: =D10*F10 -> 1063712.1 | O10: =E10*G10 -> 3184044.7 | P10: 3579482.6 | Q10: 2592298 | R10: 780949.31 | S10: 2352500 | T10: 5011684.5 | U10: 4319635 | V10: 10396291 | W10: 10520259 | X10: =30764.48+6219856.675 -> 6250621.2 | Y10: =10357+6254001 -> 6264358 | Z10: 520138.68 | AA10: 371418 | AB10: 7950408.8 | AC10: 7971182 | AD10: 2445881.9 | AE10: 2549077 | AF10: =N10/L10 -> 1.929464 | AG10: =O10/M10 -> 9.2477984 | AH10: =L10/F10 -> 0.77741798 | AI10: =M10/G10 -> 0.48552096 | AJ10: =N10/X10 -> 0.17017702 | AK10: =O10/Y10 -> 0.5082795 | AL10: =N10/AD10 -> 0.43489918 | AM10: =O10/AE10 -> 1.2490971 | AN10: =P10/X10 -> 0.5726603 | AO10: =Q10/Y10 -> 0.41381703 | AP10: =R10/X10 -> 0.12493947 | AQ10: =S10/Y10 -> 0.37553729 | AR10: =T10/X10 -> 0.80178983 | AS10: =U10/Y10 -> 0.68955749 | AT10: =L10/V10 -> 0.053028456 | AU10: =M10/W10 -> 0.032727616 | AV10: =M10/AD10 -> 0.14076845 | AW10: =N10/AE10 -> 0.41729302 | AX10: =(H10-J10)/H10 -> 0.42399752 | AY10: =(I10-K10)/I10 -> 0.4883297
B11: Standard Chartered Bank Ghana | C11: GSE.SCB | D11: 23 | E11: =C75 -> 29.22 | F11: 134758 | G11: 134758 | H11: 1807200 | I11: 1389328 | J11: 1022155 | K11: 793072 | L11: 716148 | M11: 508571 | N11: =D11*F11 -> 3099434 | O11: =E11*G11 -> 3937628.8 | P11: 4593873 | Q11: 5809442 | R11: 3680729 | S11: 5471846 | T11: =2532470+2305886 -> 4838356 | U11: =1652890+2040091 -> 3692981 | V11: 14303463 | W11: 16560337 | X11: =124582+11308032 -> 11432614 | Y11: =181852+12680660 -> 12862512 | Z11: 0 | AA11: 0 | AB11: 12250714 | AC11: 14140304 | AD11: 2052749 | AE11: 2420033 | AF11: =N11/L11 -> 4.3279238 | AG11: =O11/M11 -> 7.742535 | AH11: =L11/F11 -> 5.3143264 | AI11: =M11/G11 -> 3.7739578 | AJ11: =N11/X11 -> 0.27110458 | AK11: =O11/Y11 -> 0.30613217 | AL11: =N11/AD11 -> 1.5098943 | AM11: =O11/AE11 -> 1.6270971 | AN11: =P11/X11 -> 0.40182175 | AO11: =Q11/Y11 -> 0.45165688 | AP11: =R11/X11 -> 0.32194991 | AQ11: =S11/Y11 -> 0.42541037 | AR11: =T11/X11 -> 0.42320645 | AS11: =U11/Y11 -> 0.28711196 | AT11: =L11/V11 -> 0.050068155 | AU11: =M11/W11 -> 0.030710184 | AV11: =M11/AD11 -> 0.24775119 | AW11: =N11/AE11 -> 1.2807404 | AX11: =(H11-J11)/H11 -> 0.43439852 | AY11: =(I11-K11)/I11 -> 0.42916863
B13: First Atlantic Bank Ghana | C13: GSE.FAB | D13: =C61 -> 7.97 | E13: =C61 -> 7.97 | F13: ='Quarterly Historical Financials'!AI34 -> 334173.89 | G13: ='Quarterly Historical Financials'!AJ34 -> 349617.46 | H13: ='Quarterly Historical Financials'!AI17 -> 1092802 | I13: ='Quarterly Historical Financials'!AJ17 -> 1302415.4 | J13: ='Quarterly Historical Financials'!AI27 -> 539302 | K13: ='Quarterly Historical Financials'!AJ27 -> 702994.45 | L13: ='Quarterly Historical Financials'!AI32 -> 336679 | M13: ='Quarterly Historical Financials'!AJ32 -> 482871.06 | N13: =D13*F13 -> 2663365.9 | O13: =E13*G13 -> 2786451.2 | P13: ='Quarterly Historical Financials'!AI41 -> 4600045 | Q13: ='Quarterly Historical Financials'!AJ41 -> 8104418.8 | R13: ='Quarterly Historical Financials'!AI43 -> 2647258 | S13: ='Quarterly Historical Financials'!AJ43 -> 3178870.4 | T13: ='Quarterly Historical Financials'!AI44 -> 1927368 | U13: ='Quarterly Historical Financials'!AJ44 -> 1947024.8 | V13: ='Quarterly Historical Financials'!AI56 -> 13323325 | W13: ='Quarterly Historical Financials'!AJ56 -> 19192992 | X13: ='Quarterly Historical Financials'!AI59+'Quarterly Historical Financials'!AI60 -> 11611039 | Y13: ='Quarterly Historical Financials'!AJ59+'Quarterly Historical Financials'!AJ60 -> 16642450 | Z13: 0 | AA13: 0 | AB13: ='Quarterly Historical Financials'!AI66 -> 11726491 | AC13: ='Quarterly Historical Financials'!AJ66 -> 16984597 | AD13: ='Quarterly Historical Financials'!AI76 -> 1596834 | AE13: ='Quarterly Historical Financials'!AJ76 -> 2208394.7 | AF13: =N13/L13 -> 7.9106981 | AG13: =O13/M13 -> 5.7705905 | AH13: =L13/F13 -> 1.0074964 | AI13: =M13/G13 -> 1.3811412 | AJ13: =N13/X13 -> 0.22938222 | AK13: =O13/Y13 -> 0.16743035 | AL13: =N13/AD13 -> 1.6679041 | AM13: =O13/AE13 -> 1.2617542 | AN13: =P13/X13 -> 0.39617858 | AO13: =Q13/Y13 -> 0.48697271 | AP13: =R13/X13 -> 0.22799493 | AQ13: =S13/Y13 -> 0.19100976 | AR13: =T13/X13 -> 0.16599445 | AS13: =U13/Y13 -> 0.11699148 | AT13: =L13/V13 -> 0.025269893 | AU13: =M13/W13 -> 0.025158718 | AV13: =M13/AD13 -> 0.30239277 | AW13: =N13/AE13 -> 1.206019 | AX13: =(H13-J13)/H13 -> 0.50649614 | AY13: =(I13-K13)/I13 -> 0.46023791
B15: Low | C15: MIN | D15: =MIN(D$4:D$11) -> 0.35 | E15: =MIN(E$4:E$11) -> 0.64 | F15: =MIN(F$4:F$11) -> 134758 | G15: =MIN(G$4:G$11) -> 134758 | H15: =MIN(H$4:H$11) -> 802511 | I15: =MIN(I$4:I$11) -> 564814 | J15: =MIN(J$4:J$11) -> -255091 | K15: =MIN(K$4:K$11) -> 308561 | ... AY15: =MIN(AY$4:AY$11) -> 0.3726147
B16: Mean | C16: AVG | D16: =AVERAGE(D$4:D$11) -> 6.08 | E16: =AVERAGE(E$4:E$11) -> 12.7525 | F16: =AVERAGE(F$4:F$11) -> 621473.75 | G16: =AVERAGE(G$4:G$11) -> 621473.75 | H16: =AVERAGE(H$4:H$11) -> 2217895.9 | I16: =AVERAGE(I$4:I$11) -> 1779593.2 | J16: =AVERAGE(J$4:J$11) -> 944713.49 | K16: =AVERAGE(K$4:K$11) -> 905861.88 | ... AY16: =AVERAGE(AY$4:AY$11) -> 0.48921716
B17: Median | C17: MED | D17: =MEDIAN(D$4:D$11) -> 5.13 | E17: =MEDIAN(E$4:E$11) -> 10.63 | F17: =MEDIAN(F$4:F$11) -> 515846.18 | G17: =MEDIAN(G$4:G$11) -> 515846.18 | H17: =MEDIAN(H$4:H$11) -> 1631375.5 | I17: =MEDIAN(I$4:I$11) -> 1199336.5 | J17: =MEDIAN(J$4:J$11) -> 898800.98 | K17: =MEDIAN(K$4:K$11) -> 605489.5 | ... AY17: =MEDIAN(AY$4:AY$11) -> 0.46618887
B18: High | C18: MAX | D18: =MAX(D$4:D$11) -> 23 | E18: =MAX(E$4:E$11) -> 29.22 | F18: =MAX(F$4:F$11) -> 1660317.6 | G18: =MAX(G$4:G$11) -> 1660317.6 | H18: =MAX(H$4:H$11) -> 5359271 | I18: =MAX(I$4:I$11) -> 4346527 | J18: =MAX(J$4:J$11) -> 2357827 | K18: =MAX(K$4:K$11) -> 2108766 | ... AY18: =MAX(AY$4:AY$11) -> 0.61875466
C21: AVG
B23: FAB VALUATION - P/E
B24: FAB EPS | C24: =AI13 -> 1.3811412 | H24: AVERAGE
B25: Industry P/E Multiple | C25: =SUMIF($C$15:$C$18,$C$21,AG15:$AG$18) -> 8.8546999 | H25: Price | I25: =AVERAGE(C26,C32,C38) -> 12.142444
B26: Implied Value | C26: =C24*C25 -> 12.22959 | H26: Potential | I26: =I25/E13-1 -> 0.52351871
B27: Potential | C27: =C26/E13-1 -> 0.534453
B29: FAB VALUATION - P/B
B30: FAB BPS | C30: =AE13/G13 -> 6.3166029
B31: Industry P/B Multiple | C31: =SUMIF($C$15:$C$18,$C$21,AM$15:$AM18) -> 1.712748
B32: Implied Value | C32: =C30*C31 -> 10.818749
B33: Potential | C33: =C32/E13-1 -> 0.35743403
B35: FAB VALUATION - P/D
B36: FAB DPS | C36: =Y13/G13 -> 47.601883
B37: Industry P/D Multiple | C37: =SUMIF($C$15:$C$18,$C$21,AK$15:$AK18) -> 0.28106015
B38: Implied Value | C38: =C36*C37 -> 13.378993
B39: Potential | C39: =C38/E13-1 -> 0.67866909
B44: Ticker | C44: Price
B45: ACCESS | C45: 16.2
B46: ADB | C46: 5.06
B47: AGA | C47: 37
B48: ALLGH | C48: 6.12
B49: ALW | C49: 0.1
B50: ASG | C50: 8.89
B51: BOPP | C51: 55.82
B52: CAL | C52: 0.64
B53: CLYD | C53: 0.46
B54: CMLT | C54: 0.14
B55: CPC | C55: 0.05
B56: DASPHARMA | C56: 0.38
... B82: UNIL | C82: 19.79

Sheet Quarterly Historical Financials
B1: FIRST ATLANTIC BANK LIMITED
C2: Year | F2: =YEAR(F4) -> 2020 | G2: =YEAR(G4) -> 2020 | H2: =YEAR(H4) -> 2020 | I2: =YEAR(I4) -> 2020 | J2: =YEAR(J4) -> 2021 | K2: =YEAR(K4) -> 2021 | L2: =YEAR(L4) -> 2021 | M2: =YEAR(M4) -> 2021 | ... AC2: =YEAR(AC4) -> 2025 | AE2: =YEAR(AE4) -> 2020 | AF2: =YEAR(AF4) -> 2021 | AG2: =YEAR(AG4) -> 2022 | AH2: =YEAR(AH4) -> 2023 | AI2: =YEAR(AI4) -> 2024 | AJ2: =YEAR(AJ4) -> 2025
C3: Start Date | F3: =DATE(2020,1,1) -> 43831 | G3: =F4+1 -> 43922 | H3: =G4+1 -> 44013 | I3: =H4+1 -> 44105 | J3: =I4+1 -> 44197 | K3: =J4+1 -> 44287 | L3: =K4+1 -> 44378 | M3: =L4+1 -> 44470 | N3: =M4+1 -> 44562 | ... AC3: =AB4+1 -> 45931 | AE3: =F3 -> 43831 | AF3: =AE4+1 -> 44197 | AG3: =AF4+1 -> 44562 | AH3: =AG4+1 -> 44927 | AI3: =AH4+1 -> 45292 | AJ3: =AI4+1 -> 45658
C4: End Date | F4: =EOMONTH(F3,2) -> 43921 | G4: =EOMONTH(G3,2) -> 44012 | H4: =EOMONTH(H3,2) -> 44104 | I4: =EOMONTH(I3,2) -> 44196 | J4: =EOMONTH(J3,2) -> 44286 | K4: =EOMONTH(K3,2) -> 44377 | L4: =EOMONTH(L3,2) -> 44469 | M4: =EOMONTH(M3,2) -> 44561 | ... AC4: =EOMONTH(AC3,2) -> 46022 | AE4: =EOMONTH(AE3,11) -> 44196 | AF4: =EOMONTH(AF3,11) -> 44561 | AG4: =EOMONTH(AG3,11) -> 44926 | AH4: =EOMONTH(AH3,11) -> 45291 | AI4: =EOMONTH(AI3,11) -> 45657 | AJ4: =EOMONTH(AJ3,11) -> 46022
B5: All amounts in thousands of GHS unless stated otherwise | C5: Period | F5: =F4-F3+1 -> 91 | G5: =G4-G3+1 -> 91 | H5: =H4-H3+1 -> 92 | I5: =I4-I3+1 -> 92 | J5: =J4-J3+1 -> 90 | K5: =K4-K3+1 -> 91 | L5: =L4-L3+1 -> 92 | M5: =M4-M3+1 -> 92 | ... AC5: =AC4-AC3+1 -> 92 | AE5: =AE4-AE3+1 -> 366 | AF5: =AF4-AF3+1 -> 365 | AG5: =AG4-AG3+1 -> 365 | AH5: =AH4-AH3+1 -> 365 | AI5: =AI4-AI3+1 -> 366 | AJ5: =AJ4-AJ3+1 -> 365
B7: Income Statement
B9: Interest Income | F9: ='Raw Historical Financials'!C4 -> 64659 | G9: ='Raw Historical Financials'!D4-'Raw Historical Financials'!C4 -> 67580 | H9: ='Raw Historical Financials'!E4-'Raw Historical Financials'!D4 -> 69390 | I9: ='Raw Historical Financials'!F4-'Raw Historical Financials'!E4 -> 79260 | J9: ='Raw Historical Financials'!G4 -> 74514 | K9: ='Raw Historical Financials'!H4-'Raw Historical Financials'!G4 -> 80826 | L9: ='Raw Historical Financials'!I4-'Raw Historical Financials'!H4 -> 88836 | M9: ='Raw Historical Financials'!J4-'Raw Historical Financials'!I4 -> 141537 | N9: ='Raw Historical Financials'!K4 -> 103740 | O9: ='Raw Historical Financials'!L4-'Raw Historical Financials'!K4 -> 101585 | P9: ='Raw Historical Financials'!M4-'Raw Historical Financials'!L4 -> 152068 | Q9: ='Raw Historical Financials'!N4-'Raw Historical Financials'!M4 -> 214565 | R9: ='Raw Historical Financials'!O4 -> 192749 | S9: ='Raw Historical Financials'!P4-'Raw Historical Financials'!O4 -> 181269 | T9: ='Raw Historical Financials'!Q4-'Raw Historical Financials'!P4 -> 186282 | U9: ='Raw Historical Financials'!R4-'Raw Historical Financials'!Q4 -> 287289 | V9: ='Raw Historical Financials'!S4 -> 196483 | W9: ='Raw Historical Financials'!T4-'Raw Historical Financials'!S4 -> 184644 | X9: ='Raw Historical Financials'!U4-'Raw Historical Financials'!T4 -> 207786 | Y9: ='Raw Historical Financials'!V4-'Raw Historical Financials'!U4 -> 289576 | Z9: ='Raw Historical Financials'!W4 -> 262481 | AA9: ='Raw Historical Financials'!X4-'Raw Historical Financials'!W4 -> 210277 | AB9: ='Raw Historical Financials'!Y4-'Raw Historical Financials'!X4 -> 276147 | AC9: ='Raw Historical Financials'!Z4-'Raw Historical Financials'!Y4 -> 681759.57 | AE9: =SUMIF($F$2:$AB$2,AE$2,$F9:$AB9) -> 280889 | AF9: =SUMIF($F$2:$AB$2,AF$2,$F9:$AB9) -> 385713 | AG9: =SUMIF($F$2:$AB$2,AG$2,$F9:$AB9) -> 571958 | AH9: =SUMIF($F$2:$AB$2,AH$2,$F9:$AB9) -> 847589 | AI9: =SUMIF($F$2:$AB$2,AI$2,$F9:$AB9) -> 878489 | AJ9: =SUMIF($F$2:$AC$2,AJ$2,$F9:$AC9) -> 1430664.6
B10: Interest Expense | F10: ='Raw Historical Financials'!C5 -> -20899 | G10: ='Raw Historical Financials'!D5-'Raw Historical Financials'!C5 -> -20237 | H10: ='Raw Historical Financials'!E5-'Raw Historical Financials'!D5 -> -20666 | I10: ='Raw Historical Financials'!F5-'Raw Historical Financials'!E5 -> -21443 | J10: ='Raw Historical Financials'!G5 -> -19112 | K10: ='Raw Historical Financials'!H5-'Raw Historical Financials'!G5 -> -20071 | L10: ='Raw Historical Financials'!I5-'Raw Historical Financials'!H5 -> -21214 | M10: ='Raw Historical Financials'!J5-'Raw Historical Financials'!I5 -> -26565 | N10: ='Raw Historical Financials'!K5 -> -25345 | O10: ='Raw Historical Financials'!L5-'Raw Historical Financials'!K5 -> -28249 | P10: ='Raw Historical Financials'!M5-'Raw Historical Financials'!L5 -> -42337 | Q10: ='Raw Historical Financials'!N5-'Raw Historical Financials'!M5 -> -63530 | R10: ='Raw Historical Financials'!O5 -> -54670 | S10: ='Raw Historical Financials'!P5-'Raw Historical Financials'!O5 -> -44494 | T10: ='Raw Historical Financials'!Q5-'Raw Historical Financials'!P5 -> -40424 | U10: ='Raw Historical Financials'!R5-'Raw Historical Financials'!Q5 -> -45415 | V10: ='Raw Historical Financials'!S5 -> -51822 | W10: ='Raw Historical Financials'!T5-'Raw Historical Financials'!S5 -> -58526 | X10: ='Raw Historical Financials'!U5-'Raw Historical Financials'!T5 -> -75926 | Y10: ='Raw Historical Financials'!V5-'Raw Historical Financials'!U5 -> -116127 | Z10: ='Raw Historical Financials'!W5 -> -97346 | AA10: ='Raw Historical Financials'!X5-'Raw Historical Financials'!W5 -> -129608 | AB10: ='Raw Historical Financials'!Y5-'Raw Historical Financials'!X5 -> -138688 | AC10: ='Raw Historical Financials'!Z5-'Raw Historical Financials'!Y5 -> -102371.52 | AE10: =SUMIF($F$2:$AB$2,AE$2,$F10:$AB10) -> -83245 | AF10: =SUMIF($F$2:$AB$2,AF$2,$F10:$AB10) -> -86962 | AG10: =SUMIF($F$2:$AB$2,AG$2,$F10:$AB10) -> -159461 | AH10: =SUMIF($F$2:$AB$2,AH$2,$F10:$AB10) -> -185003 | AI10: =SUMIF($F$2:$AB$2,AI$2,$F10:$AB10) -> -302401 | AJ10: =SUMIF($F$2:$AC$2,AJ$2,$F10:$AC10) -> -468013.52
B11: Net Interest Income | F11: =SUM(F9:F10) -> 43760 | G11: =SUM(G9:G10) -> 47343 | H11: =SUM(H9:H10) -> 48724 | I11: =SUM(I9:I10) -> 57817 | J11: =SUM(J9:J10) -> 55402 | K11: =SUM(K9:K10) -> 60755 | L11: =SUM(L9:L10) -> 67622 | M11: =SUM(M9:M10) -> 114972 | ... AC11: =SUM(AC9:AC10) -> 579388.04 | AE11: =SUM(AE9:AE10) -> 197644 | AF11: =SUM(AF9:AF10) -> 298751 | AG11: =SUM(AG9:AG10) -> 412497 | AH11: =SUM(AH9:AH10) -> 662586 | AI11: =SUM(AI9:AI10) -> 576088 | AJ11: =SUM(AJ9:AJ10) -> 962651.04
B12: Fee and commission income | F12: ='Raw Historical Financials'!C7 -> 15737 | G12: ='Raw Historical Financials'!D7-'Raw Historical Financials'!C7 -> 16087 | H12: ='Raw Historical Financials'!E7-'Raw Historical Financials'!D7 -> 18152 | I12: ='Raw Historical Financials'!F7-'Raw Historical Financials'!E7 -> 7465 | J12: ='Raw Historical Financials'!G7 -> 15288 | K12: ='Raw Historical Financials'!H7-'Raw Historical Financials'!G7 -> 13214 | L12: ='Raw Historical Financials'!I7-'Raw Historical Financials'!H7 -> 16099 | M12: ='Raw Historical Financials'!J7-'Raw Historical Financials'!I7 -> 36811 | N12: ='Raw Historical Financials'!K7 -> 18434 | O12: ='Raw Historical Financials'!L7-'Raw Historical Financials'!K7 -> 19898 | P12: ='Raw Historical Financials'!M7-'Raw Historical Financials'!L7 -> 23255 | Q12: ='Raw Historical Financials'!N7-'Raw Historical Financials'!M7 -> 75049 | R12: ='Raw Historical Financials'!O7 -> 30857 | S12: ='Raw Historical Financials'!P7-'Raw Historical Financials'!O7 -> 34719 | T12: ='Raw Historical Financials'!Q7-'Raw Historical Financials'!P7 -> 38481 | U12: ='Raw Historical Financials'!R7-'Raw Historical Financials'!Q7 -> 79927 | V12: ='Raw Historical Financials'!S7 -> 32415 | W12: ='Raw Historical Financials'!T7-'Raw Historical Financials'!S7 -> 54359 | X12: ='Raw Historical Financials'!U7-'Raw Historical Financials'!T7 -> 53377 | Y12: ='Raw Historical Financials'!V7-'Raw Historical Financials'!U7 -> 138893 | Z12: ='Raw Historical Financials'!W7 -> 57745 | AA12: ='Raw Historical Financials'!X7-'Raw Historical Financials'!W7 -> 79408 | AB12: ='Raw Historical Financials'!Y7-'Raw Historical Financials'!X7 -> 80299 | AC12: ='Raw Historical Financials'!Z7-'Raw Historical Financials'!Y7 -> 76446.237 | AE12: =SUMIF($F$2:$AB$2,AE$2,$F12:$AB12) -> 57441 | AF12: =SUMIF($F$2:$AB$2,AF$2,$F12:$AB12) -> 81412 | AG12: =SUMIF($F$2:$AB$2,AG$2,$F12:$AB12) -> 136636 | AH12: =SUMIF($F$2:$AB$2,AH$2,$F12:$AB12) -> 183984 | AI12: =SUMIF($F$2:$AB$2,AI$2,$F12:$AB12) -> 279044 | AJ12: =SUMIF($F$2:$AC$2,AJ$2,$F12:$AC12) -> 293898.24
B13: Fee and commission expense | F13: ='Raw Historical Financials'!C8 -> 0 | G13: ='Raw Historical Financials'!D8-'Raw Historical Financials'!C8 -> 0 | H13: ='Raw Historical Financials'!E8-'Raw Historical Financials'!D8 -> 0 | I13: ='Raw Historical Financials'!F8-'Raw Historical Financials'!E8 -> -12482 | J13: ='Raw Historical Financials'!G8 -> 0 | K13: ='Raw Historical Financials'!H8-'Raw Historical Financials'!G8 -> 0 | L13: ='Raw Historical Financials'!I8-'Raw Historical Financials'!H8 -> 0 | M13: ='Raw Historical Financials'!J8-'Raw Historical Financials'!I8 -> -24812 | N13: ='Raw Historical Financials'!K8 -> 0 | O13: ='Raw Historical Financials'!L8-'Raw Historical Financials'!K8 -> 0 | P13: ='Raw Historical Financials'!M8-'Raw Historical Financials'!L8 -> 0 | Q13: ='Raw Historical Financials'!N8-'Raw Historical Financials'!M8 -> -41449 | R13: ='Raw Historical Financials'!O8 -> 0 | S13: ='Raw Historical Financials'!P8-'Raw Historical Financials'!O8 -> 0 | T13: ='Raw Historical Financials'!Q8-'Raw Historical Financials'!P8 -> 0 | U13: ='Raw Historical Financials'!R8-'Raw Historical Financials'!Q8 -> -60118 | V13: ='Raw Historical Financials'!S8 -> 0 | W13: ='Raw Historical Financials'!T8-'Raw Historical Financials'!S8 -> 0 | X13: ='Raw Historical Financials'!U8-'Raw Historical Financials'!T8 -> 0 | Y13: ='Raw Historical Financials'!V8-'Raw Historical Financials'!U8 -> -98846 | Z13: ='Raw Historical Financials'!W8 -> -26840 | AA13: ='Raw Historical Financials'!X8-'Raw Historical Financials'!W8 -> -38753 | AB13: ='Raw Historical Financials'!Y8-'Raw Historical Financials'!X8 -> -22529 | AC13: ='Raw Historical Financials'!Z8-'Raw Historical Financials'!Y8 -> -29426.085 | AE13: =SUMIF($F$2:$AB$2,AE$2,$F13:$AB13) -> -12482 | AF13: =SUMIF($F$2:$AB$2,AF$2,$F13:$AB13) -> -24812 | AG13: =SUMIF($F$2:$AB$2,AG$2,$F13:$AB13) -> -41449 | AH13: =SUMIF($F$2:$AB$2,AH$2,$F13:$AB13) -> -60118 | AI13: =SUMIF($F$2:$AB$2,AI$2,$F13:$AB13) -> -98846 | AJ13: =SUMIF($F$2:$AC$2,AJ$2,$F13:$AC13) -> -117548.09
B14: Net Fees and Commission Income | F14: =SUM(F12:F13) -> 15737 | G14: =SUM(G12:G13) -> 16087 | H14: =SUM(H12:H13) -> 18152 | I14: =SUM(I12:I13) -> -5017 | J14: =SUM(J12:J13) -> 15288 | K14: =SUM(K12:K13) -> 13214 | L14: =SUM(L12:L13) -> 16099 | M14: =SUM(M12:M13) -> 11999 | ... AC14: =SUM(AC12:AC13) -> 47020.152 | AE14: =SUM(AE12:AE13) -> 44959 | AF14: =SUM(AF12:AF13) -> 56600 | AG14: =SUM(AG12:AG13) -> 95187 | AH14: =SUM(AH12:AH13) -> 123866 | AI14: =SUM(AI12:AI13) -> 180198 | AJ14: =SUM(AJ12:AJ13) -> 176350.15
B15: Net trading income | F15: ='Raw Historical Financials'!C9 -> 13247 | G15: ='Raw Historical Financials'!D9-'Raw Historical Financials'!C9 -> 12034 | H15: ='Raw Historical Financials'!E9-'Raw Historical Financials'!D9 -> 9062 | I15: ='Raw Historical Financials'!F9-'Raw Historical Financials'!E9 -> 33204 | J15: ='Raw Historical Financials'!G9 -> 7979 | K15: ='Raw Historical Financials'!H9-'Raw Historical Financials'!G9 -> 7593 | L15: ='Raw Historical Financials'!I9-'Raw Historical Financials'!H9 -> 6754 | M15: ='Raw Historical Financials'!J9-'Raw Historical Financials'!I9 -> 11270 | N15: ='Raw Historical Financials'!K9 -> 15985 | O15: ='Raw Historical Financials'!L9-'Raw Historical Financials'!K9 -> 3150 | P15: ='Raw Historical Financials'!M9-'Raw Historical Financials'!L9 -> -2588 | Q15: ='Raw Historical Financials'!N9-'Raw Historical Financials'!M9 -> -9700 | R15: ='Raw Historical Financials'!O9 -> 28302 | S15: ='Raw Historical Financials'!P9-'Raw Historical Financials'!O9 -> 21369 | T15: ='Raw Historical Financials'!Q9-'Raw Historical Financials'!P9 -> 16251 | U15: ='Raw Historical Financials'!R9-'Raw Historical Financials'!Q9 -> 188932 | V15: ='Raw Historical Financials'!S9 -> 22827 | W15: ='Raw Historical Financials'!T9-'Raw Historical Financials'!S9 -> 15423 | X15: ='Raw Historical Financials'!U9-'Raw Historical Financials'!T9 -> 19306 | Y15: ='Raw Historical Financials'!V9-'Raw Historical Financials'!U9 -> 278097 | Z15: ='Raw Historical Financials'!W9 -> 13104 | AA15: ='Raw Historical Financials'!X9-'Raw Historical Financials'!W9 -> 72392 | AB15: ='Raw Historical Financials'!Y9-'Raw Historical Financials'!X9 -> 27893 | AC15: ='Raw Historical Financials'!Z9-'Raw Historical Financials'!Y9 -> 46887.804 | AE15: =SUMIF($F$2:$AB$2,AE$2,$F15:$AB15) -> 67547 | AF15: =SUMIF($F$2:$AB$2,AF$2,$F15:$AB15) -> 33596 | AG15: =SUMIF($F$2:$AB$2,AG$2,$F15:$AB15) -> 6847 | AH15: =SUMIF($F$2:$AB$2,AH$2,$F15:$AB15) -> 254854 | AI15: =SUMIF($F$2:$AB$2,AI$2,$F15:$AB15) -> 335653 | AJ15: =SUMIF($F$2:$AC$2,AJ$2,$F15:$AC15) -> 160276.8
B16: Other income | F16: ='Raw Historical Financials'!C10 -> 152 | G16: ='Raw Historical Financials'!D10-'Raw Historical Financials'!C10 -> 410 | H16: ='Raw Historical Financials'!E10-'Raw Historical Financials'!D10 -> 1073 | I16: ='Raw Historical Financials'!F10-'Raw Historical Financials'!E10 -> -7120 | J16: ='Raw Historical Financials'!G10 -> 275 | K16: ='Raw Historical Financials'!H10-'Raw Historical Financials'!G10 -> 292 | L16: ='Raw Historical Financials'!I10-'Raw Historical Financials'!H10 -> 333 | M16: ='Raw Historical Financials'!J10-'Raw Historical Financials'!I10 -> 1097 | N16: ='Raw Historical Financials'!K10 -> 345 | O16: ='Raw Historical Financials'!L10-'Raw Historical Financials'!K10 -> 2149 | P16: ='Raw Historical Financials'!M10-'Raw Historical Financials'!L10 -> 71 | Q16: ='Raw Historical Financials'!N10-'Raw Historical Financials'!M10 -> -509 | R16: ='Raw Historical Financials'!O10 -> 323 | S16: ='Raw Historical Financials'!P10-'Raw Historical Financials'!O10 -> 0 | T16: ='Raw Historical Financials'!Q10-'Raw Historical Financials'!P10 -> 172 | U16: ='Raw Historical Financials'!R10-'Raw Historical Financials'!Q10 -> 3224 | V16: ='Raw Historical Financials'!S10 -> 530 | W16: ='Raw Historical Financials'!T10-'Raw Historical Financials'!S10 -> 10 | X16: ='Raw Historical Financials'!U10-'Raw Historical Financials'!T10 -> 15 | Y16: ='Raw Historical Financials'!V10-'Raw Historical Financials'!U10 -> 308 | Z16: ='Raw Historical Financials'!W10 -> 2007 | AA16: ='Raw Historical Financials'!X10-'Raw Historical Financials'!W10 -> 131 | AB16: ='Raw Historical Financials'!Y10-'Raw Historical Financials'!X10 -> 673 | AC16: ='Raw Historical Financials'!Z10-'Raw Historical Financials'!Y10 -> 326.388 | AE16: =SUMIF($F$2:$AB$2,AE$2,$F16:$AB16) -> -5485 | AF16: =SUMIF($F$2:$AB$2,AF$2,$F16:$AB16) -> 1997 | AG16: =SUMIF($F$2:$AB$2,AG$2,$F16:$AB16) -> 2056 | AH16: =SUMIF($F$2:$AB$2,AH$2,$F16:$AB16) -> 3719 | AI16: =SUMIF($F$2:$AB$2,AI$2,$F16:$AB16) -> 863 | AJ16: =SUMIF($F$2:$AC$2,AJ$2,$F16:$AC16) -> 3137.388
B17: Operating Income | F17: =SUM(F11,F14:F16) -> 72896 | G17: =SUM(G11,G14:G16) -> 75874 | H17: =SUM(H11,H14:H16) -> 77011 | I17: =SUM(I11,I14:I16) -> 78884 | J17: =SUM(J11,J14:J16) -> 78944 | K17: =SUM(K11,K14:K16) -> 81854 | L17: =SUM(L11,L14:L16) -> 90808 | M17: =SUM(M11,M14:M16) -> 139338 | ... AC17: =SUM(AC11,AC14:AC16) -> 673622.39 | AE17: =SUM(AE11,AE14:AE16) -> 304665 | AF17: =SUM(AF11,AF14:AF16) -> 390944 | AG17: =SUM(AG11,AG14:AG16) -> 516587 | AH17: =SUM(AH11,AH14:AH16) -> 1045025 | AI17: =SUM(AI11,AI14:AI16) -> 1092802 | AJ17: =SUM(AJ11,AJ14:AJ16) -> 1302415.4
B18: Impairment losses on loans and advances | F18: ='Raw Historical Financials'!C12 -> -7000 | G18: ='Raw Historical Financials'!D12-'Raw Historical Financials'!C12 -> -9146 | H18: ='Raw Historical Financials'!E12-'Raw Historical Financials'!D12 -> -8947 | I18: ='Raw Historical Financials'!F12-'Raw Historical Financials'!E12 -> -7400 | J18: ='Raw Historical Financials'!G12 -> -7618 | K18: ='Raw Historical Financials'!H12-'Raw Historical Financials'!G12 -> -588 | L18: ='Raw Historical Financials'!I12-'Raw Historical Financials'!H12 -> -529 | M18: ='Raw Historical Financials'!J12-'Raw Historical Financials'!I12 -> -9074 | N18: ='Raw Historical Financials'!K12 -> -10462 | O18: ='Raw Historical Financials'!L12-'Raw Historical Financials'!K12 -> -5982 | P18: ='Raw Historical Financials'!M12-'Raw Historical Financials'!L12 -> -19852 | Q18: ='Raw Historical Financials'!N12-'Raw Historical Financials'!M12 -> -193528 | R18: ='Raw Historical Financials'!O12 -> -55740 | S18: ='Raw Historical Financials'!P12-'Raw Historical Financials'!O12 -> -38035 | T18: ='Raw Historical Financials'!Q12-'Raw Historical Financials'!P12 -> -50531 | U18: ='Raw Historical Financials'!R12-'Raw Historical Financials'!Q12 -> 66999 | V18: ='Raw Historical Financials'!S12 -> -10015 | W18: ='Raw Historical Financials'!T12-'Raw Historical Financials'!S12 -> -15623 | X18: ='Raw Historical Financials'!U12-'Raw Historical Financials'!T12 -> -75457 | Y18: ='Raw Historical Financials'!V12-'Raw Historical Financials'!U12 -> 62566 | Z18: ='Raw Historical Financials'!W12 -> 25416 | AA18: ='Raw Historical Financials'!X12-'Raw Historical Financials'!W12 -> 26628 | AB18: ='Raw Historical Financials'!Y12-'Raw Historical Financials'!X12 -> 46660 | AC18: ='Raw Historical Financials'!Z12-'Raw Historical Financials'!Y12 -> -178305.4 | AE18: =SUMIF($F$2:$AB$2,AE$2,$F18:$AB18) -> -32493 | AF18: =SUMIF($F$2:$AB$2,AF$2,$F18:$AB18) -> -17809 | AG18: =SUMIF($F$2:$AB$2,AG$2,$F18:$AB18) -> -229824 | AH18: =SUMIF($F$2:$AB$2,AH$2,$F18:$AB18) -> -77307 | AI18: =SUMIF($F$2:$AB$2,AI$2,$F18:$AB18) -> -38529 | AJ18: =SUMIF($F$2:$AC$2,AJ$2,$F18:$AC18) -> -79601.396
B19: Modification loss | F19: ='Raw Historical Financials'!C13 -> 0 | G19: ='Raw Historical Financials'!D13-'Raw Historical Financials'!C13 -> 0 | H19: ='Raw Historical Financials'!E13-'Raw Historical Financials'!D13 -> 0 | I19: ='Raw Historical Financials'!F13-'Raw Historical Financials'!E13 -> 0 | J19: ='Raw Historical Financials'!G13 -> 0 | K19: ='Raw Historical Financials'!H13-'Raw Historical Financials'!G13 -> 0 | L19: ='Raw Historical Financials'!I13-'Raw Historical Financials'!H13 -> 0 | M19: ='Raw Historical Financials'!J13-'Raw Historical Financials'!I13 -> 0 | N19: ='Raw Historical Financials'!K13 -> 0 | O19: ='Raw Historical Financials'!L13-'Raw Historical Financials'!K13 -> 0 | P19: ='Raw Historical Financials'!M13-'Raw Historical Financials'!L13 -> 0 | Q19: ='Raw Historical Financials'!N13-'Raw Historical Financials'!M13 -> 0 | R19: ='Raw Historical Financials'!O13 -> 0 | S19: ='Raw Historical Financials'!P13-'Raw Historical Financials'!O13 -> 0 | T19: ='Raw Historical Financials'!Q13-'Raw Historical Financials'!P13 -> 0 | U19: ='Raw Historical Financials'!R13-'Raw Historical Financials'!Q13 -> -289120 | V19: ='Raw Historical Financials'!S13 -> 0 | W19: ='Raw Historical Financials'!T13-'Raw Historical Financials'!S13 -> 0 | X19: ='Raw Historical Financials'!U13-'Raw Historical Financials'!T13 -> 0 | Y19: ='Raw Historical Financials'!V13-'Raw Historical Financials'!U13 -> 0 | Z19: ='Raw Historical Financials'!W13 -> 0 | AA19: ='Raw Historical Financials'!X13-'Raw Historical Financials'!W13 -> 0 | AB19: ='Raw Historical Financials'!Y13-'Raw Historical Financials'!X13 -> 0 | AC19: ='Raw Historical Financials'!Z13-'Raw Historical Financials'!Y13 -> 0 | AE19: =SUMIF($F$2:$AB$2,AE$2,$F19:$AB19) -> 0 | AF19: =SUMIF($F$2:$AB$2,AF$2,$F19:$AB19) -> 0 | AG19: =SUMIF($F$2:$AB$2,AG$2,$F19:$AB19) -> 0 | AH19: =SUMIF($F$2:$AB$2,AH$2,$F19:$AB19) -> -289120 | AI19: =SUMIF($F$2:$AB$2,AI$2,$F19:$AB19) -> 0 | AJ19: =SUMIF($F$2:$AC$2,AJ$2,$F19:$AC19) -> 0
B20: Personnel expenses | F20: ='Raw Historical Financials'!C14 -> -19294 | G20: ='Raw Historical Financials'!D14-'Raw Historical Financials'!C14 -> -19084 | H20: ='Raw Historical Financials'!E14-'Raw Historical Financials'!D14 -> -18328 | I20: ='Raw Historical Financials'!F14-'Raw Historical Financials'!E14 -> -17975 | J20: ='Raw Historical Financials'!G14 -> -17662 | K20: ='Raw Historical Financials'!H14-'Raw Historical Financials'!G14 -> -21659 | L20: ='Raw Historical Financials'!I14-'Raw Historical Financials'!H14 -> -22919 | M20: ='Raw Historical Financials'!J14-'Raw Historical Financials'!I14 -> -40493 | N20: ='Raw Historical Financials'!K14 -> -25734 | O20: ='Raw Historical Financials'!L14-'Raw Historical Financials'!K14 -> -25968 | P20: ='Raw Historical Financials'!M14-'Raw Historical Financials'!L14 -> -27183 | Q20: ='Raw Historical Financials'!N14-'Raw Historical Financials'!M14 -> -34062 | R20: ='Raw Historical Financials'!O14 -> -29760 | S20: ='Raw Historical Financials'!P14-'Raw Historical Financials'!O14 -> -38219 | T20: ='Raw Historical Financials'!Q14-'Raw Historical Financials'!P14 -> -32323 | U20: ='Raw Historical Financials'!R14-'Raw Historical Financials'!Q14 -> -45505 | V20: ='Raw Historical Financials'!S14 -> -43138 | W20: ='Raw Historical Financials'!T14-'Raw Historical Financials'!S14 -> -42885 | X20: ='Raw Historical Financials'!U14-'Raw Historical Financials'!T14 -> -43308 | Y20: ='Raw Historical Financials'!V14-'Raw Historical Financials'!U14 -> -127280 | Z20: ='Raw Historical Financials'!W14 -> -46453 | AA20: ='Raw Historical Financials'!X14-'Raw Historical Financials'!W14 -> -46755 | AB20: ='Raw Historical Financials'!Y14-'Raw Historical Financials'!X14 -> -46163 | AC20: ='Raw Historical Financials'!Z14-'Raw Historical Financials'!Y14 -> -119879.86 | AE20: =SUMIF($F$2:$AB$2,AE$2,$F20:$AB20) -> -74681 | AF20: =SUMIF($F$2:$AB$2,AF$2,$F20:$AB20) -> -102733 | AG20: =SUMIF($F$2:$AB$2,AG$2,$F20:$AB20) -> -112947 | AH20: =SUMIF($F$2:$AB$2,AH$2,$F20:$AB20) -> -145807 | AI20: =SUMIF($F$2:$AB$2,AI$2,$F20:$AB20) -> -256611 | AJ20: =SUMIF($F$2:$AC$2,AJ$2,$F20:$AC20) -> -259250.86
B21: Depreciation and amortisation | F21: ='Raw Historical Financials'!C15 -> -3877 | G21: ='Raw Historical Financials'!D15-'Raw Historical Financials'!C15 -> -6365 | H21: ='Raw Historical Financials'!E15-'Raw Historical Financials'!D15 -> -5098 | I21: ='Raw Historical Financials'!F15-'Raw Historical Financials'!E15 -> -5437 | J21: ='Raw Historical Financials'!G15 -> -5542 | K21: ='Raw Historical Financials'!H15-'Raw Historical Financials'!G15 -> -5433 | L21: ='Raw Historical Financials'!I15-'Raw Historical Financials'!H15 -> -5447 | M21: ='Raw Historical Financials'!J15-'Raw Historical Financials'!I15 -> -6601 | N21: ='Raw Historical Financials'!K15 -> -6701 | O21: ='Raw Historical Financials'!L15-'Raw Historical Financials'!K15 -> -6588 | P21: ='Raw Historical Financials'!M15-'Raw Historical Financials'!L15 -> -6464 | Q21: ='Raw Historical Financials'!N15-'Raw Historical Financials'!M15 -> -2540 | R21: ='Raw Historical Financials'!O15 -> -8291 | S21: ='Raw Historical Financials'!P15-'Raw Historical Financials'!O15 -> -8426 | T21: ='Raw Historical Financials'!Q15-'Raw Historical Financials'!P15 -> -8315 | U21: ='Raw Historical Financials'!R15-'Raw Historical Financials'!Q15 -> -7176 | V21: ='Raw Historical Financials'!S15 -> -11436 | W21: ='Raw Historical Financials'!T15-'Raw Historical Financials'!S15 -> -11476 | X21: ='Raw Historical Financials'!U15-'Raw Historical Financials'!T15 -> -12648 | Y21: ='Raw Historical Financials'!V15-'Raw Historical Financials'!U15 -> -9828 | Z21: ='Raw Historical Financials'!W15 -> -10964 | AA21: ='Raw Historical Financials'!X15-'Raw Historical Financials'!W15 -> -14660 | AB21: ='Raw Historical Financials'!Y15-'Raw Historical Financials'!X15 -> -15613 | AC21: ='Raw Historical Financials'!Z15-'Raw Historical Financials'!Y15 -> -18327.089 | AE21: =SUMIF($F$2:$AB$2,AE$2,$F21:$AB21) -> -20777 | AF21: =SUMIF($F$2:$AB$2,AF$2,$F21:$AB21) -> -23023 | AG21: =SUMIF($F$2:$AB$2,AG$2,$F21:$AB21) -> -22293 | AH21: =SUMIF($F$2:$AB$2,AH$2,$F21:$AB21) -> -32208 | AI21: =SUMIF($F$2:$AB$2,AI$2,$F21:$AB21) -> -45388 | AJ21: =SUMIF($F$2:$AC$2,AJ$2,$F21:$AC21) -> -59564.089
B22: Other expenses | F22: ='Raw Historical Financials'!C16 -> -22054 | G22: ='Raw Historical Financials'!D16-'Raw Historical Financials'!C16 -> -15064 | H22: ='Raw Historical Financials'!E16-'Raw Historical Financials'!D16 -> -19233 | I22: ='Raw Historical Financials'!F16-'Raw Historical Financials'!E16 -> -14494 | J22: ='Raw Historical Financials'!G16 -> -17027 | K22: ='Raw Historical Financials'!H16-'Raw Historical Financials'!G16 -> -18787 | L22: ='Raw Historical Financials'!I16-'Raw Historical Financials'!H16 -> -21074 | M22: ='Raw Historical Financials'!J16-'Raw Historical Financials'!I16 -> -31158 | N22: ='Raw Historical Financials'!K16 -> -26503 | O22: ='Raw Historical Financials'!L16-'Raw Historical Financials'!K16 -> -26430 | P22: ='Raw Historical Financials'!M16-'Raw Historical Financials'!L16 -> -33317 | Q22: ='Raw Historical Financials'!N16-'Raw Historical Financials'!M16 -> -40879 | R22: ='Raw Historical Financials'!O16 -> -33704 | S22: ='Raw Historical Financials'!P16-'Raw Historical Financials'!O16 -> -38860 | T22: ='Raw Historical Financials'!Q16-'Raw Historical Financials'!P16 -> -45748 | U22: ='Raw Historical Financials'!R16-'Raw Historical Financials'!Q16 -> -56795 | V22: ='Raw Historical Financials'!S16 -> -44770 | W22: ='Raw Historical Financials'!T16-'Raw Historical Financials'!S16 -> -42271 | X22: ='Raw Historical Financials'!U16-'Raw Historical Financials'!T16 -> -40200 | Y22: ='Raw Historical Financials'!V16-'Raw Historical Financials'!U16 -> -79890 | Z22: ='Raw Historical Financials'!W16 -> -56889 | AA22: ='Raw Historical Financials'!X16-'Raw Historical Financials'!W16 -> -61772 | AB22: ='Raw Historical Financials'!Y16-'Raw Historical Financials'!X16 -> -51147 | AC22: ='Raw Historical Financials'!Z16-'Raw Historical Financials'!Y16 -> -25698.955 | AE22: =SUMIF($F$2:$AB$2,AE$2,$F22:$AB22) -> -70845 | AF22: =SUMIF($F$2:$AB$2,AF$2,$F22:$AB22) -> -88046 | AG22: =SUMIF($F$2:$AB$2,AG$2,$F22:$AB22) -> -127129 | AH22: =SUMIF($F$2:$AB$2,AH$2,$F22:$AB22) -> -175107 | AI22: =SUMIF($F$2:$AB$2,AI$2,$F22:$AB22) -> -207131 | AJ22: =SUMIF($F$2:$AC$2,AJ$2,$F22:$AC22) -> -195506.95
B23: Finance cost on lease liability | F23: ='Raw Historical Financials'!C17 -> 0 | G23: ='Raw Historical Financials'!D17-'Raw Historical Financials'!C17 -> 0 | H23: ='Raw Historical Financials'!E17-'Raw Historical Financials'!D17 -> 0 | I23: ='Raw Historical Financials'!F17-'Raw Historical Financials'!E17 -> -3177 | J23: ='Raw Historical Financials'!G17 -> 0 | K23: ='Raw Historical Financials'!H17-'Raw Historical Financials'!G17 -> 0 | L23: ='Raw Historical Financials'!I17-'Raw Historical Financials'!H17 -> 0 | M23: ='Raw Historical Financials'!J17-'Raw Historical Financials'!I17 -> -3709 | N23: ='Raw Historical Financials'!K17 -> 0 | O23: ='Raw Historical Financials'!L17-'Raw Historical Financials'!K17 -> 0 | P23: ='Raw Historical Financials'!M17-'Raw Historical Financials'!L17 -> 0 | Q23: ='Raw Historical Financials'!N17-'Raw Historical Financials'!M17 -> -2738 | R23: ='Raw Historical Financials'!O17 -> 0 | S23: ='Raw Historical Financials'!P17-'Raw Historical Financials'!O17 -> 0 | T23: ='Raw Historical Financials'!Q17-'Raw Historical Financials'!P17 -> 0 | U23: ='Raw Historical Financials'!R17-'Raw Historical Financials'!Q17 -> -2364 | V23: ='Raw Historical Financials'!S17 -> 0 | W23: ='Raw Historical Financials'!T17-'Raw Historical Financials'!S17 -> 0 | X23: ='Raw Historical Financials'!U17-'Raw Historical Financials'!T17 -> 0 | Y23: ='Raw Historical Financials'!V17-'Raw Historical Financials'!U17 -> -6218 | Z23: ='Raw Historical Financials'!W17 -> -1464 | AA23: ='Raw Historical Financials'!X17-'Raw Historical Financials'!W17 -> -1168 | AB23: ='Raw Historical Financials'!Y17-'Raw Historical Financials'!X17 -> -3166 | AC23: ='Raw Historical Financials'!Z17-'Raw Historical Financials'!Y17 -> -416.745 | AE23: =SUMIF($F$2:$AB$2,AE$2,$F23:$AB23) -> -3177 | AF23: =SUMIF($F$2:$AB$2,AF$2,$F23:$AB23) -> -3709 | AG23: =SUMIF($F$2:$AB$2,AG$2,$F23:$AB23) -> -2738 | AH23: =SUMIF($F$2:$AB$2,AH$2,$F23:$AB23) -> -2364 | AI23: =SUMIF($F$2:$AB$2,AI$2,$F23:$AB23) -> -6218 | AJ23: =SUMIF($F$2:$AC$2,AJ$2,$F23:$AC23) -> -6214.745
B24: Merger related cost | F24: ='Raw Historical Financials'!C18 -> 0 | G24: ='Raw Historical Financials'!D18-'Raw Historical Financials'!C18 -> -1715 | H24: ='Raw Historical Financials'!E18-'Raw Historical Financials'!D18 -> 1715 | I24: ='Raw Historical Financials'!F18-'Raw Historical Financials'!E18 -> 0 | J24: ='Raw Historical Financials'!G18 -> 0 | K24: ='Raw Historical Financials'!H18-'Raw Historical Financials'!G18 -> 0 | L24: ='Raw Historical Financials'!I18-'Raw Historical Financials'!H18 -> 0 | M24: ='Raw Historical Financials'!J18-'Raw Historical Financials'!I18 -> 0 | N24: ='Raw Historical Financials'!K18 -> 0 | O24: ='Raw Historical Financials'!L18-'Raw Historical Financials'!K18 -> 0 | P24: ='Raw Historical Financials'!M18-'Raw Historical Financials'!L18 -> 0 | Q24: ='Raw Historical Financials'!N18-'Raw Historical Financials'!M18 -> 0 | R24: ='Raw Historical Financials'!O18 -> 0 | S24: ='Raw Historical Financials'!P18-'Raw Historical Financials'!O18 -> 0 | T24: ='Raw Historical Financials'!Q18-'Raw Historical Financials'!P18 -> 0 | U24: ='Raw Historical Financials'!R18-'Raw Historical Financials'!Q18 -> 0 | V24: ='Raw Historical Financials'!S18 -> 0 | W24: ='Raw Historical Financials'!T18-'Raw Historical Financials'!S18 -> 0 | X24: ='Raw Historical Financials'!U18-'Raw Historical Financials'!T18 -> 0 | Y24: ='Raw Historical Financials'!V18-'Raw Historical Financials'!U18 -> 0 | Z24: ='Raw Historical Financials'!W18 -> 0 | AA24: ='Raw Historical Financials'!X18-'Raw Historical Financials'!W18 -> 0 | AB24: ='Raw Historical Financials'!Y18-'Raw Historical Financials'!X18 -> 0 | AC24: ='Raw Historical Financials'!Z18-'Raw Historical Financials'!Y18 -> 0 | AE24: =SUMIF($F$2:$AB$2,AE$2,$F24:$AB24) -> 0 | AF24: =SUMIF($F$2:$AB$2,AF$2,$F24:$AB24) -> 0 | AG24: =SUMIF($F$2:$AB$2,AG$2,$F24:$AB24) -> 0 | AH24: =SUMIF($F$2:$AB$2,AH$2,$F24:$AB24) -> 0 | AI24: =SUMIF($F$2:$AB$2,AI$2,$F24:$AB24) -> 0 | AJ24: =SUMIF($F$2:$AC$2,AJ$2,$F24:$AC24) -> 0
B25: Total Operating Expenses | F25: =SUM(F18:F24) -> -52225 | G25: =SUM(G18:G24) -> -51374 | H25: =SUM(H18:H24) -> -49891 | I25: =SUM(I18:I24) -> -48483 | J25: =SUM(J18:J24) -> -47849 | K25: =SUM(K18:K24) -> -46467 | L25: =SUM(L18:L24) -> -49969 | M25: =SUM(M18:M24) -> -91035 | ... AC25: =SUM(AC18:AC24) -> -342628.05 | AE25: =SUM(AE18:AE24) -> -201973 | AF25: =SUM(AF18:AF24) -> -235320 | AG25: =SUM(AG18:AG24) -> -494931 | AH25: =SUM(AH18:AH24) -> -721913 | AI25: =SUM(AI18:AI24) -> -553877 | AJ25: =SUM(AJ18:AJ24) -> -600138.05
B26: Share of profit from associate company | F26: ='Raw Historical Financials'!C19 -> 0 | G26: ='Raw Historical Financials'!D19-'Raw Historical Financials'!C19 -> 0 | H26: ='Raw Historical Financials'!E19-'Raw Historical Financials'!D19 -> 0 | I26: ='Raw Historical Financials'!F19-'Raw Historical Financials'!E19 -> 94 | J26: ='Raw Historical Financials'!G19 -> 0 | K26: ='Raw Historical Financials'!H19-'Raw Historical Financials'!G19 -> 0 | L26: ='Raw Historical Financials'!I19-'Raw Historical Financials'!H19 -> 0 | M26: ='Raw Historical Financials'!J19-'Raw Historical Financials'!I19 -> 227 | N26: ='Raw Historical Financials'!K19 -> 0 | O26: ='Raw Historical Financials'!L19-'Raw Historical Financials'!K19 -> 0 | P26: ='Raw Historical Financials'!M19-'Raw Historical Financials'!L19 -> 0 | Q26: ='Raw Historical Financials'!N19-'Raw Historical Financials'!M19 -> 299 | R26: ='Raw Historical Financials'!O19 -> 0 | S26: ='Raw Historical Financials'!P19-'Raw Historical Financials'!O19 -> 0 | T26: ='Raw Historical Financials'!Q19-'Raw Historical Financials'!P19 -> 0 | U26: ='Raw Historical Financials'!R19-'Raw Historical Financials'!Q19 -> 230 | V26: ='Raw Historical Financials'!S19 -> 0 | W26: ='Raw Historical Financials'!T19-'Raw Historical Financials'!S19 -> 0 | X26: ='Raw Historical Financials'!U19-'Raw Historical Financials'!T19 -> 0 | Y26: ='Raw Historical Financials'!V19-'Raw Historical Financials'!U19 -> 377 | Z26: ='Raw Historical Financials'!W19 -> 0 | AA26: ='Raw Historical Financials'!X19-'Raw Historical Financials'!W19 -> 0 | AB26: ='Raw Historical Financials'!Y19-'Raw Historical Financials'!X19 -> 422 | AC26: ='Raw Historical Financials'!Z19-'Raw Historical Financials'!Y19 -> 295.116 | AE26: =SUMIF($F$2:$AB$2,AE$2,$F26:$AB26) -> 94 | AF26: =SUMIF($F$2:$AB$2,AF$2,$F26:$AB26) -> 227 | AG26: =SUMIF($F$2:$AB$2,AG$2,$F26:$AB26) -> 299 | AH26: =SUMIF($F$2:$AB$2,AH$2,$F26:$AB26) -> 230 | AI26: =SUMIF($F$2:$AB$2,AI$2,$F26:$AB26) -> 377 | AJ26: =SUMIF($F$2:$AC$2,AJ$2,$F26:$AC26) -> 717.116
B27: Profit before income tax | F27: =SUM(F17,F25:F26) -> 20671 | G27: =SUM(G17,G25:G26) -> 24500 | H27: =SUM(H17,H25:H26) -> 27120 | I27: =SUM(I17,I25:I26) -> 30495 | J27: =SUM(J17,J25:J26) -> 31095 | K27: =SUM(K17,K25:K26) -> 35387 | L27: =SUM(L17,L25:L26) -> 40839 | M27: =SUM(M17,M25:M26) -> 48530 | ... AC27: =SUM(AC17,AC25:AC26) -> 331289.45 | AE27: =SUM(AE17,AE25:AE26) -> 102786 | AF27: =SUM(AF17,AF25:AF26) -> 155851 | AG27: =SUM(AG17,AG25:AG26) -> 21955 | AH27: =SUM(AH17,AH25:AH26) -> 323342 | AI27: =SUM(AI17,AI25:AI26) -> 539302 | AJ27: =SUM(AJ17,AJ25:AJ26) -> 702994.45
B28: Income tax expense | F28: ='Raw Historical Financials'!C21 -> -5168 | G28: ='Raw Historical Financials'!D21-'Raw Historical Financials'!C21 -> -6125 | H28: ='Raw Historical Financials'!E21-'Raw Historical Financials'!D21 -> -6780 | I28: ='Raw Historical Financials'!F21-'Raw Historical Financials'!E21 -> 6239 | J28: ='Raw Historical Financials'!G21 -> -7774 | K28: ='Raw Historical Financials'!H21-'Raw Historical Financials'!G21 -> -8847 | L28: ='Raw Historical Financials'!I21-'Raw Historical Financials'!H21 -> 1930 | M28: ='Raw Historical Financials'!J21-'Raw Historical Financials'!I21 -> -11165 | N28: ='Raw Historical Financials'!K21 -> -10187 | O28: ='Raw Historical Financials'!L21-'Raw Historical Financials'!K21 -> -10494 | P28: ='Raw Historical Financials'!M21-'Raw Historical Financials'!L21 -> -8757 | Q28: ='Raw Historical Financials'!N21-'Raw Historical Financials'!M21 -> 9492 | R28: ='Raw Historical Financials'!O21 -> -17362 | S28: ='Raw Historical Financials'!P21-'Raw Historical Financials'!O21 -> -15246 | T28: ='Raw Historical Financials'!Q21-'Raw Historical Financials'!P21 -> -19340 | U28: ='Raw Historical Financials'!R21-'Raw Historical Financials'!Q21 -> 51841 | V28: ='Raw Historical Financials'!S21 -> -24064 | W28: ='Raw Historical Financials'!T21-'Raw Historical Financials'!S21 -> -20914 | X28: ='Raw Historical Financials'!U21-'Raw Historical Financials'!T21 -> -8236 | Y28: ='Raw Historical Financials'!V21-'Raw Historical Financials'!U21 -> -95505 | Z28: ='Raw Historical Financials'!W21 -> -30199 | AA28: ='Raw Historical Financials'!X21-'Raw Historical Financials'!W21 -> -24030 | AB28: ='Raw Historical Financials'!Y21-'Raw Historical Financials'!X21 -> -27546 | AC28: ='Raw Historical Financials'!Z21-'Raw Historical Financials'!Y21 -> -68002.631 | AE28: =SUMIF($F$2:$AB$2,AE$2,$F28:$AB28) -> -11834 | AF28: =SUMIF($F$2:$AB$2,AF$2,$F28:$AB28) -> -25856 | AG28: =SUMIF($F$2:$AB$2,AG$2,$F28:$AB28) -> -19946 | AH28: =SUMIF($F$2:$AB$2,AH$2,$F28:$AB28) -> -107 | AI28: =SUMIF($F$2:$AB$2,AI$2,$F28:$AB28) -> -148719 | AJ28: =SUMIF($F$2:$AC$2,AJ$2,$F28:$AC28) -> -149777.63
B29: National stabilisation levy | F29: ='Raw Historical Financials'!C22 -> -1034 | G29: ='Raw Historical Financials'!D22-'Raw Historical Financials'!C22 -> -1225 | H29: ='Raw Historical Financials'!E22-'Raw Historical Financials'!D22 -> -1356 | I29: ='Raw Historical Financials'!F22-'Raw Historical Financials'!E22 -> -1524 | J29: ='Raw Historical Financials'!G22 -> -1554 | K29: ='Raw Historical Financials'!H22-'Raw Historical Financials'!G22 -> -1770 | L29: ='Raw Historical Financials'!I22-'Raw Historical Financials'!H22 -> -2042 | M29: ='Raw Historical Financials'!J22-'Raw Historical Financials'!I22 -> -2427 | N29: ='Raw Historical Financials'!K22 -> -1600 | O29: ='Raw Historical Financials'!L22-'Raw Historical Financials'!K22 -> -1678 | P29: ='Raw Historical Financials'!M22-'Raw Historical Financials'!L22 -> -2771 | Q29: ='Raw Historical Financials'!N22-'Raw Historical Financials'!M22 -> 6049 | R29: ='Raw Historical Financials'!O22 -> 0 | S29: ='Raw Historical Financials'!P22-'Raw Historical Financials'!O22 -> 0 | T29: ='Raw Historical Financials'!Q22-'Raw Historical Financials'!P22 -> 0 | U29: ='Raw Historical Financials'!R22-'Raw Historical Financials'!Q22 -> 0 | V29: ='Raw Historical Financials'!S22 -> 0 | W29: ='Raw Historical Financials'!T22-'Raw Historical Financials'!S22 -> 0 | X29: ='Raw Historical Financials'!U22-'Raw Historical Financials'!T22 -> 0 | Y29: ='Raw Historical Financials'!V22-'Raw Historical Financials'!U22 -> 0 | Z29: ='Raw Historical Financials'!W22 -> 0 | AA29: ='Raw Historical Financials'!X22-'Raw Historical Financials'!W22 -> 0 | AB29: ='Raw Historical Financials'!Y22-'Raw Historical Financials'!X22 -> -18585 | AC29: ='Raw Historical Financials'!Z22-'Raw Historical Financials'!Y22 -> -16564.655 | AE29: =SUMIF($F$2:$AB$2,AE$2,$F29:$AB29) -> -5139 | AF29: =SUMIF($F$2:$AB$2,AF$2,$F29:$AB29) -> -7793 | AG29: =SUMIF($F$2:$AB$2,AG$2,$F29:$AB29) -> 0 | AH29: =SUMIF($F$2:$AB$2,AH$2,$F29:$AB29) -> 0 | AI29: =SUMIF($F$2:$AB$2,AI$2,$F29:$AB29) -> 0 | AJ29: =SUMIF($F$2:$AC$2,AJ$2,$F29:$AC29) -> -35149.655
B30: Growth and Sustainability levy | F30: ='Raw Historical Financials'!C23 -> 0 | G30: ='Raw Historical Financials'!D23-'Raw Historical Financials'!C23 -> 0 | H30: ='Raw Historical Financials'!E23-'Raw Historical Financials'!D23 -> 0 | I30: ='Raw Historical Financials'!F23-'Raw Historical Financials'!E23 -> 0 | J30: ='Raw Historical Financials'!G23 -> 0 | K30: ='Raw Historical Financials'!H23-'Raw Historical Financials'!G23 -> 0 | L30: ='Raw Historical Financials'!I23-'Raw Historical Financials'!H23 -> 0 | M30: ='Raw Historical Financials'!J23-'Raw Historical Financials'!I23 -> 0 | N30: ='Raw Historical Financials'!K23 -> 0 | O30: ='Raw Historical Financials'!L23-'Raw Historical Financials'!K23 -> 0 | P30: ='Raw Historical Financials'!M23-'Raw Historical Financials'!L23 -> 0 | Q30: ='Raw Historical Financials'!N23-'Raw Historical Financials'!M23 -> -1083 | R30: ='Raw Historical Financials'!O23 -> -3503 | S30: ='Raw Historical Financials'!P23-'Raw Historical Financials'!O23 -> -3466 | T30: ='Raw Historical Financials'!Q23-'Raw Historical Financials'!P23 -> -3193 | U30: ='Raw Historical Financials'!R23-'Raw Historical Financials'!Q23 -> -6005 | V30: ='Raw Historical Financials'!S23 -> -4554 | W30: ='Raw Historical Financials'!T23-'Raw Historical Financials'!S23 -> -4182 | X30: ='Raw Historical Financials'!U23-'Raw Historical Financials'!T23 -> -1648 | Y30: ='Raw Historical Financials'!V23-'Raw Historical Financials'!U23 -> -16568 | Z30: ='Raw Historical Financials'!W23 -> -6040 | AA30: ='Raw Historical Financials'!X23-'Raw Historical Financials'!W23 -> -4806 | AB30: ='Raw Historical Financials'!Y23-'Raw Historical Financials'!X23 -> 10846 | AC30: ='Raw Historical Financials'!Z23-'Raw Historical Financials'!Y23 -> -35196.104 | AE30: =SUMIF($F$2:$AB$2,AE$2,$F30:$AB30) -> 0 | AF30: =SUMIF($F$2:$AB$2,AF$2,$F30:$AB30) -> 0 | AG30: =SUMIF($F$2:$AB$2,AG$2,$F30:$AB30) -> -1083 | AH30: =SUMIF($F$2:$AB$2,AH$2,$F30:$AB30) -> -16167 | AI30: =SUMIF($F$2:$AB$2,AI$2,$F30:$AB30) -> -26952 | AJ30: =SUMIF($F$2:$AC$2,AJ$2,$F30:$AC30) -> -35196.104
B31: Financial sector recovery levy | F31: ='Raw Historical Financials'!C24 -> 0 | G31: ='Raw Historical Financials'!D24-'Raw Historical Financials'!C24 -> 0 | H31: ='Raw Historical Financials'!E24-'Raw Historical Financials'!D24 -> 0 | I31: ='Raw Historical Financials'!F24-'Raw Historical Financials'!E24 -> 0 | J31: ='Raw Historical Financials'!G24 -> 0 | K31: ='Raw Historical Financials'!H24-'Raw Historical Financials'!G24 -> 0 | L31: ='Raw Historical Financials'!I24-'Raw Historical Financials'!H24 -> -4025 | M31: ='Raw Historical Financials'!J24-'Raw Historical Financials'!I24 -> -1819 | N31: ='Raw Historical Financials'!K24 -> -1600 | O31: ='Raw Historical Financials'!L24-'Raw Historical Financials'!K24 -> -1678 | P31: ='Raw Historical Financials'!M24-'Raw Historical Financials'!L24 -> -2771 | Q31: ='Raw Historical Financials'!N24-'Raw Historical Financials'!M24 -> 4966 | R31: ='Raw Historical Financials'!O24 -> -3503 | S31: ='Raw Historical Financials'!P24-'Raw Historical Financials'!O24 -> -3466 | T31: ='Raw Historical Financials'!Q24-'Raw Historical Financials'!P24 -> -3193 | U31: ='Raw Historical Financials'!R24-'Raw Historical Financials'!Q24 -> -6005 | V31: ='Raw Historical Financials'!S24 -> -4554 | W31: ='Raw Historical Financials'!T24-'Raw Historical Financials'!S24 -> -4182 | X31: ='Raw Historical Financials'!U24-'Raw Historical Financials'!T24 -> -1648 | Y31: ='Raw Historical Financials'!V24-'Raw Historical Financials'!U24 -> -16568 | Z31: ='Raw Historical Financials'!W24 -> -6040 | AA31: ='Raw Historical Financials'!X24-'Raw Historical Financials'!W24 -> -4806 | AB31: ='Raw Historical Financials'!Y24-'Raw Historical Financials'!X24 -> -7739 | AC31: ='Raw Historical Financials'!Z24-'Raw Historical Financials'!Y24 -> 18585 | AE31: =SUMIF($F$2:$AB$2,AE$2,$F31:$AB31) -> 0 | AF31: =SUMIF($F$2:$AB$2,AF$2,$F31:$AB31) -> -5844 | AG31: =SUMIF($F$2:$AB$2,AG$2,$F31:$AB31) -> -1083 | AH31: =SUMIF($F$2:$AB$2,AH$2,$F31:$AB31) -> -16167 | AI31: =SUMIF($F$2:$AB$2,AI$2,$F31:$AB31) -> -26952 | AJ31: =SUMIF($F$2:$AC$2,AJ$2,$F31:$AC31) -> 0
B32: Profit for the period | F32: =SUM(F27:F31) -> 14469 | G32: =SUM(G27:G31) -> 17150 | H32: =SUM(H27:H31) -> 18984 | I32: =SUM(I27:I31) -> 35210 | J32: =SUM(J27:J31) -> 21767 | K32: =SUM(K27:K31) -> 24770 | L32: =SUM(L27:L31) -> 36702 | M32: =SUM(M27:M31) -> 33119 | ... AC32: =SUM(AC27:AC31) -> 230111.06 | AE32: =SUM(AE27:AE31) -> 85813 | AF32: =SUM(AF27:AF31) -> 116358 | AG32: =SUM(AG27:AG31) -> -157 | AH32: =SUM(AH27:AH31) -> 290901 | AI32: =SUM(AI27:AI31) -> 336679 | AJ32: =SUM(AJ27:AJ31) -> 482871.06
B34: Shares Outstanding | F34: 322291.25 | G34: 322291.25 | H34: 322291.25 | I34: 322291.25 | J34: 334173.89 | K34: 334173.89 | L34: 334173.89 | M34: 334173.89 | N34: 334173.89 | O34: 334173.89 | P34: 334173.89 | Q34: 334173.89 | R34: 334173.89 | S34: 334173.89 | T34: 334173.89 | U34: 334173.89 | V34: 334173.89 | W34: 334173.89 | X34: 334173.89 | Y34: 334173.89 | Z34: 349617.46 | AA34: 349617.46 | AB34: 349617.46 | AC34: 349618.46 | AE34: =I34 -> 322291.25 | AF34: =M34 -> 334173.89 | AG34: =Q34 -> 334173.89 | AH34: =U34 -> 334173.89 | AI34: =Y34 -> 334173.89 | AJ34: =AB34 -> 349617.46
B35: EPS | F35: =F32/F34 -> 0.044894175 | G35: =G32/G34 -> 0.053212738 | H35: =H32/H34 -> 0.058903243 | I35: =I32/I34 -> 0.10924901 | J35: =J32/J34 -> 0.065136746 | K35: =K32/K34 -> 0.074123085 | L35: =L32/L34 -> 0.10982905 | M35: =M32/M34 -> 0.099107084 | ... AC35: =AC32/AC34 -> 0.65817767 | AE35: =AE32/AE34 -> 0.26625917 | AF35: =AF32/AF34 -> 0.34819596 | AG35: =AG32/AG34 -> -0.00046981528 | AH35: =AH32/AH34 -> 0.87050786 | AI35: =AI32/AI34 -> 1.0074964 | AJ35: =AJ32/AJ34 -> 1.3811412
B38: Statement of Financial Position
B40: Assets
B41: Cash and cash equivalents | F41: ='Raw Historical Financials'!C36 -> 664482 | G41: ='Raw Historical Financials'!D36 -> 553668 | H41: ='Raw Historical Financials'!E36 -> 688100 | I41: ='Raw Historical Financials'!F36 -> 771158 | J41: ='Raw Historical Financials'!G36 -> 702206 | K41: ='Raw Historical Financials'!H36 -> 604605 | L41: ='Raw Historical Financials'!I36 -> 718939 | M41: ='Raw Historical Financials'!J36 -> 961689 | ... AC41: ='Raw Historical Financials'!Z36 -> 8104418.8 | AE41: =I41 -> 771158 | AF41: =M41 -> 961689 | AG41: =Q41 -> 1990143 | AH41: =U41 -> 3226881 | AI41: =Y41 -> 4600045 | AJ41: =AC41 -> 8104418.8
B42: ='Raw Historical Financials'!B37 -> Placements with banks | F42: ='Raw Historical Financials'!C37 -> 0 | G42: ='Raw Historical Financials'!D37 -> 0 | H42: ='Raw Historical Financials'!E37 -> 0 | I42: ='Raw Historical Financials'!F37 -> 0 | J42: ='Raw Historical Financials'!G37 -> 0 | K42: ='Raw Historical Financials'!H37 -> 0 | L42: ='Raw Historical Financials'!I37 -> 0 | M42: ='Raw Historical Financials'!J37 -> 0 | ... AC42: ='Raw Historical Financials'!Z37 -> 58041.704 | AE42: =I42 -> 0 | AF42: =M42 -> 0 | AG42: =Q42 -> 0 | AH42: =U42 -> 0 | AI42: =Y42 -> 0 | AJ42: =AC42 -> 58041.704
B43: Trading assets (Investment securities) | F43: ='Raw Historical Financials'!C38 -> 841803 | G43: ='Raw Historical Financials'!D38 -> 1121649 | H43: ='Raw Historical Financials'!E38 -> 1085506 | I43: ='Raw Historical Financials'!F38 -> 857232 | J43: ='Raw Historical Financials'!G38 -> 1182364 | K43: ='Raw Historical Financials'!H38 -> 1384113 | L43: ='Raw Historical Financials'!I38 -> 1392672 | M43: ='Raw Historical Financials'!J38 -> 820239 | ... AC43: ='Raw Historical Financials'!Z38 -> 3178870.4 | AE43: =I43 -> 857232 | AF43: =M43 -> 820239 | AG43: =Q43 -> 1661135 | AH43: =U43 -> 2059376 | AI43: =Y43 -> 2647258 | AJ43: =AC43 -> 3178870.4
